Workbook
Name RentangBernama1: #REF!

Sheet 🙎‍♂️ Pasien
A1: . | B1: Timestamp | D1: Tanggal | E1: BULAN | F1: TAHUN | G1: Nama Pasien | H1: No. RM | I1: Usia | J1: Kategori Usia | K1: Tanggal Lahir | L1: Jenis Kelamin | M1: Alamat | N1: Kelurahan/Desa | O1: Kecamatan | P1: Kabupaten/Kota | Q1: Provinsi | R1: Agama | S1: Pekerjaan | T1: Keluhan | U1: Hobi/Aktivitas Sehari-hari | V1: No. HP/WhatsApp
A2: =IFERROR(__xludf.DUMMYFUNCTION("IMPORTRANGE(""https://docs.google.com/spreadsheets/d/1q5irXBuyRkQM_goHlRjPTSwHk1on6thK70p8lljqLrs/edit?gid=1342096879#gid=1342096879"",""🙎‍♂️ Pasien!A2:W"")"),"") | B2: =IFERROR(__xludf.DUMMYFUNCTION("""COMPUTED_VALUE"""),"Timestamp") -> Timestamp | D2: =IFERROR(__xludf.DUMMYFUNCTION("""COMPUTED_VALUE"""),"Tanggal") -> Tanggal | E2: =IFERROR(__xludf.DUMMYFUNCTION("""COMPUTED_VALUE"""),"Bulan") -> Bulan | F2: =IFERROR(__xludf.DUMMYFUNCTION("""COMPUTED_VALUE"""),"Tahun") -> Tahun | G2: =IFERROR(__xludf.DUMMYFUNCTION("""COMPUTED_VALUE"""),"Nama Pasien") -> Nama Pasien | H2: =IFERROR(__xludf.DUMMYFUNCTION("""COMPUTED_VALUE"""),"No. RM") -> No. RM | I2: =IFERROR(__xludf.DUMMYFUNCTION("""COMPUTED_VALUE"""),"Usia") -> Usia | J2: =IFERROR(__xludf.DUMMYFUNCTION("""COMPUTED_VALUE"""),"Kategori Usia") -> Kategori Usia | K2: =IFERROR(__xludf.DUMMYFUNCTION("""COMPUTED_VALUE"""),"Tanggal Lahir") -> Tanggal Lahir | L2: =IFERROR(__xludf.DUMMYFUNCTION("""COMPUTED_VALUE"""),"Jenis Kelamin") -> Jenis Kelamin | M2: =IFERROR(__xludf.DUMMYFUNCTION("""COMPUTED_VALUE"""),"Alamat") -> Alamat | N2: =IFERROR(__xludf.DUMMYFUNCTION("""COMPUTED_VALUE"""),"Kel./Desa") -> Kel./Desa | O2: =IFERROR(__xludf.DUMMYFUNCTION("""COMPUTED_VALUE"""),"Kecamatan") -> Kecamatan | P2: =IFERROR(__xludf.DUMMYFUNCTION("""COMPUTED_VALUE"""),"Kab./Kota") -> Kab./Kota | Q2: =IFERROR(__xludf.DUMMYFUNCTION("""COMPUTED_VALUE"""),"Provinsi") -> Provinsi | R2: =IFERROR(__xludf.DUMMYFUNCTION("""COMPUTED_VALUE"""),"Agama") -> Agama | S2: =IFERROR(__xludf.DUMMYFUNCTION("""COMPUTED_VALUE"""),"Pekerjaan") -> Pekerjaan | T2: =IFERROR(__xludf.DUMMYFUNCTION("""COMPUTED_VALUE"""),"Keluhan") -> Keluhan | U2: =IFERROR(__xludf.DUMMYFUNCTION("""COMPUTED_VALUE"""),"Hobi/Aktivitas Sehari-hari") -> Hobi/Aktivitas Sehari-hari | V2: =IFERROR(__xludf.DUMMYFUNCTION("""COMPUTED_VALUE"""),"No. WA") -> No. WA | W2: =IFERROR(__xludf.DUMMYFUNCTION("""COMPUTED_VALUE"""),"Column 1") -> Column 1
F3: =IFERROR(__xludf.DUMMYFUNCTION("""COMPUTED_VALUE"""),"1899") -> 1899 | G3: =IFERROR(__xludf.DUMMYFUNCTION("""COMPUTED_VALUE"""),"OFF") -> OFF | H3: =IFERROR(__xludf.DUMMYFUNCTION("""COMPUTED_VALUE"""),"OFF") -> OFF
F4: =IFERROR(__xludf.DUMMYFUNCTION("""COMPUTED_VALUE"""),"1899") -> 1899 | G4: =IFERROR(__xludf.DUMMYFUNCTION("""COMPUTED_VALUE"""),"LIBUR") -> LIBUR | H4: =IFERROR(__xludf.DUMMYFUNCTION("""COMPUTED_VALUE"""),"LIBUR") -> LIBUR
F5: =IFERROR(__xludf.DUMMYFUNCTION("""COMPUTED_VALUE"""),"1899") -> 1899 | G5: =IFERROR(__xludf.DUMMYFUNCTION("""COMPUTED_VALUE"""),"TA") -> TA
F6: =IFERROR(__xludf.DUMMYFUNCTION("""COMPUTED_VALUE"""),"1899") -> 1899 | G6: =IFERROR(__xludf.DUMMYFUNCTION("""COMPUTED_VALUE"""),"MANAJEMEN") -> MANAJEMEN | H6: =IFERROR(__xludf.DUMMYFUNCTION("""COMPUTED_VALUE"""),"MANAJEMEN") -> MANAJEMEN
F7: =IFERROR(__xludf.DUMMYFUNCTION("""COMPUTED_VALUE"""),"1899") -> 1899 | G7: =IFERROR(__xludf.DUMMYFUNCTION("""COMPUTED_VALUE"""),"KHUSUS") -> KHUSUS | H7: =IFERROR(__xludf.DUMMYFUNCTION("""COMPUTED_VALUE"""),"KHUSUS") -> KHUSUS
F8: =IFERROR(__xludf.DUMMYFUNCTION("""COMPUTED_VALUE"""),"1899") -> 1899 | G8: =IFERROR(__xludf.DUMMYFUNCTION("""COMPUTED_VALUE"""),"PIPO") -> PIPO | H8: =IFERROR(__xludf.DUMMYFUNCTION("""COMPUTED_VALUE"""),"PANGSUMA FC") -> PANGSUMA FC
E9: =IFERROR(__xludf.DUMMYFUNCTION("""COMPUTED_VALUE"""),"") | F9: =IFERROR(__xludf.DUMMYFUNCTION("""COMPUTED_VALUE"""),"1899") -> 1899 | H9: =IFERROR(__xludf.DUMMYFUNCTION("""COMPUTED_VALUE"""),"") | I9: =IFERROR(__xludf.DUMMYFUNCTION("""COMPUTED_VALUE"""),"") | J9: =IFERROR(__xludf.DUMMYFUNCTION("""COMPUTED_VALUE"""),"")
B10: =IFERROR(__xludf.DUMMYFUNCTION("""COMPUTED_VALUE"""),45006.90524418982) -> 45006.905 | D10: =IFERROR(__xludf.DUMMYFUNCTION("""COMPUTED_VALUE"""),44856.83403935185) -> 44856.834 | E10: =IFERROR(__xludf.DUMMYFUNCTION("""COMPUTED_VALUE"""),"10Okt") -> 10Okt | F10: =IFERROR(__xludf.DUMMYFUNCTION("""COMPUTED_VALUE"""),"2022") -> 2022 | G10: =IFERROR(__xludf.DUMMYFUNCTION("""COMPUTED_VALUE"""),"ZHOFRAN FARRAS ATAYA") -> ZHOFRAN FARRAS ATAYA | H10: =IFERROR(__xludf.DUMMYFUNCTION("""COMPUTED_VALUE"""),"Z0922105765") -> Z0922105765 | I10: =IFERROR(__xludf.DUMMYFUNCTION("""COMPUTED_VALUE"""),17.0) -> 17 | J10: =IFERROR(__xludf.DUMMYFUNCTION("""COMPUTED_VALUE"""),"< 18 tahun") -> < 18 tahun | K10: =IFERROR(__xludf.DUMMYFUNCTION("""COMPUTED_VALUE"""),39833.0) -> 39833 | L10: =IFERROR(__xludf.DUMMYFUNCTION("""COMPUTED_VALUE"""),"LAKI-LAKI") -> LAKI-LAKI | M10: =IFERROR(__xludf.DUMMYFUNCTION("""COMPUTED_VALUE"""),"JL. PARIT H. MUKSIN KOMP. PERMATA HIJAU") -> JL. PARIT H. MUKSIN KOMP. PERMATA HIJAU | N10: =IFERROR(__xludf.DUMMYFUNCTION("""COMPUTED_VALUE"""),"") | R10: =IFERROR(__xludf.DUMMYFUNCTION("""COMPUTED_VALUE"""),"ISLAM") -> ISLAM | S10: =IFERROR(__xludf.DUMMYFUNCTION("""COMPUTED_VALUE"""),"PELAJAR/MAHASISWA") -> PELAJAR/MAHASISWA | T10: =IFERROR(__xludf.DUMMYFUNCTION("""COMPUTED_VALUE"""),"SIKU - LENGAN BAWAH") -> SIKU - LENGAN BAWAH | U10: =IFERROR(__xludf.DUMMYFUNCTION("""COMPUTED_VALUE"""),"") | V10: =IFERROR(__xludf.DUMMYFUNCTION("""COMPUTED_VALUE"""),"082149675765") -> 082149675765
B11: =IFERROR(__xludf.DUMMYFUNCTION("""COMPUTED_VALUE"""),45006.90415178241) -> 45006.904 | D11: =IFERROR(__xludf.DUMMYFUNCTION("""COMPUTED_VALUE"""),44857.73925293981) -> 44857.739 | E11: =IFERROR(__xludf.DUMMYFUNCTION("""COMPUTED_VALUE"""),"10Okt") -> 10Okt | F11: =IFERROR(__xludf.DUMMYFUNCTION("""COMPUTED_VALUE"""),"2022") -> 2022 | G11: =IFERROR(__xludf.DUMMYFUNCTION("""COMPUTED_VALUE"""),"DIAH SUCI RINI") -> DIAH SUCI RINI | H11: =IFERROR(__xludf.DUMMYFUNCTION("""COMPUTED_VALUE"""),"D5722102445") -> D5722102445 | I11: =IFERROR(__xludf.DUMMYFUNCTION("""COMPUTED_VALUE"""),68.0) -> 68 | J11: =IFERROR(__xludf.DUMMYFUNCTION("""COMPUTED_VALUE"""),"> 44 tahun") -> > 44 tahun | K11: =IFERROR(__xludf.DUMMYFUNCTION("""COMPUTED_VALUE"""),21049.0) -> 21049 | L11: =IFERROR(__xludf.DUMMYFUNCTION("""COMPUTED_VALUE"""),"PEREMPUAN") -> PEREMPUAN | M11: =IFERROR(__xludf.DUMMYFUNCTION("""COMPUTED_VALUE"""),"JL. BERSAMA GG. BERSAMA") -> JL. BERSAMA GG. BERSAMA | R11: =IFERROR(__xludf.DUMMYFUNCTION("""COMPUTED_VALUE"""),"ISLAM") -> ISLAM | S11: =IFERROR(__xludf.DUMMYFUNCTION("""COMPUTED_VALUE"""),"PENSIUN") -> PENSIUN | T11: =IFERROR(__xludf.DUMMYFUNCTION("""COMPUTED_VALUE"""),"TULANG BELAKANG") -> TULANG BELAKANG | U11: =IFERROR(__xludf.DUMMYFUNCTION("""COMPUTED_VALUE"""),"") | V11: =IFERROR(__xludf.DUMMYFUNCTION("""COMPUTED_VALUE"""),"082158402445") -> 082158402445
B12: =IFERROR(__xludf.DUMMYFUNCTION("""COMPUTED_VALUE"""),45006.96855240741) -> 45006.969 | D12: =IFERROR(__xludf.DUMMYFUNCTION("""COMPUTED_VALUE"""),44921.725439814814) -> 44921.725 | E12: =IFERROR(__xludf.DUMMYFUNCTION("""COMPUTED_VALUE"""),"12Des") -> 12Des | F12: =IFERROR(__xludf.DUMMYFUNCTION("""COMPUTED_VALUE"""),"2022") -> 2022 | G12: =IFERROR(__xludf.DUMMYFUNCTION("""COMPUTED_VALUE"""),"MEIZARANI HELJA") -> MEIZARANI HELJA | H12: =IFERROR(__xludf.DUMMYFUNCTION("""COMPUTED_VALUE"""),"M9322128010") -> M9322128010 | I12: =IFERROR(__xludf.DUMMYFUNCTION("""COMPUTED_VALUE"""),33.0) -> 33 | J12: =IFERROR(__xludf.DUMMYFUNCTION("""COMPUTED_VALUE"""),"25-34 tahun") -> 25-34 tahun | K12: =IFERROR(__xludf.DUMMYFUNCTION("""COMPUTED_VALUE"""),34100.0) -> 34100 | L12: =IFERROR(__xludf.DUMMYFUNCTION("""COMPUTED_VALUE"""),"PEREMPUAN") -> PEREMPUAN | M12: =IFERROR(__xludf.DUMMYFUNCTION("""COMPUTED_VALUE"""),"JL. KOMYOS SOEDARSO GG, SAMBAS") -> JL. KOMYOS SOEDARSO GG, SAMBAS | R12: =IFERROR(__xludf.DUMMYFUNCTION("""COMPUTED_VALUE"""),"ISLAM") -> ISLAM | S12: =IFERROR(__xludf.DUMMYFUNCTION("""COMPUTED_VALUE"""),"BPD") -> BPD | T12: =IFERROR(__xludf.DUMMYFUNCTION("""COMPUTED_VALUE"""),"KEPALA - LEHER") -> KEPALA - LEHER | U12: =IFERROR(__xludf.DUMMYFUNCTION("""COMPUTED_VALUE"""),"") | V12: =IFERROR(__xludf.DUMMYFUNCTION("""COMPUTED_VALUE"""),"085245008010") -> 085245008010
B13: =IFERROR(__xludf.DUMMYFUNCTION("""COMPUTED_VALUE"""),45006.910388958335) -> 45006.91 | D13: =IFERROR(__xludf.DUMMYFUNCTION("""COMPUTED_VALUE"""),44928.0) -> 44928 | E13: =IFERROR(__xludf.DUMMYFUNCTION("""COMPUTED_VALUE"""),"01Jan") -> 01Jan | F13: =IFERROR(__xludf.DUMMYFUNCTION("""COMPUTED_VALUE"""),"2023") -> 2023 | G13: =IFERROR(__xludf.DUMMYFUNCTION("""COMPUTED_VALUE"""),"HUWAIDAH THIFAL NAURAH") -> HUWAIDAH THIFAL NAURAH | H13: =IFERROR(__xludf.DUMMYFUNCTION("""COMPUTED_VALUE"""),"H0123016085") -> H0123016085 | I13: =IFERROR(__xludf.DUMMYFUNCTION("""COMPUTED_VALUE"""),25.0) -> 25 | J13: =IFERROR(__xludf.DUMMYFUNCTION("""COMPUTED_VALUE"""),"25-34 tahun") -> 25-34 tahun | K13: =IFERROR(__xludf.DUMMYFUNCTION("""COMPUTED_VALUE"""),37038.0) -> 37038 | L13: =IFERROR(__xludf.DUMMYFUNCTION("""COMPUTED_VALUE"""),"PEREMPUAN") -> PEREMPUAN | M13: =IFERROR(__xludf.DUMMYFUNCTION("""COMPUTED_VALUE"""),"JL. KARET KOMP SEJAHTERA") -> JL. KARET KOMP SEJAHTERA | R13: =IFERROR(__xludf.DUMMYFUNCTION("""COMPUTED_VALUE"""),"ISLAM") -> ISLAM | S13: =IFERROR(__xludf.DUMMYFUNCTION("""COMPUTED_VALUE"""),"DOSEN/GURU") -> DOSEN/GURU | T13: =IFERROR(__xludf.DUMMYFUNCTION("""COMPUTED_VALUE"""),"PINGGANG") -> PINGGANG | U13: =IFERROR(__xludf.DUMMYFUNCTION("""COMPUTED_VALUE"""),"") | V13: =IFERROR(__xludf.DUMMYFUNCTION("""COMPUTED_VALUE"""),"085349896085") -> 085349896085
B14: =IFERROR(__xludf.DUMMYFUNCTION("""COMPUTED_VALUE"""),44941.5940162037) -> 44941.594 | D14: =IFERROR(__xludf.DUMMYFUNCTION("""COMPUTED_VALUE"""),44928.0) -> 44928 | E14: =IFERROR(__xludf.DUMMYFUNCTION("""COMPUTED_VALUE"""),"01Jan") -> 01Jan | F14: =IFERROR(__xludf.DUMMYFUNCTION("""COMPUTED_VALUE"""),"2023") -> 2023 | G14: =IFERROR(__xludf.DUMMYFUNCTION("""COMPUTED_VALUE"""),"SUFIRNA") -> SUFIRNA | H14: =IFERROR(__xludf.DUMMYFUNCTION("""COMPUTED_VALUE"""),"S7823018882") -> S7823018882 | I14: =IFERROR(__xludf.DUMMYFUNCTION("""COMPUTED_VALUE"""),48.0) -> 48 | J14: =IFERROR(__xludf.DUMMYFUNCTION("""COMPUTED_VALUE"""),"> 44 tahun") -> > 44 tahun | K14: =IFERROR(__xludf.DUMMYFUNCTION("""COMPUTED_VALUE"""),28629.0) -> 28629 | L14: =IFERROR(__xludf.DUMMYFUNCTION("""COMPUTED_VALUE"""),"PEREMPUAN") -> PEREMPUAN | M14: =IFERROR(__xludf.DUMMYFUNCTION("""COMPUTED_VALUE"""),"JL HIJAS NO 193") -> JL HIJAS NO 193 | R14: =IFERROR(__xludf.DUMMYFUNCTION("""COMPUTED_VALUE"""),"BUDDHA") -> BUDDHA | S14: =IFERROR(__xludf.DUMMYFUNCTION("""COMPUTED_VALUE"""),"SWASTA") -> SWASTA | T14: =IFERROR(__xludf.DUMMYFUNCTION("""COMPUTED_VALUE"""),"JARI TANGAN") -> JARI TANGAN | U14: =IFERROR(__xludf.DUMMYFUNCTION("""COMPUTED_VALUE"""),"-") -> - | V14: =IFERROR(__xludf.DUMMYFUNCTION("""COMPUTED_VALUE"""),"082148458882") -> 082148458882
B15: =IFERROR(__xludf.DUMMYFUNCTION("""COMPUTED_VALUE"""),44951.8272337963) -> 44951.827 | D15: =IFERROR(__xludf.DUMMYFUNCTION("""COMPUTED_VALUE"""),44929.0) -> 44929 | E15: =IFERROR(__xludf.DUMMYFUNCTION("""COMPUTED_VALUE"""),"01Jan") -> 01Jan | F15: =IFERROR(__xludf.DUMMYFUNCTION("""COMPUTED_VALUE"""),"2023") -> 2023 | G15: =IFERROR(__xludf.DUMMYFUNCTION("""COMPUTED_VALUE"""),"ALVIN DIYANDRA") -> ALVIN DIYANDRA | H15: =IFERROR(__xludf.DUMMYFUNCTION("""COMPUTED_VALUE"""),"A9723017817") -> A9723017817 | I15: =IFERROR(__xludf.DUMMYFUNCTION("""COMPUTED_VALUE"""),29.0) -> 29 | J15: =IFERROR(__xludf.DUMMYFUNCTION("""COMPUTED_VALUE"""),"25-34 tahun") -> 25-34 tahun | K15: =IFERROR(__xludf.DUMMYFUNCTION("""COMPUTED_VALUE"""),35517.0) -> 35517 | L15: =IFERROR(__xludf.DUMMYFUNCTION("""COMPUTED_VALUE"""),"LAKI-LAKI") -> LAKI-LAKI | M15: =IFERROR(__xludf.DUMMYFUNCTION("""COMPUTED_VALUE"""),"JL PARIS 2 KOMP BALIMAS 2 NO B8") -> JL PARIS 2 KOMP BALIMAS 2 NO B8 | R15: =IFERROR(__xludf.DUMMYFUNCTION("""COMPUTED_VALUE"""),"ISLAM") -> ISLAM | S15: =IFERROR(__xludf.DUMMYFUNCTION("""COMPUTED_VALUE"""),"SWASTA") -> SWASTA | T15: =IFERROR(__xludf.DUMMYFUNCTION("""COMPUTED_VALUE"""),"BAHU") -> BAHU | U15: =IFERROR(__xludf.DUMMYFUNCTION("""COMPUTED_VALUE"""),"-") -> - | V15: =IFERROR(__xludf.DUMMYFUNCTION("""COMPUTED_VALUE"""),"08988277817") -> 08988277817
B16: =IFERROR(__xludf.DUMMYFUNCTION("""COMPUTED_VALUE"""),44971.58675925926) -> 44971.587 | D16: =IFERROR(__xludf.DUMMYFUNCTION("""COMPUTED_VALUE"""),44929.0) -> 44929 | E16: =IFERROR(__xludf.DUMMYFUNCTION("""COMPUTED_VALUE"""),"01Jan") -> 01Jan | F16: =IFERROR(__xludf.DUMMYFUNCTION("""COMPUTED_VALUE"""),"2023") -> 2023 | G16: =IFERROR(__xludf.DUMMYFUNCTION("""COMPUTED_VALUE"""),"ANDI ICHWANUL AZWAR") -> ANDI ICHWANUL AZWAR | H16: =IFERROR(__xludf.DUMMYFUNCTION("""COMPUTED_VALUE"""),"A8823011011") -> A8823011011 | I16: =IFERROR(__xludf.DUMMYFUNCTION("""COMPUTED_VALUE"""),37.0) -> 37 | J16: =IFERROR(__xludf.DUMMYFUNCTION("""COMPUTED_VALUE"""),"35-44 tahun") -> 35-44 tahun | K16: =IFERROR(__xludf.DUMMYFUNCTION("""COMPUTED_VALUE"""),32379.0) -> 32379 | L16: =IFERROR(__xludf.DUMMYFUNCTION("""COMPUTED_VALUE"""),"LAKI-LAKI") -> LAKI-LAKI | M16: =IFERROR(__xludf.DUMMYFUNCTION("""COMPUTED_VALUE"""),"JL. H. R. A. RAHMAN GG. GUNUNG SAHARI") -> JL. H. R. A. RAHMAN GG. GUNUNG SAHARI | R16: =IFERROR(__xludf.DUMMYFUNCTION("""COMPUTED_VALUE"""),"ISLAM") -> ISLAM | S16: =IFERROR(__xludf.DUMMYFUNCTION("""COMPUTED_VALUE"""),"SWASTA") -> SWASTA | T16: =IFERROR(__xludf.DUMMYFUNCTION("""COMPUTED_VALUE"""),"- TUNGKAI BAWAH") -> - TUNGKAI BAWAH | U16: =IFERROR(__xludf.DUMMYFUNCTION("""COMPUTED_VALUE"""),"") | V16: =IFERROR(__xludf.DUMMYFUNCTION("""COMPUTED_VALUE"""),"08115691011") -> 08115691011
B17: =IFERROR(__xludf.DUMMYFUNCTION("""COMPUTED_VALUE"""),45006.87813922454) -> 45006.878 | D17: =IFERROR(__xludf.DUMMYFUNCTION("""COMPUTED_VALUE"""),44930.0) -> 44930 | E17: =IFERROR(__xludf.DUMMYFUNCTION("""COMPUTED_VALUE"""),"01Jan") -> 01Jan | F17: =IFERROR(__xludf.DUMMYFUNCTION("""COMPUTED_VALUE"""),"2023") -> 2023 | G17: =IFERROR(__xludf.DUMMYFUNCTION("""COMPUTED_VALUE"""),"AREEFAQEEL DIEN HAQQ") -> AREEFAQEEL DIEN HAQQ | H17: =IFERROR(__xludf.DUMMYFUNCTION("""COMPUTED_VALUE"""),"A1023015335") -> A1023015335 | I17: =IFERROR(__xludf.DUMMYFUNCTION("""COMPUTED_VALUE"""),15.0) -> 15 | J17: =IFERROR(__xludf.DUMMYFUNCTION("""COMPUTED_VALUE"""),"< 18 tahun") -> < 18 tahun | K17: =IFERROR(__xludf.DUMMYFUNCTION("""COMPUTED_VALUE"""),40440.0) -> 40440 | L17: =IFERROR(__xludf.DUMMYFUNCTION("""COMPUTED_VALUE"""),"LAKI-LAKI") -> LAKI-LAKI | M17: =IFERROR(__xludf.DUMMYFUNCTION("""COMPUTED_VALUE"""),"JL A R SALEH III NO 16") -> JL A R SALEH III NO 16 | R17: =IFERROR(__xludf.DUMMYFUNCTION("""COMPUTED_VALUE"""),"ISLAM") -> ISLAM | S17: =IFERROR(__xludf.DUMMYFUNCTION("""COMPUTED_VALUE"""),"PELAJAR/MAHASISWA") -> PELAJAR/MAHASISWA | U17: =IFERROR(__xludf.DUMMYFUNCTION("""COMPUTED_VALUE"""),"") | V17: =IFERROR(__xludf.DUMMYFUNCTION("""COMPUTED_VALUE"""),"081257035335") -> 081257035335
B18: =IFERROR(__xludf.DUMMYFUNCTION("""COMPUTED_VALUE"""),44985.451886574076) -> 44985.452 | D18: =IFERROR(__xludf.DUMMYFUNCTION("""COMPUTED_VALUE"""),44930.0) -> 44930 | E18: =IFERROR(__xludf.DUMMYFUNCTION("""COMPUTED_VALUE"""),"01Jan") -> 01Jan | F18: =IFERROR(__xludf.DUMMYFUNCTION("""COMPUTED_VALUE"""),"2023") -> 2023 | G18: =IFERROR(__xludf.DUMMYFUNCTION("""COMPUTED_VALUE"""),"NURLINA") -> NURLINA | H18: =IFERROR(__xludf.DUMMYFUNCTION("""COMPUTED_VALUE"""),"N8523017483") -> N8523017483 | I18: =IFERROR(__xludf.DUMMYFUNCTION("""COMPUTED_VALUE"""),40.0) -> 40 | J18: =IFERROR(__xludf.DUMMYFUNCTION("""COMPUTED_VALUE"""),"35-44 tahun") -> 35-44 tahun | K18: =IFERROR(__xludf.DUMMYFUNCTION("""COMPUTED_VALUE"""),31343.0) -> 31343 | L18: =IFERROR(__xludf.DUMMYFUNCTION("""COMPUTED_VALUE"""),"PEREMPUAN") -> PEREMPUAN | M18: =IFERROR(__xludf.DUMMYFUNCTION("""COMPUTED_VALUE"""),"JL. K. H. W. HASYIM GG. USAHA 1 NO. 17") -> JL. K. H. W. HASYIM GG. USAHA 1 NO. 17 | R18: =IFERROR(__xludf.DUMMYFUNCTION("""COMPUTED_VALUE"""),"ISLAM") -> ISLAM | S18: =IFERROR(__xludf.DUMMYFUNCTION("""COMPUTED_VALUE"""),"DOSEN/GURU") -> DOSEN/GURU | T18: =IFERROR(__xludf.DUMMYFUNCTION("""COMPUTED_VALUE"""),"TELAPAK KAKI") -> TELAPAK KAKI | U18: =IFERROR(__xludf.DUMMYFUNCTION("""COMPUTED_VALUE"""),"") | V18: =IFERROR(__xludf.DUMMYFUNCTION("""COMPUTED_VALUE"""),"08565007483") -> 08565007483
B19: =IFERROR(__xludf.DUMMYFUNCTION("""COMPUTED_VALUE"""),45011.63774479167) -> 45011.638 | D19: =IFERROR(__xludf.DUMMYFUNCTION("""COMPUTED_VALUE"""),44931.0) -> 44931 | E19: =IFERROR(__xludf.DUMMYFUNCTION("""COMPUTED_VALUE"""),"01Jan") -> 01Jan | F19: =IFERROR(__xludf.DUMMYFUNCTION("""COMPUTED_VALUE"""),"2023") -> 2023 | G19: =IFERROR(__xludf.DUMMYFUNCTION("""COMPUTED_VALUE"""),"A. THENU") -> A. THENU | H19: =IFERROR(__xludf.DUMMYFUNCTION("""COMPUTED_VALUE"""),"A7023018857") -> A7023018857 | I19: =IFERROR(__xludf.DUMMYFUNCTION("""COMPUTED_VALUE"""),55.0) -> 55 | J19: =IFERROR(__xludf.DUMMYFUNCTION("""COMPUTED_VALUE"""),"> 44 tahun") -> > 44 tahun | K19: =IFERROR(__xludf.DUMMYFUNCTION("""COMPUTED_VALUE"""),25875.0) -> 25875 | L19: =IFERROR(__xludf.DUMMYFUNCTION("""COMPUTED_VALUE"""),"LAKI-LAKI") -> LAKI-LAKI | M19: =IFERROR(__xludf.DUMMYFUNCTION("""COMPUTED_VALUE"""),"JL TABRANI AHMAD GG IKRAR NON70") -> JL TABRANI AHMAD GG IKRAR NON70 | R19: =IFERROR(__xludf.DUMMYFUNCTION("""COMPUTED_VALUE"""),"PROTESTAN") -> PROTESTAN | S19: =IFERROR(__xludf.DUMMYFUNCTION("""COMPUTED_VALUE"""),"SWASTA") -> SWASTA | T19: =IFERROR(__xludf.DUMMYFUNCTION("""COMPUTED_VALUE"""),"PINGGANG") -> PINGGANG | U19: =IFERROR(__xludf.DUMMYFUNCTION("""COMPUTED_VALUE"""),"-") -> - | V19: =IFERROR(__xludf.DUMMYFUNCTION("""COMPUTED_VALUE"""),"08125728857") -> 08125728857
B20: =IFERROR(__xludf.DUMMYFUNCTION("""COMPUTED_VALUE"""),45006.90633336805) -> 45006.906 | D20: =IFERROR(__xludf.DUMMYFUNCTION("""COMPUTED_VALUE"""),44931.0) -> 44931 | E20: =IFERROR(__xludf.DUMMYFUNCTION("""COMPUTED_VALUE"""),"01Jan") -> 01Jan | F20: =IFERROR(__xludf.DUMMYFUNCTION("""COMPUTED_VALUE"""),"2023") -> 2023 | G20: =IFERROR(__xludf.DUMMYFUNCTION("""COMPUTED_VALUE"""),"ATIKA ALIFIA F. TOBING") -> ATIKA ALIFIA F. TOBING | H20: =IFERROR(__xludf.DUMMYFUNCTION("""COMPUTED_VALUE"""),"A9023018425") -> A9023018425 | I20: =IFERROR(__xludf.DUMMYFUNCTION("""COMPUTED_VALUE"""),36.0) -> 36 | J20: =IFERROR(__xludf.DUMMYFUNCTION("""COMPUTED_VALUE"""),"35-44 tahun") -> 35-44 tahun | K20: =IFERROR(__xludf.DUMMYFUNCTION("""COMPUTED_VALUE"""),32990.0) -> 32990 | L20: =IFERROR(__xludf.DUMMYFUNCTION("""COMPUTED_VALUE"""),"PEREMPUAN") -> PEREMPUAN | M20: =IFERROR(__xludf.DUMMYFUNCTION("""COMPUTED_VALUE"""),"JL. PADAT KARYA GG. KARYA BARU NO. A1") -> JL. PADAT KARYA GG. KARYA BARU NO. A1 | R20: =IFERROR(__xludf.DUMMYFUNCTION("""COMPUTED_VALUE"""),"ISLAM") -> ISLAM | S20: =IFERROR(__xludf.DUMMYFUNCTION("""COMPUTED_VALUE"""),"ASN") -> ASN | T20: =IFERROR(__xludf.DUMMYFUNCTION("""COMPUTED_VALUE"""),"KAKI") -> KAKI | U20: =IFERROR(__xludf.DUMMYFUNCTION("""COMPUTED_VALUE"""),"DUDUK LAMA") -> DUDUK LAMA | V20: =IFERROR(__xludf.DUMMYFUNCTION("""COMPUTED_VALUE"""),"087789068425") -> 087789068425
B21: =IFERROR(__xludf.DUMMYFUNCTION("""COMPUTED_VALUE"""),45011.640681296296) -> 45011.641 | D21: =IFERROR(__xludf.DUMMYFUNCTION("""COMPUTED_VALUE"""),44931.0) -> 44931 | E21: =IFERROR(__xludf.DUMMYFUNCTION("""COMPUTED_VALUE"""),"01Jan") -> 01Jan | F21: =IFERROR(__xludf.DUMMYFUNCTION("""COMPUTED_VALUE"""),"2023") -> 2023 | G21: =IFERROR(__xludf.DUMMYFUNCTION("""COMPUTED_VALUE"""),"JAKA SEPTIADI") -> JAKA SEPTIADI | H21: =IFERROR(__xludf.DUMMYFUNCTION("""COMPUTED_VALUE"""),"J8823016633") -> J8823016633 | I21: =IFERROR(__xludf.DUMMYFUNCTION("""COMPUTED_VALUE"""),38.0) -> 38 | J21: =IFERROR(__xludf.DUMMYFUNCTION("""COMPUTED_VALUE"""),"35-44 tahun") -> 35-44 tahun | K21: =IFERROR(__xludf.DUMMYFUNCTION("""COMPUTED_VALUE"""),32239.0) -> 32239 | L21: =IFERROR(__xludf.DUMMYFUNCTION("""COMPUTED_VALUE"""),"LAKI-LAKI") -> LAKI-LAKI | M21: =IFERROR(__xludf.DUMMYFUNCTION("""COMPUTED_VALUE"""),"JL. PARIS 2 PONTIANAK") -> JL. PARIS 2 PONTIANAK | R21: =IFERROR(__xludf.DUMMYFUNCTION("""COMPUTED_VALUE"""),"ISLAM") -> ISLAM | S21: =IFERROR(__xludf.DUMMYFUNCTION("""COMPUTED_VALUE"""),"SWASTA") -> SWASTA | T21: =IFERROR(__xludf.DUMMYFUNCTION("""COMPUTED_VALUE"""),"PINGGANG") -> PINGGANG | U21: =IFERROR(__xludf.DUMMYFUNCTION("""COMPUTED_VALUE"""),"DUDUK LAMA") -> DUDUK LAMA | V21: =IFERROR(__xludf.DUMMYFUNCTION("""COMPUTED_VALUE"""),"081281616633") -> 081281616633
B22: =IFERROR(__xludf.DUMMYFUNCTION("""COMPUTED_VALUE"""),44888.56218804399) -> 44888.562 | D22: =IFERROR(__xludf.DUMMYFUNCTION("""COMPUTED_VALUE"""),44931.0) -> 44931 | E22: =IFERROR(__xludf.DUMMYFUNCTION("""COMPUTED_VALUE"""),"01Jan") -> 01Jan | F22: =IFERROR(__xludf.DUMMYFUNCTION("""COMPUTED_VALUE"""),"2023") -> 2023 | G22: =IFERROR(__xludf.DUMMYFUNCTION("""COMPUTED_VALUE"""),"MARIYO") -> MARIYO | H22: =IFERROR(__xludf.DUMMYFUNCTION("""COMPUTED_VALUE"""),"M6523010470") -> M6523010470 | I22: =IFERROR(__xludf.DUMMYFUNCTION("""COMPUTED_VALUE"""),60.0) -> 60 | J22: =IFERROR(__xludf.DUMMYFUNCTION("""COMPUTED_VALUE"""),"> 44 tahun") -> > 44 tahun | K22: =IFERROR(__xludf.DUMMYFUNCTION("""COMPUTED_VALUE"""),24088.0) -> 24088 | L22: =IFERROR(__xludf.DUMMYFUNCTION("""COMPUTED_VALUE"""),"LAKI-LAKI") -> LAKI-LAKI | M22: =IFERROR(__xludf.DUMMYFUNCTION("""COMPUTED_VALUE"""),"JL. PROF DR HAMKA GG NILAM 8") -> JL. PROF DR HAMKA GG NILAM 8 | R22: =IFERROR(__xludf.DUMMYFUNCTION("""COMPUTED_VALUE"""),"ISLAM") -> ISLAM | S22: =IFERROR(__xludf.DUMMYFUNCTION("""COMPUTED_VALUE"""),"SWASTA") -> SWASTA | T22: =IFERROR(__xludf.DUMMYFUNCTION("""COMPUTED_VALUE"""),"PINGGANG BOKONG") -> PINGGANG BOKONG | U22: =IFERROR(__xludf.DUMMYFUNCTION("""COMPUTED_VALUE"""),"") | V22: =IFERROR(__xludf.DUMMYFUNCTION("""COMPUTED_VALUE"""),"081933860470") -> 081933860470
B23: =IFERROR(__xludf.DUMMYFUNCTION("""COMPUTED_VALUE"""),44921.8215625) -> 44921.822 | D23: =IFERROR(__xludf.DUMMYFUNCTION("""COMPUTED_VALUE"""),44933.0) -> 44933 | E23: =IFERROR(__xludf.DUMMYFUNCTION("""COMPUTED_VALUE"""),"01Jan") -> 01Jan | F23: =IFERROR(__xludf.DUMMYFUNCTION("""COMPUTED_VALUE"""),"2023") -> 2023 | G23: =IFERROR(__xludf.DUMMYFUNCTION("""COMPUTED_VALUE"""),"ADIEL PRATAMA PUTRA K.") -> ADIEL PRATAMA PUTRA K. | H23: =IFERROR(__xludf.DUMMYFUNCTION("""COMPUTED_VALUE"""),"A0623015163") -> A0623015163 | I23: =IFERROR(__xludf.DUMMYFUNCTION("""COMPUTED_VALUE"""),20.0) -> 20 | J23: =IFERROR(__xludf.DUMMYFUNCTION("""COMPUTED_VALUE"""),"18-24 tahun") -> 18-24 tahun | K23: =IFERROR(__xludf.DUMMYFUNCTION("""COMPUTED_VALUE"""),38793.0) -> 38793 | L23: =IFERROR(__xludf.DUMMYFUNCTION("""COMPUTED_VALUE"""),"LAKI-LAKI") -> LAKI-LAKI | M23: =IFERROR(__xludf.DUMMYFUNCTION("""COMPUTED_VALUE"""),"JL DANAU SENTARUM GG PERSATUAN NO B4") -> JL DANAU SENTARUM GG PERSATUAN NO B4 | R23: =IFERROR(__xludf.DUMMYFUNCTION("""COMPUTED_VALUE"""),"ISLAM") -> ISLAM | S23: =IFERROR(__xludf.DUMMYFUNCTION("""COMPUTED_VALUE"""),"PELAJAR/MAHASISWA") -> PELAJAR/MAHASISWA | T23: =IFERROR(__xludf.DUMMYFUNCTION("""COMPUTED_VALUE"""),"SKOLIOSIS") -> SKOLIOSIS | U23: =IFERROR(__xludf.DUMMYFUNCTION("""COMPUTED_VALUE"""),"-") -> - | V23: =IFERROR(__xludf.DUMMYFUNCTION("""COMPUTED_VALUE"""),"085779775163") -> 085779775163
B24: =IFERROR(__xludf.DUMMYFUNCTION("""COMPUTED_VALUE"""),44973.39733796296) -> 44973.397 | D24: =IFERROR(__xludf.DUMMYFUNCTION("""COMPUTED_VALUE"""),44933.0) -> 44933 | E24: =IFERROR(__xludf.DUMMYFUNCTION("""COMPUTED_VALUE"""),"01Jan") -> 01Jan | F24: =IFERROR(__xludf.DUMMYFUNCTION("""COMPUTED_VALUE"""),"2023") -> 2023 | G24: =IFERROR(__xludf.DUMMYFUNCTION("""COMPUTED_VALUE"""),"DAVID BURUI") -> DAVID BURUI | H24: =IFERROR(__xludf.DUMMYFUNCTION("""COMPUTED_VALUE"""),"D6123013327") -> D6123013327 | I24: =IFERROR(__xludf.DUMMYFUNCTION("""COMPUTED_VALUE"""),64.0) -> 64 | J24: =IFERROR(__xludf.DUMMYFUNCTION("""COMPUTED_VALUE"""),"> 44 tahun") -> > 44 tahun | K24: =IFERROR(__xludf.DUMMYFUNCTION("""COMPUTED_VALUE"""),22626.0) -> 22626 | L24: =IFERROR(__xludf.DUMMYFUNCTION("""COMPUTED_VALUE"""),"LAKI-LAKI") -> LAKI-LAKI | M24: =IFERROR(__xludf.DUMMYFUNCTION("""COMPUTED_VALUE"""),"JL. PERUMNAS GG. MANTAN XI") -> JL. PERUMNAS GG. MANTAN XI | R24: =IFERROR(__xludf.DUMMYFUNCTION("""COMPUTED_VALUE"""),"ISLAM") -> ISLAM | S24: =IFERROR(__xludf.DUMMYFUNCTION("""COMPUTED_VALUE"""),"TIDAK ADA") -> TIDAK ADA | T24: =IFERROR(__xludf.DUMMYFUNCTION("""COMPUTED_VALUE"""),"DADA") -> DADA | U24: =IFERROR(__xludf.DUMMYFUNCTION("""COMPUTED_VALUE"""),"") | V24: =IFERROR(__xludf.DUMMYFUNCTION("""COMPUTED_VALUE"""),"081280423327") -> 081280423327
B25: =IFERROR(__xludf.DUMMYFUNCTION("""COMPUTED_VALUE"""),45006.87726905092) -> 45006.877 | D25: =IFERROR(__xludf.DUMMYFUNCTION("""COMPUTED_VALUE"""),44933.0) -> 44933 | E25: =IFERROR(__xludf.DUMMYFUNCTION("""COMPUTED_VALUE"""),"01Jan") -> 01Jan | F25: =IFERROR(__xludf.DUMMYFUNCTION("""COMPUTED_VALUE"""),"2023") -> 2023 | G25: =IFERROR(__xludf.DUMMYFUNCTION("""COMPUTED_VALUE"""),"DEDI SUNARDI") -> DEDI SUNARDI | H25: =IFERROR(__xludf.DUMMYFUNCTION("""COMPUTED_VALUE"""),"D8223017622") -> D8223017622 | I25: =IFERROR(__xludf.DUMMYFUNCTION("""COMPUTED_VALUE"""),43.0) -> 43 | J25: =IFERROR(__xludf.DUMMYFUNCTION("""COMPUTED_VALUE"""),"35-44 tahun") -> 35-44 tahun | K25: =IFERROR(__xludf.DUMMYFUNCTION("""COMPUTED_VALUE"""),30309.0) -> 30309 | L25: =IFERROR(__xludf.DUMMYFUNCTION("""COMPUTED_VALUE"""),"LAKI-LAKI") -> LAKI-LAKI | M25: =IFERROR(__xludf.DUMMYFUNCTION("""COMPUTED_VALUE"""),"SANGGAU") -> SANGGAU | R25: =IFERROR(__xludf.DUMMYFUNCTION("""COMPUTED_VALUE"""),"ISLAM") -> ISLAM | S25: =IFERROR(__xludf.DUMMYFUNCTION("""COMPUTED_VALUE"""),"SWASTA") -> SWASTA | T25: =IFERROR(__xludf.DUMMYFUNCTION("""COMPUTED_VALUE"""),"PINGGANG") -> PINGGANG | U25: =IFERROR(__xludf.DUMMYFUNCTION("""COMPUTED_VALUE"""),"") | V25: =IFERROR(__xludf.DUMMYFUNCTION("""COMPUTED_VALUE"""),"085822957622") -> 085822957622
B26: =IFERROR(__xludf.DUMMYFUNCTION("""COMPUTED_VALUE"""),44983.46637731481) -> 44983.466 | D26: =IFERROR(__xludf.DUMMYFUNCTION("""COMPUTED_VALUE"""),44933.0) -> 44933 | E26: =IFERROR(__xludf.DUMMYFUNCTION("""COMPUTED_VALUE"""),"01Jan") -> 01Jan | F26: =IFERROR(__xludf.DUMMYFUNCTION("""COMPUTED_VALUE"""),"2023") -> 2023 | G26: =IFERROR(__xludf.DUMMYFUNCTION("""COMPUTED_VALUE"""),"MIGUEL TJONDRO") -> MIGUEL TJONDRO | H26: =IFERROR(__xludf.DUMMYFUNCTION("""COMPUTED_VALUE"""),"M9823010741") -> M9823010741 | I26: =IFERROR(__xludf.DUMMYFUNCTION("""COMPUTED_VALUE"""),28.0) -> 28 | J26: =IFERROR(__xludf.DUMMYFUNCTION("""COMPUTED_VALUE"""),"25-34 tahun") -> 25-34 tahun | K26: =IFERROR(__xludf.DUMMYFUNCTION("""COMPUTED_VALUE"""),35871.0) -> 35871 | L26: =IFERROR(__xludf.DUMMYFUNCTION("""COMPUTED_VALUE"""),"LAKI-LAKI") -> LAKI-LAKI | M26: =IFERROR(__xludf.DUMMYFUNCTION("""COMPUTED_VALUE"""),"JL. P. H. HUSIN 1 GG. PERWIRA NO. 18A") -> JL. P. H. HUSIN 1 GG. PERWIRA NO. 18A | R26: =IFERROR(__xludf.DUMMYFUNCTION("""COMPUTED_VALUE"""),"KATOLIK") -> KATOLIK | S26: =IFERROR(__xludf.DUMMYFUNCTION("""COMPUTED_VALUE"""),"SWASTA") -> SWASTA | T26: =IFERROR(__xludf.DUMMYFUNCTION("""COMPUTED_VALUE"""),"KIRI") -> KIRI | U26: =IFERROR(__xludf.DUMMYFUNCTION("""COMPUTED_VALUE"""),"") | V26: =IFERROR(__xludf.DUMMYFUNCTION("""COMPUTED_VALUE"""),"08977200741") -> 08977200741
B27: =IFERROR(__xludf.DUMMYFUNCTION("""COMPUTED_VALUE"""),44941.44567129629) -> 44941.446 | D27: =IFERROR(__xludf.DUMMYFUNCTION("""COMPUTED_VALUE"""),44933.0) -> 44933 | E27: =IFERROR(__xludf.DUMMYFUNCTION("""COMPUTED_VALUE"""),"01Jan") -> 01Jan | F27: =IFERROR(__xludf.DUMMYFUNCTION("""COMPUTED_VALUE"""),"2023") -> 2023 | G27: =IFERROR(__xludf.DUMMYFUNCTION("""COMPUTED_VALUE"""),"TRI WAHYUNI") -> TRI WAHYUNI | H27: =IFERROR(__xludf.DUMMYFUNCTION("""COMPUTED_VALUE"""),"T7623010391") -> T7623010391 | I27: =IFERROR(__xludf.DUMMYFUNCTION("""COMPUTED_VALUE"""),50.0) -> 50 | J27: =IFERROR(__xludf.DUMMYFUNCTION("""COMPUTED_VALUE"""),"> 44 tahun") -> > 44 tahun | K27: =IFERROR(__xludf.DUMMYFUNCTION("""COMPUTED_VALUE"""),27825.0) -> 27825 | L27: =IFERROR(__xludf.DUMMYFUNCTION("""COMPUTED_VALUE"""),"PEREMPUAN") -> PEREMPUAN | M27: =IFERROR(__xludf.DUMMYFUNCTION("""COMPUTED_VALUE"""),"BENGKAYANG") -> BENGKAYANG | R27: =IFERROR(__xludf.DUMMYFUNCTION("""COMPUTED_VALUE"""),"ISLAM") -> ISLAM | S27: =IFERROR(__xludf.DUMMYFUNCTION("""COMPUTED_VALUE"""),"ASN") -> ASN | T27: =IFERROR(__xludf.DUMMYFUNCTION("""COMPUTED_VALUE"""),"PINGGANG") -> PINGGANG | U27: =IFERROR(__xludf.DUMMYFUNCTION("""COMPUTED_VALUE"""),"-") -> - | V27: =IFERROR(__xludf.DUMMYFUNCTION("""COMPUTED_VALUE"""),"081345790391") -> 081345790391
B28: =IFERROR(__xludf.DUMMYFUNCTION("""COMPUTED_VALUE"""),45006.8960915625) -> 45006.896 | D28: =IFERROR(__xludf.DUMMYFUNCTION("""COMPUTED_VALUE"""),44934.0) -> 44934 | E28: =IFERROR(__xludf.DUMMYFUNCTION("""COMPUTED_VALUE"""),"01Jan") -> 01Jan | F28: =IFERROR(__xludf.DUMMYFUNCTION("""COMPUTED_VALUE"""),"2023") -> 2023 | G28: =IFERROR(__xludf.DUMMYFUNCTION("""COMPUTED_VALUE"""),"ANANTA UTAMI") -> ANANTA UTAMI | H28: =IFERROR(__xludf.DUMMYFUNCTION("""COMPUTED_VALUE"""),"A9123011070") -> A9123011070 | I28: =IFERROR(__xludf.DUMMYFUNCTION("""COMPUTED_VALUE"""),34.0) -> 34 | J28: =IFERROR(__xludf.DUMMYFUNCTION("""COMPUTED_VALUE"""),"25-34 tahun") -> 25-34 tahun | K28: =IFERROR(__xludf.DUMMYFUNCTION("""COMPUTED_VALUE"""),33550.0) -> 33550 | L28: =IFERROR(__xludf.DUMMYFUNCTION("""COMPUTED_VALUE"""),"PEREMPUAN") -> PEREMPUAN | M28: =IFERROR(__xludf.DUMMYFUNCTION("""COMPUTED_VALUE"""),"JL. DR. SUTOMO GG. KARYA 1") -> JL. DR. SUTOMO GG. KARYA 1 | R28: =IFERROR(__xludf.DUMMYFUNCTION("""COMPUTED_VALUE"""),"KATOLIK") -> KATOLIK | S28: =IFERROR(__xludf.DUMMYFUNCTION("""COMPUTED_VALUE"""),"ASN") -> ASN | T28: =IFERROR(__xludf.DUMMYFUNCTION("""COMPUTED_VALUE"""),"KIRI") -> KIRI | U28: =IFERROR(__xludf.DUMMYFUNCTION("""COMPUTED_VALUE"""),"") | V28: =IFERROR(__xludf.DUMMYFUNCTION("""COMPUTED_VALUE"""),"081253051070") -> 081253051070
B29: =IFERROR(__xludf.DUMMYFUNCTION("""COMPUTED_VALUE"""),44973.42521990741) -> 44973.425 | D29: =IFERROR(__xludf.DUMMYFUNCTION("""COMPUTED_VALUE"""),44934.0) -> 44934 | E29: =IFERROR(__xludf.DUMMYFUNCTION("""COMPUTED_VALUE"""),"01Jan") -> 01Jan | F29: =IFERROR(__xludf.DUMMYFUNCTION("""COMPUTED_VALUE"""),"2023") -> 2023 | G29: =IFERROR(__xludf.DUMMYFUNCTION("""COMPUTED_VALUE"""),"EMMI") -> EMMI | H29: =IFERROR(__xludf.DUMMYFUNCTION("""COMPUTED_VALUE"""),"E6223013059") -> E6223013059 | I29: =IFERROR(__xludf.DUMMYFUNCTION("""COMPUTED_VALUE"""),63.0) -> 63 | J29: =IFERROR(__xludf.DUMMYFUNCTION("""COMPUTED_VALUE"""),"> 44 tahun") -> > 44 tahun | K29: =IFERROR(__xludf.DUMMYFUNCTION("""COMPUTED_VALUE"""),22971.0) -> 22971 | L29: =IFERROR(__xludf.DUMMYFUNCTION("""COMPUTED_VALUE"""),"PEREMPUAN") -> PEREMPUAN | M29: =IFERROR(__xludf.DUMMYFUNCTION("""COMPUTED_VALUE"""),"JL PURNAMA KOMP PURNAMA AGUNG 2 NO G1") -> JL PURNAMA KOMP PURNAMA AGUNG 2 NO G1 | R29: =IFERROR(__xludf.DUMMYFUNCTION("""COMPUTED_VALUE"""),"LAINNYA") -> LAINNYA | S29: =IFERROR(__xludf.DUMMYFUNCTION("""COMPUTED_VALUE"""),"TIDAK ADA") -> TIDAK ADA | T29: =IFERROR(__xludf.DUMMYFUNCTION("""COMPUTED_VALUE"""),"PINGGANG") -> PINGGANG | U29: =IFERROR(__xludf.DUMMYFUNCTION("""COMPUTED_VALUE"""),"-") -> - | V29: =IFERROR(__xludf.DUMMYFUNCTION("""COMPUTED_VALUE"""),"081345583059") -> 081345583059
B30: =IFERROR(__xludf.DUMMYFUNCTION("""COMPUTED_VALUE"""),44973.424212962964) -> 44973.424 | D30: =IFERROR(__xludf.DUMMYFUNCTION("""COMPUTED_VALUE"""),44934.0) -> 44934 | E30: =IFERROR(__xludf.DUMMYFUNCTION("""COMPUTED_VALUE"""),"01Jan") -> 01Jan | F30: =IFERROR(__xludf.DUMMYFUNCTION("""COMPUTED_VALUE"""),"2023") -> 2023 | G30: =IFERROR(__xludf.DUMMYFUNCTION("""COMPUTED_VALUE"""),"ZIQRIL HAKIM R") -> ZIQRIL HAKIM R | H30: =IFERROR(__xludf.DUMMYFUNCTION("""COMPUTED_VALUE"""),"Z0423010391") -> Z0423010391 | I30: =IFERROR(__xludf.DUMMYFUNCTION("""COMPUTED_VALUE"""),21.0) -> 21 | J30: =IFERROR(__xludf.DUMMYFUNCTION("""COMPUTED_VALUE"""),"18-24 tahun") -> 18-24 tahun | K30: =IFERROR(__xludf.DUMMYFUNCTION("""COMPUTED_VALUE"""),38279.0) -> 38279 | L30: =IFERROR(__xludf.DUMMYFUNCTION("""COMPUTED_VALUE"""),"LAKI-LAKI") -> LAKI-LAKI | M30: =IFERROR(__xludf.DUMMYFUNCTION("""COMPUTED_VALUE"""),"BENGKAYANG") -> BENGKAYANG | R30: =IFERROR(__xludf.DUMMYFUNCTION("""COMPUTED_VALUE"""),"ISLAM") -> ISLAM | S30: =IFERROR(__xludf.DUMMYFUNCTION("""COMPUTED_VALUE"""),"TNI/POLRI") -> TNI/POLRI | T30: =IFERROR(__xludf.DUMMYFUNCTION("""COMPUTED_VALUE"""),"RAHANG") -> RAHANG | U30: =IFERROR(__xludf.DUMMYFUNCTION("""COMPUTED_VALUE"""),"-") -> - | V30: =IFERROR(__xludf.DUMMYFUNCTION("""COMPUTED_VALUE"""),"081345790391") -> 081345790391
B31: =IFERROR(__xludf.DUMMYFUNCTION("""COMPUTED_VALUE"""),45006.89896464121) -> 45006.899 | D31: =IFERROR(__xludf.DUMMYFUNCTION("""COMPUTED_VALUE"""),44935.0) -> 44935 | E31: =IFERROR(__xludf.DUMMYFUNCTION("""COMPUTED_VALUE"""),"01Jan") -> 01Jan | F31: =IFERROR(__xludf.DUMMYFUNCTION("""COMPUTED_VALUE"""),"2023") -> 2023 | G31: =IFERROR(__xludf.DUMMYFUNCTION("""COMPUTED_VALUE"""),"ERNA SETIAWATY") -> ERNA SETIAWATY | H31: =IFERROR(__xludf.DUMMYFUNCTION("""COMPUTED_VALUE"""),"E5423019005") -> E5423019005 | I31: =IFERROR(__xludf.DUMMYFUNCTION("""COMPUTED_VALUE"""),71.0) -> 71 | J31: =IFERROR(__xludf.DUMMYFUNCTION("""COMPUTED_VALUE"""),"> 44 tahun") -> > 44 tahun | K31: =IFERROR(__xludf.DUMMYFUNCTION("""COMPUTED_VALUE"""),20084.0) -> 20084 | L31: =IFERROR(__xludf.DUMMYFUNCTION("""COMPUTED_VALUE"""),"PEREMPUAN") -> PEREMPUAN | M31: =IFERROR(__xludf.DUMMYFUNCTION("""COMPUTED_VALUE"""),"JL. KAPTEN P. TENDEAN NO. 17A") -> JL. KAPTEN P. TENDEAN NO. 17A | R31: =IFERROR(__xludf.DUMMYFUNCTION("""COMPUTED_VALUE"""),"BUDDHA") -> BUDDHA | S31: =IFERROR(__xludf.DUMMYFUNCTION("""COMPUTED_VALUE"""),"RUMAH TANGGA") -> RUMAH TANGGA | T31: =IFERROR(__xludf.DUMMYFUNCTION("""COMPUTED_VALUE"""),"PINGGANG") -> PINGGANG | U31: =IFERROR(__xludf.DUMMYFUNCTION("""COMPUTED_VALUE"""),"") | V31: =IFERROR(__xludf.DUMMYFUNCTION("""COMPUTED_VALUE"""),"087878219005") -> 087878219005
B32: =IFERROR(__xludf.DUMMYFUNCTION("""COMPUTED_VALUE"""),44908.589479166665) -> 44908.589 | D32: =IFERROR(__xludf.DUMMYFUNCTION("""COMPUTED_VALUE"""),44935.0) -> 44935 | E32: =IFERROR(__xludf.DUMMYFUNCTION("""COMPUTED_VALUE"""),"01Jan") -> 01Jan | F32: =IFERROR(__xludf.DUMMYFUNCTION("""COMPUTED_VALUE"""),"2023") -> 2023 | G32: =IFERROR(__xludf.DUMMYFUNCTION("""COMPUTED_VALUE"""),"EVA DOLOROSA") -> EVA DOLOROSA | H32: =IFERROR(__xludf.DUMMYFUNCTION("""COMPUTED_VALUE"""),"E6723010889") -> E6723010889 | I32: =IFERROR(__xludf.DUMMYFUNCTION("""COMPUTED_VALUE"""),58.0) -> 58 | J32: =IFERROR(__xludf.DUMMYFUNCTION("""COMPUTED_VALUE"""),"> 44 tahun") -> > 44 tahun | K32: =IFERROR(__xludf.DUMMYFUNCTION("""COMPUTED_VALUE"""),24668.0) -> 24668 | L32: =IFERROR(__xludf.DUMMYFUNCTION("""COMPUTED_VALUE"""),"PEREMPUAN") -> PEREMPUAN | M32: =IFERROR(__xludf.DUMMYFUNCTION("""COMPUTED_VALUE"""),"JL. PARIS II GG. DEMAK NO.10") -> JL. PARIS II GG. DEMAK NO.10 | R32: =IFERROR(__xludf.DUMMYFUNCTION("""COMPUTED_VALUE"""),"ISLAM") -> ISLAM | S32: =IFERROR(__xludf.DUMMYFUNCTION("""COMPUTED_VALUE"""),"DOSEN/GURU") -> DOSEN/GURU | U32: =IFERROR(__xludf.DUMMYFUNCTION("""COMPUTED_VALUE"""),"-") -> - | V32: =IFERROR(__xludf.DUMMYFUNCTION("""COMPUTED_VALUE"""),"08125700889") -> 08125700889
B33: =IFERROR(__xludf.DUMMYFUNCTION("""COMPUTED_VALUE"""),44964.8041087963) -> 44964.804 | D33: =IFERROR(__xludf.DUMMYFUNCTION("""COMPUTED_VALUE"""),44936.0) -> 44936 | E33: =IFERROR(__xludf.DUMMYFUNCTION("""COMPUTED_VALUE"""),"01Jan") -> 01Jan | F33: =IFERROR(__xludf.DUMMYFUNCTION("""COMPUTED_VALUE"""),"2023") -> 2023 | G33: =IFERROR(__xludf.DUMMYFUNCTION("""COMPUTED_VALUE"""),"ANTO PRAYUGO") -> ANTO PRAYUGO | H33: =IFERROR(__xludf.DUMMYFUNCTION("""COMPUTED_VALUE"""),"A9523012989") -> A9523012989 | I33: =IFERROR(__xludf.DUMMYFUNCTION("""COMPUTED_VALUE"""),31.0) -> 31 | J33: =IFERROR(__xludf.DUMMYFUNCTION("""COMPUTED_VALUE"""),"25-34 tahun") -> 25-34 tahun | K33: =IFERROR(__xludf.DUMMYFUNCTION("""COMPUTED_VALUE"""),34806.0) -> 34806 | L33: =IFERROR(__xludf.DUMMYFUNCTION("""COMPUTED_VALUE"""),"LAKI-LAKI") -> LAKI-LAKI | M33: =IFERROR(__xludf.DUMMYFUNCTION("""COMPUTED_VALUE"""),"JL PERDANA KOMP BALI AGUNG 2") -> JL PERDANA KOMP BALI AGUNG 2 | R33: =IFERROR(__xludf.DUMMYFUNCTION("""COMPUTED_VALUE"""),"ISLAM") -> ISLAM | S33: =IFERROR(__xludf.DUMMYFUNCTION("""COMPUTED_VALUE"""),"PERBANKAN") -> PERBANKAN | U33: =IFERROR(__xludf.DUMMYFUNCTION("""COMPUTED_VALUE"""),"FUTSAL") -> FUTSAL | V33: =IFERROR(__xludf.DUMMYFUNCTION("""COMPUTED_VALUE"""),"081350622989") -> 081350622989
B34: =IFERROR(__xludf.DUMMYFUNCTION("""COMPUTED_VALUE"""),45006.87447142361) -> 45006.874 | D34: =IFERROR(__xludf.DUMMYFUNCTION("""COMPUTED_VALUE"""),44936.0) -> 44936 | E34: =IFERROR(__xludf.DUMMYFUNCTION("""COMPUTED_VALUE"""),"01Jan") -> 01Jan | F34: =IFERROR(__xludf.DUMMYFUNCTION("""COMPUTED_VALUE"""),"2023") -> 2023 | G34: =IFERROR(__xludf.DUMMYFUNCTION("""COMPUTED_VALUE"""),"FAHMI") -> FAHMI | H34: =IFERROR(__xludf.DUMMYFUNCTION("""COMPUTED_VALUE"""),"F8623010888") -> F8623010888 | I34: =IFERROR(__xludf.DUMMYFUNCTION("""COMPUTED_VALUE"""),40.0) -> 40 | J34: =IFERROR(__xludf.DUMMYFUNCTION("""COMPUTED_VALUE"""),"35-44 tahun") -> 35-44 tahun | K34: =IFERROR(__xludf.DUMMYFUNCTION("""COMPUTED_VALUE"""),31523.0) -> 31523 | L34: =IFERROR(__xludf.DUMMYFUNCTION("""COMPUTED_VALUE"""),"LAKI-LAKI") -> LAKI-LAKI | M34: =IFERROR(__xludf.DUMMYFUNCTION("""COMPUTED_VALUE"""),"JL KARYA") -> JL KARYA | R34: =IFERROR(__xludf.DUMMYFUNCTION("""COMPUTED_VALUE"""),"ISLAM") -> ISLAM | S34: =IFERROR(__xludf.DUMMYFUNCTION("""COMPUTED_VALUE"""),"SWASTA") -> SWASTA | T34: =IFERROR(__xludf.DUMMYFUNCTION("""COMPUTED_VALUE"""),"PUNGGUNG ATAS") -> PUNGGUNG ATAS | U34: =IFERROR(__xludf.DUMMYFUNCTION("""COMPUTED_VALUE"""),"") | V34: =IFERROR(__xludf.DUMMYFUNCTION("""COMPUTED_VALUE"""),"087819990888") -> 087819990888
B35: =IFERROR(__xludf.DUMMYFUNCTION("""COMPUTED_VALUE"""),45006.90724241898) -> 45006.907 | D35: =IFERROR(__xludf.DUMMYFUNCTION("""COMPUTED_VALUE"""),44936.0) -> 44936 | E35: =IFERROR(__xludf.DUMMYFUNCTION("""COMPUTED_VALUE"""),"01Jan") -> 01Jan | F35: =IFERROR(__xludf.DUMMYFUNCTION("""COMPUTED_VALUE"""),"2023") -> 2023 | G35: =IFERROR(__xludf.DUMMYFUNCTION("""COMPUTED_VALUE"""),"RYANDI ARDIENDA P.") -> RYANDI ARDIENDA P. | H35: =IFERROR(__xludf.DUMMYFUNCTION("""COMPUTED_VALUE"""),"R9323012323") -> R9323012323 | I35: =IFERROR(__xludf.DUMMYFUNCTION("""COMPUTED_VALUE"""),32.0) -> 32 | J35: =IFERROR(__xludf.DUMMYFUNCTION("""COMPUTED_VALUE"""),"25-34 tahun") -> 25-34 tahun | K35: =IFERROR(__xludf.DUMMYFUNCTION("""COMPUTED_VALUE"""),34184.0) -> 34184 | L35: =IFERROR(__xludf.DUMMYFUNCTION("""COMPUTED_VALUE"""),"LAKI-LAKI") -> LAKI-LAKI | M35: =IFERROR(__xludf.DUMMYFUNCTION("""COMPUTED_VALUE"""),"JL. P. H. HUSIN 2") -> JL. P. H. HUSIN 2 | R35: =IFERROR(__xludf.DUMMYFUNCTION("""COMPUTED_VALUE"""),"ISLAM") -> ISLAM | S35: =IFERROR(__xludf.DUMMYFUNCTION("""COMPUTED_VALUE"""),"BUMN") -> BUMN | T35: =IFERROR(__xludf.DUMMYFUNCTION("""COMPUTED_VALUE"""),"BAHU KANAN") -> BAHU KANAN | U35: =IFERROR(__xludf.DUMMYFUNCTION("""COMPUTED_VALUE"""),"") | V35: =IFERROR(__xludf.DUMMYFUNCTION("""COMPUTED_VALUE"""),"081255802323") -> 081255802323
B36: =IFERROR(__xludf.DUMMYFUNCTION("""COMPUTED_VALUE"""),45006.890850497686) -> 45006.891 | D36: =IFERROR(__xludf.DUMMYFUNCTION("""COMPUTED_VALUE"""),44936.762511574074) -> 44936.763 | E36: =IFERROR(__xludf.DUMMYFUNCTION("""COMPUTED_VALUE"""),"01Jan") -> 01Jan | F36: =IFERROR(__xludf.DUMMYFUNCTION("""COMPUTED_VALUE"""),"2023") -> 2023 | G36: =IFERROR(__xludf.DUMMYFUNCTION("""COMPUTED_VALUE"""),"NURYANTO") -> NURYANTO | H36: =IFERROR(__xludf.DUMMYFUNCTION("""COMPUTED_VALUE"""),"N5423010002") -> N5423010002 | I36: =IFERROR(__xludf.DUMMYFUNCTION("""COMPUTED_VALUE"""),71.0) -> 71 | J36: =IFERROR(__xludf.DUMMYFUNCTION("""COMPUTED_VALUE"""),"> 44 tahun") -> > 44 tahun | K36: =IFERROR(__xludf.DUMMYFUNCTION("""COMPUTED_VALUE"""),19988.0) -> 19988 | L36: =IFERROR(__xludf.DUMMYFUNCTION("""COMPUTED_VALUE"""),"LAKI-LAKI") -> LAKI-LAKI | M36: =IFERROR(__xludf.DUMMYFUNCTION("""COMPUTED_VALUE"""),"JL. NIRBAYA NO. 3") -> JL. NIRBAYA NO. 3 | R36: =IFERROR(__xludf.DUMMYFUNCTION("""COMPUTED_VALUE"""),"ISLAM") -> ISLAM | S36: =IFERROR(__xludf.DUMMYFUNCTION("""COMPUTED_VALUE"""),"PENSIUN") -> PENSIUN | T36: =IFERROR(__xludf.DUMMYFUNCTION("""COMPUTED_VALUE"""),"KAKI KIRI") -> KAKI KIRI | U36: =IFERROR(__xludf.DUMMYFUNCTION("""COMPUTED_VALUE"""),"") | V36: =IFERROR(__xludf.DUMMYFUNCTION("""COMPUTED_VALUE"""),"081256340002") -> 081256340002
B37: =IFERROR(__xludf.DUMMYFUNCTION("""COMPUTED_VALUE"""),45010.53389464121) -> 45010.534 | D37: =IFERROR(__xludf.DUMMYFUNCTION("""COMPUTED_VALUE"""),44937.0) -> 44937 | E37: =IFERROR(__xludf.DUMMYFUNCTION("""COMPUTED_VALUE"""),"01Jan") -> 01Jan | F37: =IFERROR(__xludf.DUMMYFUNCTION("""COMPUTED_VALUE"""),"2023") -> 2023 | G37: =IFERROR(__xludf.DUMMYFUNCTION("""COMPUTED_VALUE"""),"DIMAS PANDU HIDAYATULLAH") -> DIMAS PANDU HIDAYATULLAH | H37: =IFERROR(__xludf.DUMMYFUNCTION("""COMPUTED_VALUE"""),"D0023011314") -> D0023011314 | I37: =IFERROR(__xludf.DUMMYFUNCTION("""COMPUTED_VALUE"""),26.0) -> 26 | J37: =IFERROR(__xludf.DUMMYFUNCTION("""COMPUTED_VALUE"""),"25-34 tahun") -> 25-34 tahun | K37: =IFERROR(__xludf.DUMMYFUNCTION("""COMPUTED_VALUE"""),36670.0) -> 36670 | L37: =IFERROR(__xludf.DUMMYFUNCTION("""COMPUTED_VALUE"""),"LAKI-LAKI") -> LAKI-LAKI | M37: =IFERROR(__xludf.DUMMYFUNCTION("""COMPUTED_VALUE"""),"JL. KOMYOS SOEDARSO GG. HIDAYAH") -> JL. KOMYOS SOEDARSO GG. HIDAYAH | R37: =IFERROR(__xludf.DUMMYFUNCTION("""COMPUTED_VALUE"""),"ISLAM") -> ISLAM | S37: =IFERROR(__xludf.DUMMYFUNCTION("""COMPUTED_VALUE"""),"PELAJAR/MAHASISWA") -> PELAJAR/MAHASISWA | T37: =IFERROR(__xludf.DUMMYFUNCTION("""COMPUTED_VALUE"""),"ANKLE") -> ANKLE | U37: =IFERROR(__xludf.DUMMYFUNCTION("""COMPUTED_VALUE"""),"") | V37: =IFERROR(__xludf.DUMMYFUNCTION("""COMPUTED_VALUE"""),"0895611361314") -> 0895611361314
B38: =IFERROR(__xludf.DUMMYFUNCTION("""COMPUTED_VALUE"""),45006.89271108796) -> 45006.893 | D38: =IFERROR(__xludf.DUMMYFUNCTION("""COMPUTED_VALUE"""),44937.0) -> 44937 | E38: =IFERROR(__xludf.DUMMYFUNCTION("""COMPUTED_VALUE"""),"01Jan") -> 01Jan | F38: =IFERROR(__xludf.DUMMYFUNCTION("""COMPUTED_VALUE"""),"2023") -> 2023 | G38: =IFERROR(__xludf.DUMMYFUNCTION("""COMPUTED_VALUE"""),"EIVA RADE SIHO") -> EIVA RADE SIHO | H38: =IFERROR(__xludf.DUMMYFUNCTION("""COMPUTED_VALUE"""),"E7623015810") -> E7623015810 | I38: =IFERROR(__xludf.DUMMYFUNCTION("""COMPUTED_VALUE"""),49.0) -> 49 | J38: =IFERROR(__xludf.DUMMYFUNCTION("""COMPUTED_VALUE"""),"> 44 tahun") -> > 44 tahun | K38: =IFERROR(__xludf.DUMMYFUNCTION("""COMPUTED_VALUE"""),28091.0) -> 28091 | L38: =IFERROR(__xludf.DUMMYFUNCTION("""COMPUTED_VALUE"""),"PEREMPUAN") -> PEREMPUAN | M38: =IFERROR(__xludf.DUMMYFUNCTION("""COMPUTED_VALUE"""),"JL PERINTIS GG MADRASAH BLOK E10") -> JL PERINTIS GG MADRASAH BLOK E10 | R38: =IFERROR(__xludf.DUMMYFUNCTION("""COMPUTED_VALUE"""),"PROTESTAN") -> PROTESTAN | S38: =IFERROR(__xludf.DUMMYFUNCTION("""COMPUTED_VALUE"""),"SWASTA") -> SWASTA | T38: =IFERROR(__xludf.DUMMYFUNCTION("""COMPUTED_VALUE"""),"TANGAN KANAN") -> TANGAN KANAN | U38: =IFERROR(__xludf.DUMMYFUNCTION("""COMPUTED_VALUE"""),"-") -> - | V38: =IFERROR(__xludf.DUMMYFUNCTION("""COMPUTED_VALUE"""),"08125705810") -> 08125705810
B39: =IFERROR(__xludf.DUMMYFUNCTION("""COMPUTED_VALUE"""),44931.62291666667) -> 44931.623 | D39: =IFERROR(__xludf.DUMMYFUNCTION("""COMPUTED_VALUE"""),44937.0) -> 44937 | E39: =IFERROR(__xludf.DUMMYFUNCTION("""COMPUTED_VALUE"""),"01Jan") -> 01Jan | F39: =IFERROR(__xludf.DUMMYFUNCTION("""COMPUTED_VALUE"""),"2023") -> 2023 | G39: =IFERROR(__xludf.DUMMYFUNCTION("""COMPUTED_VALUE"""),"ERICK TRIENARDO") -> ERICK TRIENARDO | H39: =IFERROR(__xludf.DUMMYFUNCTION("""COMPUTED_VALUE"""),"E9723014638") -> E9723014638 | I39: =IFERROR(__xludf.DUMMYFUNCTION("""COMPUTED_VALUE"""),29.0) -> 29 | J39: =IFERROR(__xludf.DUMMYFUNCTION("""COMPUTED_VALUE"""),"25-34 tahun") -> 25-34 tahun | K39: =IFERROR(__xludf.DUMMYFUNCTION("""COMPUTED_VALUE"""),35502.0) -> 35502 | L39: =IFERROR(__xludf.DUMMYFUNCTION("""COMPUTED_VALUE"""),"LAKI-LAKI") -> LAKI-LAKI | M39: =IFERROR(__xludf.DUMMYFUNCTION("""COMPUTED_VALUE"""),"DESA SEMUDUN") -> DESA SEMUDUN | R39: =IFERROR(__xludf.DUMMYFUNCTION("""COMPUTED_VALUE"""),"PROTESTAN") -> PROTESTAN | S39: =IFERROR(__xludf.DUMMYFUNCTION("""COMPUTED_VALUE"""),"SWASTA") -> SWASTA | T39: =IFERROR(__xludf.DUMMYFUNCTION("""COMPUTED_VALUE"""),"ANKLE") -> ANKLE | U39: =IFERROR(__xludf.DUMMYFUNCTION("""COMPUTED_VALUE"""),"") | V39: =IFERROR(__xludf.DUMMYFUNCTION("""COMPUTED_VALUE"""),"081348474638") -> 081348474638
B40: =IFERROR(__xludf.DUMMYFUNCTION("""COMPUTED_VALUE"""),44917.445069444446) -> 44917.445 | D40: =IFERROR(__xludf.DUMMYFUNCTION("""COMPUTED_VALUE"""),44937.0) -> 44937 | E40: =IFERROR(__xludf.DUMMYFUNCTION("""COMPUTED_VALUE"""),"01Jan") -> 01Jan | F40: =IFERROR(__xludf.DUMMYFUNCTION("""COMPUTED_VALUE"""),"2023") -> 2023 | G40: =IFERROR(__xludf.DUMMYFUNCTION("""COMPUTED_VALUE"""),"FLAVIUS PANGAREGO") -> FLAVIUS PANGAREGO | H40: =IFERROR(__xludf.DUMMYFUNCTION("""COMPUTED_VALUE"""),"F9623012859") -> F9623012859 | I40: =IFERROR(__xludf.DUMMYFUNCTION("""COMPUTED_VALUE"""),30.0) -> 30 | J40: =IFERROR(__xludf.DUMMYFUNCTION("""COMPUTED_VALUE"""),"25-34 tahun") -> 25-34 tahun | K40: =IFERROR(__xludf.DUMMYFUNCTION("""COMPUTED_VALUE"""),35203.0) -> 35203 | L40: =IFERROR(__xludf.DUMMYFUNCTION("""COMPUTED_VALUE"""),"LAKI-LAKI") -> LAKI-LAKI | M40: =IFERROR(__xludf.DUMMYFUNCTION("""COMPUTED_VALUE"""),"JL. AMPERA NO. B7") -> JL. AMPERA NO. B7 | R40: =IFERROR(__xludf.DUMMYFUNCTION("""COMPUTED_VALUE"""),"KATOLIK") -> KATOLIK | S40: =IFERROR(__xludf.DUMMYFUNCTION("""COMPUTED_VALUE"""),"ASN") -> ASN | U40: =IFERROR(__xludf.DUMMYFUNCTION("""COMPUTED_VALUE"""),"FUTSAL") -> FUTSAL | V40: =IFERROR(__xludf.DUMMYFUNCTION("""COMPUTED_VALUE"""),"082298792859") -> 082298792859
B41: =IFERROR(__xludf.DUMMYFUNCTION("""COMPUTED_VALUE"""),45010.58521449074) -> 45010.585 | D41: =IFERROR(__xludf.DUMMYFUNCTION("""COMPUTED_VALUE"""),44937.0) -> 44937 | E41: =IFERROR(__xludf.DUMMYFUNCTION("""COMPUTED_VALUE"""),"01Jan") -> 01Jan | F41: =IFERROR(__xludf.DUMMYFUNCTION("""COMPUTED_VALUE"""),"2023") -> 2023 | G41: =IFERROR(__xludf.DUMMYFUNCTION("""COMPUTED_VALUE"""),"HERI RAHMANTO") -> HERI RAHMANTO | H41: =IFERROR(__xludf.DUMMYFUNCTION("""COMPUTED_VALUE"""),"H6123011926") -> H6123011926 | I41: =IFERROR(__xludf.DUMMYFUNCTION("""COMPUTED_VALUE"""),65.0) -> 65 | J41: =IFERROR(__xludf.DUMMYFUNCTION("""COMPUTED_VALUE"""),"> 44 tahun") -> > 44 tahun | K41: =IFERROR(__xludf.DUMMYFUNCTION("""COMPUTED_VALUE"""),22421.0) -> 22421 | L41: =IFERROR(__xludf.DUMMYFUNCTION("""COMPUTED_VALUE"""),"LAKI-LAKI") -> LAKI-LAKI | M41: =IFERROR(__xludf.DUMMYFUNCTION("""COMPUTED_VALUE"""),"JL. ALIANYANG ASPOL HONGGO PRANOTO") -> JL. ALIANYANG ASPOL HONGGO PRANOTO | R41: =IFERROR(__xludf.DUMMYFUNCTION("""COMPUTED_VALUE"""),"ISLAM") -> ISLAM | S41: =IFERROR(__xludf.DUMMYFUNCTION("""COMPUTED_VALUE"""),"") | T41: =IFERROR(__xludf.DUMMYFUNCTION("""COMPUTED_VALUE"""),"- TUNGKAI BAWAH") -> - TUNGKAI BAWAH | U41: =IFERROR(__xludf.DUMMYFUNCTION("""COMPUTED_VALUE"""),"") | V41: =IFERROR(__xludf.DUMMYFUNCTION("""COMPUTED_VALUE"""),"082127941926") -> 082127941926
B42: =IFERROR(__xludf.DUMMYFUNCTION("""COMPUTED_VALUE"""),44950.5268287037) -> 44950.527 | D42: =IFERROR(__xludf.DUMMYFUNCTION("""COMPUTED_VALUE"""),44937.0) -> 44937 | E42: =IFERROR(__xludf.DUMMYFUNCTION("""COMPUTED_VALUE"""),"01Jan") -> 01Jan | F42: =IFERROR(__xludf.DUMMYFUNCTION("""COMPUTED_VALUE"""),"2023") -> 2023 | G42: =IFERROR(__xludf.DUMMYFUNCTION("""COMPUTED_VALUE"""),"HILMIY DZAKIY") -> HILMIY DZAKIY | H42: =IFERROR(__xludf.DUMMYFUNCTION("""COMPUTED_VALUE"""),"H0923018457") -> H0923018457 | I42: =IFERROR(__xludf.DUMMYFUNCTION("""COMPUTED_VALUE"""),17.0) -> 17 | J42: =IFERROR(__xludf.DUMMYFUNCTION("""COMPUTED_VALUE"""),"< 18 tahun") -> < 18 tahun | K42: =IFERROR(__xludf.DUMMYFUNCTION("""COMPUTED_VALUE"""),39939.0) -> 39939 | L42: =IFERROR(__xludf.DUMMYFUNCTION("""COMPUTED_VALUE"""),"LAKI-LAKI") -> LAKI-LAKI | M42: =IFERROR(__xludf.DUMMYFUNCTION("""COMPUTED_VALUE"""),"JL URAY BAWADI GG SUDITRISNO") -> JL URAY BAWADI GG SUDITRISNO | R42: =IFERROR(__xludf.DUMMYFUNCTION("""COMPUTED_VALUE"""),"ISLAM") -> ISLAM | S42: =IFERROR(__xludf.DUMMYFUNCTION("""COMPUTED_VALUE"""),"PELAJAR/MAHASISWA") -> PELAJAR/MAHASISWA | U42: =IFERROR(__xludf.DUMMYFUNCTION("""COMPUTED_VALUE"""),"") | V42: =IFERROR(__xludf.DUMMYFUNCTION("""COMPUTED_VALUE"""),"081345438457") -> 081345438457
B43: =IFERROR(__xludf.DUMMYFUNCTION("""COMPUTED_VALUE"""),45011.63868106481) -> 45011.639 | D43: =IFERROR(__xludf.DUMMYFUNCTION("""COMPUTED_VALUE"""),44938.0) -> 44938 | E43: =IFERROR(__xludf.DUMMYFUNCTION("""COMPUTED_VALUE"""),"01Jan") -> 01Jan | F43: =IFERROR(__xludf.DUMMYFUNCTION("""COMPUTED_VALUE"""),"2023") -> 2023 | G43: =IFERROR(__xludf.DUMMYFUNCTION("""COMPUTED_VALUE"""),"BARIONO") -> BARIONO | H43: =IFERROR(__xludf.DUMMYFUNCTION("""COMPUTED_VALUE"""),"B7723012106") -> B7723012106 | I43: =IFERROR(__xludf.DUMMYFUNCTION("""COMPUTED_VALUE"""),49.0) -> 49 | J43: =IFERROR(__xludf.DUMMYFUNCTION("""COMPUTED_VALUE"""),"> 44 tahun") -> > 44 tahun | K43: =IFERROR(__xludf.DUMMYFUNCTION("""COMPUTED_VALUE"""),28292.0) -> 28292 | L43: =IFERROR(__xludf.DUMMYFUNCTION("""COMPUTED_VALUE"""),"LAKI-LAKI") -> LAKI-LAKI | M43: =IFERROR(__xludf.DUMMYFUNCTION("""COMPUTED_VALUE"""),"JL. PANGERAN NATAKUSUMA GG. SILIWANGI NO. 4A") -> JL. PANGERAN NATAKUSUMA GG. SILIWANGI NO. 4A | R43: =IFERROR(__xludf.DUMMYFUNCTION("""COMPUTED_VALUE"""),"ISLAM") -> ISLAM | S43: =IFERROR(__xludf.DUMMYFUNCTION("""COMPUTED_VALUE"""),"TNI/POLRI") -> TNI/POLRI | T43: =IFERROR(__xludf.DUMMYFUNCTION("""COMPUTED_VALUE"""),"BELL PALSY") -> BELL PALSY | U43: =IFERROR(__xludf.DUMMYFUNCTION("""COMPUTED_VALUE"""),"") | V43: =IFERROR(__xludf.DUMMYFUNCTION("""COMPUTED_VALUE"""),"081345212106") -> 081345212106
B44: =IFERROR(__xludf.DUMMYFUNCTION("""COMPUTED_VALUE"""),44973.39570601852) -> 44973.396 | D44: =IFERROR(__xludf.DUMMYFUNCTION("""COMPUTED_VALUE"""),44938.0) -> 44938 | E44: =IFERROR(__xludf.DUMMYFUNCTION("""COMPUTED_VALUE"""),"01Jan") -> 01Jan | F44: =IFERROR(__xludf.DUMMYFUNCTION("""COMPUTED_VALUE"""),"2023") -> 2023 | G44: =IFERROR(__xludf.DUMMYFUNCTION("""COMPUTED_VALUE"""),"BASORI") -> BASORI | H44: =IFERROR(__xludf.DUMMYFUNCTION("""COMPUTED_VALUE"""),"B9723011146") -> B9723011146 | I44: =IFERROR(__xludf.DUMMYFUNCTION("""COMPUTED_VALUE"""),29.0) -> 29 | J44: =IFERROR(__xludf.DUMMYFUNCTION("""COMPUTED_VALUE"""),"25-34 tahun") -> 25-34 tahun | K44: =IFERROR(__xludf.DUMMYFUNCTION("""COMPUTED_VALUE"""),35526.0) -> 35526 | L44: =IFERROR(__xludf.DUMMYFUNCTION("""COMPUTED_VALUE"""),"LAKI-LAKI") -> LAKI-LAKI | M44: =IFERROR(__xludf.DUMMYFUNCTION("""COMPUTED_VALUE"""),"PROF YAMIN") -> PROF YAMIN | R44: =IFERROR(__xludf.DUMMYFUNCTION("""COMPUTED_VALUE"""),"ISLAM") -> ISLAM | S44: =IFERROR(__xludf.DUMMYFUNCTION("""COMPUTED_VALUE"""),"SWASTA") -> SWASTA | U44: =IFERROR(__xludf.DUMMYFUNCTION("""COMPUTED_VALUE"""),"-") -> - | V44: =IFERROR(__xludf.DUMMYFUNCTION("""COMPUTED_VALUE"""),"08990991146") -> 08990991146
B45: =IFERROR(__xludf.DUMMYFUNCTION("""COMPUTED_VALUE"""),44956.554247685184) -> 44956.554 | D45: =IFERROR(__xludf.DUMMYFUNCTION("""COMPUTED_VALUE"""),44938.0) -> 44938 | E45: =IFERROR(__xludf.DUMMYFUNCTION("""COMPUTED_VALUE"""),"01Jan") -> 01Jan | F45: =IFERROR(__xludf.DUMMYFUNCTION("""COMPUTED_VALUE"""),"2023") -> 2023 | G45: =IFERROR(__xludf.DUMMYFUNCTION("""COMPUTED_VALUE"""),"CHALISA PUTRI PRISYLA") -> CHALISA PUTRI PRISYLA | H45: =IFERROR(__xludf.DUMMYFUNCTION("""COMPUTED_VALUE"""),"C0923018735") -> C0923018735 | I45: =IFERROR(__xludf.DUMMYFUNCTION("""COMPUTED_VALUE"""),16.0) -> 16 | J45: =IFERROR(__xludf.DUMMYFUNCTION("""COMPUTED_VALUE"""),"< 18 tahun") -> < 18 tahun | K45: =IFERROR(__xludf.DUMMYFUNCTION("""COMPUTED_VALUE"""),40129.0) -> 40129 | L45: =IFERROR(__xludf.DUMMYFUNCTION("""COMPUTED_VALUE"""),"PEREMPUAN") -> PEREMPUAN | M45: =IFERROR(__xludf.DUMMYFUNCTION("""COMPUTED_VALUE"""),"JL. SUI RAYA DALAM KOMP. TAMAN SUNGAI RAYA") -> JL. SUI RAYA DALAM KOMP. TAMAN SUNGAI RAYA | R45: =IFERROR(__xludf.DUMMYFUNCTION("""COMPUTED_VALUE"""),"ISLAM") -> ISLAM | S45: =IFERROR(__xludf.DUMMYFUNCTION("""COMPUTED_VALUE"""),"PELAJAR/MAHASISWA") -> PELAJAR/MAHASISWA | T45: =IFERROR(__xludf.DUMMYFUNCTION("""COMPUTED_VALUE"""),"SKOLIOSIS") -> SKOLIOSIS | U45: =IFERROR(__xludf.DUMMYFUNCTION("""COMPUTED_VALUE"""),"-") -> - | V45: =IFERROR(__xludf.DUMMYFUNCTION("""COMPUTED_VALUE"""),"08567988735") -> 08567988735
B46: =IFERROR(__xludf.DUMMYFUNCTION("""COMPUTED_VALUE"""),45011.659044201384) -> 45011.659 | D46: =IFERROR(__xludf.DUMMYFUNCTION("""COMPUTED_VALUE"""),44938.0) -> 44938 | E46: =IFERROR(__xludf.DUMMYFUNCTION("""COMPUTED_VALUE"""),"01Jan") -> 01Jan | F46: =IFERROR(__xludf.DUMMYFUNCTION("""COMPUTED_VALUE"""),"2023") -> 2023 | G46: =IFERROR(__xludf.DUMMYFUNCTION("""COMPUTED_VALUE"""),"HARDJONO") -> HARDJONO | H46: =IFERROR(__xludf.DUMMYFUNCTION("""COMPUTED_VALUE"""),"H4623015667") -> H4623015667 | I46: =IFERROR(__xludf.DUMMYFUNCTION("""COMPUTED_VALUE"""),80.0) -> 80 | J46: =IFERROR(__xludf.DUMMYFUNCTION("""COMPUTED_VALUE"""),"> 44 tahun") -> > 44 tahun | K46: =IFERROR(__xludf.DUMMYFUNCTION("""COMPUTED_VALUE"""),16864.0) -> 16864 | L46: =IFERROR(__xludf.DUMMYFUNCTION("""COMPUTED_VALUE"""),"LAKI-LAKI") -> LAKI-LAKI | M46: =IFERROR(__xludf.DUMMYFUNCTION("""COMPUTED_VALUE"""),"JL. KESEHATAN GG. SEJAHTERA") -> JL. KESEHATAN GG. SEJAHTERA | R46: =IFERROR(__xludf.DUMMYFUNCTION("""COMPUTED_VALUE"""),"ISLAM") -> ISLAM | S46: =IFERROR(__xludf.DUMMYFUNCTION("""COMPUTED_VALUE"""),"PENSIUN") -> PENSIUN | T46: =IFERROR(__xludf.DUMMYFUNCTION("""COMPUTED_VALUE"""),"STROKE") -> STROKE | U46: =IFERROR(__xludf.DUMMYFUNCTION("""COMPUTED_VALUE"""),"") | V46: =IFERROR(__xludf.DUMMYFUNCTION("""COMPUTED_VALUE"""),"08115755667") -> 08115755667
B47: =IFERROR(__xludf.DUMMYFUNCTION("""COMPUTED_VALUE"""),45006.88994719907) -> 45006.89 | D47: =IFERROR(__xludf.DUMMYFUNCTION("""COMPUTED_VALUE"""),44938.0) -> 44938 | E47: =IFERROR(__xludf.DUMMYFUNCTION("""COMPUTED_VALUE"""),"01Jan") -> 01Jan | F47: =IFERROR(__xludf.DUMMYFUNCTION("""COMPUTED_VALUE"""),"2023") -> 2023 | G47: =IFERROR(__xludf.DUMMYFUNCTION("""COMPUTED_VALUE"""),"JUSWARDI") -> JUSWARDI | H47: =IFERROR(__xludf.DUMMYFUNCTION("""COMPUTED_VALUE"""),"J6223019000") -> J6223019000 | I47: =IFERROR(__xludf.DUMMYFUNCTION("""COMPUTED_VALUE"""),63.0) -> 63 | J47: =IFERROR(__xludf.DUMMYFUNCTION("""COMPUTED_VALUE"""),"> 44 tahun") -> > 44 tahun | K47: =IFERROR(__xludf.DUMMYFUNCTION("""COMPUTED_VALUE"""),22854.0) -> 22854 | L47: =IFERROR(__xludf.DUMMYFUNCTION("""COMPUTED_VALUE"""),"LAKI-LAKI") -> LAKI-LAKI | M47: =IFERROR(__xludf.DUMMYFUNCTION("""COMPUTED_VALUE"""),"SEKURA") -> SEKURA | R47: =IFERROR(__xludf.DUMMYFUNCTION("""COMPUTED_VALUE"""),"ISLAM") -> ISLAM | S47: =IFERROR(__xludf.DUMMYFUNCTION("""COMPUTED_VALUE"""),"PENSIUN") -> PENSIUN | T47: =IFERROR(__xludf.DUMMYFUNCTION("""COMPUTED_VALUE"""),"STROKE") -> STROKE | U47: =IFERROR(__xludf.DUMMYFUNCTION("""COMPUTED_VALUE"""),"-") -> - | V47: =IFERROR(__xludf.DUMMYFUNCTION("""COMPUTED_VALUE"""),"081345489000") -> 081345489000
B48: =IFERROR(__xludf.DUMMYFUNCTION("""COMPUTED_VALUE"""),45006.87765203704) -> 45006.878 | D48: =IFERROR(__xludf.DUMMYFUNCTION("""COMPUTED_VALUE"""),44938.0) -> 44938 | E48: =IFERROR(__xludf.DUMMYFUNCTION("""COMPUTED_VALUE"""),"01Jan") -> 01Jan | F48: =IFERROR(__xludf.DUMMYFUNCTION("""COMPUTED_VALUE"""),"2023") -> 2023 | G48: =IFERROR(__xludf.DUMMYFUNCTION("""COMPUTED_VALUE"""),"TUTI NOVITA") -> TUTI NOVITA | H48: =IFERROR(__xludf.DUMMYFUNCTION("""COMPUTED_VALUE"""),"T7223011339") -> T7223011339 | I48: =IFERROR(__xludf.DUMMYFUNCTION("""COMPUTED_VALUE"""),53.0) -> 53 | J48: =IFERROR(__xludf.DUMMYFUNCTION("""COMPUTED_VALUE"""),"> 44 tahun") -> > 44 tahun | K48: =IFERROR(__xludf.DUMMYFUNCTION("""COMPUTED_VALUE"""),26608.0) -> 26608 | L48: =IFERROR(__xludf.DUMMYFUNCTION("""COMPUTED_VALUE"""),"PEREMPUAN") -> PEREMPUAN | M48: =IFERROR(__xludf.DUMMYFUNCTION("""COMPUTED_VALUE"""),"JL PUTRI DARANANTE 88A") -> JL PUTRI DARANANTE 88A | R48: =IFERROR(__xludf.DUMMYFUNCTION("""COMPUTED_VALUE"""),"ISLAM") -> ISLAM | S48: =IFERROR(__xludf.DUMMYFUNCTION("""COMPUTED_VALUE"""),"RUMAH TANGGA") -> RUMAH TANGGA | T48: =IFERROR(__xludf.DUMMYFUNCTION("""COMPUTED_VALUE"""),"KAKI KANAN") -> KAKI KANAN | U48: =IFERROR(__xludf.DUMMYFUNCTION("""COMPUTED_VALUE"""),"-") -> - | V48: =IFERROR(__xludf.DUMMYFUNCTION("""COMPUTED_VALUE"""),"085252521339") -> 085252521339
B49: =IFERROR(__xludf.DUMMYFUNCTION("""COMPUTED_VALUE"""),45010.71009674769) -> 45010.71 | D49: =IFERROR(__xludf.DUMMYFUNCTION("""COMPUTED_VALUE"""),44940.0) -> 44940 | E49: =IFERROR(__xludf.DUMMYFUNCTION("""COMPUTED_VALUE"""),"01Jan") -> 01Jan | F49: =IFERROR(__xludf.DUMMYFUNCTION("""COMPUTED_VALUE"""),"2023") -> 2023 | G49: =IFERROR(__xludf.DUMMYFUNCTION("""COMPUTED_VALUE"""),"HENDRI WAHYUDHI") -> HENDRI WAHYUDHI | H49: =IFERROR(__xludf.DUMMYFUNCTION("""COMPUTED_VALUE"""),"H7623014100") -> H7623014100 | I49: =IFERROR(__xludf.DUMMYFUNCTION("""COMPUTED_VALUE"""),49.0) -> 49 | J49: =IFERROR(__xludf.DUMMYFUNCTION("""COMPUTED_VALUE"""),"> 44 tahun") -> > 44 tahun | K49: =IFERROR(__xludf.DUMMYFUNCTION("""COMPUTED_VALUE"""),28096.0) -> 28096 | L49: =IFERROR(__xludf.DUMMYFUNCTION("""COMPUTED_VALUE"""),"LAKI-LAKI") -> LAKI-LAKI | M49: =IFERROR(__xludf.DUMMYFUNCTION("""COMPUTED_VALUE"""),"JL. KAPTEN TENDEAN NO. 17") -> JL. KAPTEN TENDEAN NO. 17 | R49: =IFERROR(__xludf.DUMMYFUNCTION("""COMPUTED_VALUE"""),"PROTESTAN") -> PROTESTAN | S49: =IFERROR(__xludf.DUMMYFUNCTION("""COMPUTED_VALUE"""),"SWASTA") -> SWASTA | T49: =IFERROR(__xludf.DUMMYFUNCTION("""COMPUTED_VALUE"""),"PINGGANG") -> PINGGANG | U49: =IFERROR(__xludf.DUMMYFUNCTION("""COMPUTED_VALUE"""),"") | V49: =IFERROR(__xludf.DUMMYFUNCTION("""COMPUTED_VALUE"""),"082157684100") -> 082157684100
B50: =IFERROR(__xludf.DUMMYFUNCTION("""COMPUTED_VALUE"""),44983.45313657408) -> 44983.453 | D50: =IFERROR(__xludf.DUMMYFUNCTION("""COMPUTED_VALUE"""),44940.0) -> 44940 | E50: =IFERROR(__xludf.DUMMYFUNCTION("""COMPUTED_VALUE"""),"01Jan") -> 01Jan | F50: =IFERROR(__xludf.DUMMYFUNCTION("""COMPUTED_VALUE"""),"2023") -> 2023 | G50: =IFERROR(__xludf.DUMMYFUNCTION("""COMPUTED_VALUE"""),"HERLINA AGUSTININGSIH") -> HERLINA AGUSTININGSIH | H50: =IFERROR(__xludf.DUMMYFUNCTION("""COMPUTED_VALUE"""),"H8523011399") -> H8523011399 | I50: =IFERROR(__xludf.DUMMYFUNCTION("""COMPUTED_VALUE"""),40.0) -> 40 | J50: =IFERROR(__xludf.DUMMYFUNCTION("""COMPUTED_VALUE"""),"35-44 tahun") -> 35-44 tahun | K50: =IFERROR(__xludf.DUMMYFUNCTION("""COMPUTED_VALUE"""),31274.0) -> 31274 | L50: =IFERROR(__xludf.DUMMYFUNCTION("""COMPUTED_VALUE"""),"PEREMPUAN") -> PEREMPUAN | M50: =IFERROR(__xludf.DUMMYFUNCTION("""COMPUTED_VALUE"""),"JL PROF M YAMIN GG TELUK PAKEDAI NO 30") -> JL PROF M YAMIN GG TELUK PAKEDAI NO 30 | R50: =IFERROR(__xludf.DUMMYFUNCTION("""COMPUTED_VALUE"""),"ISLAM") -> ISLAM | S50: =IFERROR(__xludf.DUMMYFUNCTION("""COMPUTED_VALUE"""),"ASN") -> ASN | T50: =IFERROR(__xludf.DUMMYFUNCTION("""COMPUTED_VALUE"""),"KAKI") -> KAKI | U50: =IFERROR(__xludf.DUMMYFUNCTION("""COMPUTED_VALUE"""),"SKIPPING") -> SKIPPING | V50: =IFERROR(__xludf.DUMMYFUNCTION("""COMPUTED_VALUE"""),"081345081399") -> 081345081399
B51: =IFERROR(__xludf.DUMMYFUNCTION("""COMPUTED_VALUE"""),44956.55168981481) -> 44956.552 | D51: =IFERROR(__xludf.DUMMYFUNCTION("""COMPUTED_VALUE"""),44940.0) -> 44940 | E51: =IFERROR(__xludf.DUMMYFUNCTION("""COMPUTED_VALUE"""),"01Jan") -> 01Jan | F51: =IFERROR(__xludf.DUMMYFUNCTION("""COMPUTED_VALUE"""),"2023") -> 2023 | G51: =IFERROR(__xludf.DUMMYFUNCTION("""COMPUTED_VALUE"""),"JOCELYN WAHYUDHI") -> JOCELYN WAHYUDHI | H51: =IFERROR(__xludf.DUMMYFUNCTION("""COMPUTED_VALUE"""),"J0623019005") -> J0623019005 | I51: =IFERROR(__xludf.DUMMYFUNCTION("""COMPUTED_VALUE"""),20.0) -> 20 | J51: =IFERROR(__xludf.DUMMYFUNCTION("""COMPUTED_VALUE"""),"18-24 tahun") -> 18-24 tahun | K51: =IFERROR(__xludf.DUMMYFUNCTION("""COMPUTED_VALUE"""),38767.0) -> 38767 | L51: =IFERROR(__xludf.DUMMYFUNCTION("""COMPUTED_VALUE"""),"PEREMPUAN") -> PEREMPUAN | M51: =IFERROR(__xludf.DUMMYFUNCTION("""COMPUTED_VALUE"""),"JL. KAPTEN TENDEAN NO. 17") -> JL. KAPTEN TENDEAN NO. 17 | R51: =IFERROR(__xludf.DUMMYFUNCTION("""COMPUTED_VALUE"""),"PROTESTAN") -> PROTESTAN | S51: =IFERROR(__xludf.DUMMYFUNCTION("""COMPUTED_VALUE"""),"PELAJAR/MAHASISWA") -> PELAJAR/MAHASISWA | T51: =IFERROR(__xludf.DUMMYFUNCTION("""COMPUTED_VALUE"""),"SKOLIOSIS") -> SKOLIOSIS | U51: =IFERROR(__xludf.DUMMYFUNCTION("""COMPUTED_VALUE"""),"DUDUK LAMA") -> DUDUK LAMA | V51: =IFERROR(__xludf.DUMMYFUNCTION("""COMPUTED_VALUE"""),"087878219005") -> 087878219005
B52: =IFERROR(__xludf.DUMMYFUNCTION("""COMPUTED_VALUE"""),45006.584449745365) -> 45006.584 | D52: =IFERROR(__xludf.DUMMYFUNCTION("""COMPUTED_VALUE"""),44940.0) -> 44940 | E52: =IFERROR(__xludf.DUMMYFUNCTION("""COMPUTED_VALUE"""),"01Jan") -> 01Jan | F52: =IFERROR(__xludf.DUMMYFUNCTION("""COMPUTED_VALUE"""),"2023") -> 2023 | G52: =IFERROR(__xludf.DUMMYFUNCTION("""COMPUTED_VALUE"""),"JON ALI") -> JON ALI | H52: =IFERROR(__xludf.DUMMYFUNCTION("""COMPUTED_VALUE"""),"J8823019998") -> J8823019998 | I52: =IFERROR(__xludf.DUMMYFUNCTION("""COMPUTED_VALUE"""),38.0) -> 38 | J52: =IFERROR(__xludf.DUMMYFUNCTION("""COMPUTED_VALUE"""),"35-44 tahun") -> 35-44 tahun | K52: =IFERROR(__xludf.DUMMYFUNCTION("""COMPUTED_VALUE"""),32239.0) -> 32239 | L52: =IFERROR(__xludf.DUMMYFUNCTION("""COMPUTED_VALUE"""),"LAKI-LAKI") -> LAKI-LAKI | M52: =IFERROR(__xludf.DUMMYFUNCTION("""COMPUTED_VALUE"""),"JL. D. I PANJAITAN NO. 19") -> JL. D. I PANJAITAN NO. 19 | R52: =IFERROR(__xludf.DUMMYFUNCTION("""COMPUTED_VALUE"""),"BUDDHA") -> BUDDHA | S52: =IFERROR(__xludf.DUMMYFUNCTION("""COMPUTED_VALUE"""),"WIRASWASTA") -> WIRASWASTA | T52: =IFERROR(__xludf.DUMMYFUNCTION("""COMPUTED_VALUE"""),"STROKE") -> STROKE | U52: =IFERROR(__xludf.DUMMYFUNCTION("""COMPUTED_VALUE"""),"-") -> - | V52: =IFERROR(__xludf.DUMMYFUNCTION("""COMPUTED_VALUE"""),"082111899998") -> 082111899998
B53: =IFERROR(__xludf.DUMMYFUNCTION("""COMPUTED_VALUE"""),44934.477488425924) -> 44934.477 | D53: =IFERROR(__xludf.DUMMYFUNCTION("""COMPUTED_VALUE"""),44940.0) -> 44940 | E53: =IFERROR(__xludf.DUMMYFUNCTION("""COMPUTED_VALUE"""),"01Jan") -> 01Jan | F53: =IFERROR(__xludf.DUMMYFUNCTION("""COMPUTED_VALUE"""),"2023") -> 2023 | G53: =IFERROR(__xludf.DUMMYFUNCTION("""COMPUTED_VALUE"""),"LIWONO") -> LIWONO | H53: =IFERROR(__xludf.DUMMYFUNCTION("""COMPUTED_VALUE"""),"L6623014041") -> L6623014041 | I53: =IFERROR(__xludf.DUMMYFUNCTION("""COMPUTED_VALUE"""),59.0) -> 59 | J53: =IFERROR(__xludf.DUMMYFUNCTION("""COMPUTED_VALUE"""),"> 44 tahun") -> > 44 tahun | K53: =IFERROR(__xludf.DUMMYFUNCTION("""COMPUTED_VALUE"""),24350.0) -> 24350 | L53: =IFERROR(__xludf.DUMMYFUNCTION("""COMPUTED_VALUE"""),"LAKI-LAKI") -> LAKI-LAKI | M53: =IFERROR(__xludf.DUMMYFUNCTION("""COMPUTED_VALUE"""),"JL SUKA MULIA GG SUKMA NO 1") -> JL SUKA MULIA GG SUKMA NO 1 | R53: =IFERROR(__xludf.DUMMYFUNCTION("""COMPUTED_VALUE"""),"ISLAM") -> ISLAM | S53: =IFERROR(__xludf.DUMMYFUNCTION("""COMPUTED_VALUE"""),"ASN") -> ASN | T53: =IFERROR(__xludf.DUMMYFUNCTION("""COMPUTED_VALUE"""),"BAHU") -> BAHU | U53: =IFERROR(__xludf.DUMMYFUNCTION("""COMPUTED_VALUE"""),"") | V53: =IFERROR(__xludf.DUMMYFUNCTION("""COMPUTED_VALUE"""),"08125614041") -> 08125614041
B54: =IFERROR(__xludf.DUMMYFUNCTION("""COMPUTED_VALUE"""),45006.969433969905) -> 45006.969 | D54: =IFERROR(__xludf.DUMMYFUNCTION("""COMPUTED_VALUE"""),44941.0) -> 44941 | E54: =IFERROR(__xludf.DUMMYFUNCTION("""COMPUTED_VALUE"""),"01Jan") -> 01Jan | F54: =IFERROR(__xludf.DUMMYFUNCTION("""COMPUTED_VALUE"""),"2023") -> 2023 | G54: =IFERROR(__xludf.DUMMYFUNCTION("""COMPUTED_VALUE"""),"AGUS SETIAWAN") -> AGUS SETIAWAN | H54: =IFERROR(__xludf.DUMMYFUNCTION("""COMPUTED_VALUE"""),"A9523018347") -> A9523018347 | I54: =IFERROR(__xludf.DUMMYFUNCTION("""COMPUTED_VALUE"""),30.0) -> 30 | J54: =IFERROR(__xludf.DUMMYFUNCTION("""COMPUTED_VALUE"""),"25-34 tahun") -> 25-34 tahun | K54: =IFERROR(__xludf.DUMMYFUNCTION("""COMPUTED_VALUE"""),34916.0) -> 34916 | L54: =IFERROR(__xludf.DUMMYFUNCTION("""COMPUTED_VALUE"""),"LAKI-LAKI") -> LAKI-LAKI | M54: =IFERROR(__xludf.DUMMYFUNCTION("""COMPUTED_VALUE"""),"JL. H. R. ARAHMAN GG. BUKIT SEBEDANG NO. 2") -> JL. H. R. ARAHMAN GG. BUKIT SEBEDANG NO. 2 | R54: =IFERROR(__xludf.DUMMYFUNCTION("""COMPUTED_VALUE"""),"ISLAM") -> ISLAM | S54: =IFERROR(__xludf.DUMMYFUNCTION("""COMPUTED_VALUE"""),"BUMD") -> BUMD | V54: =IFERROR(__xludf.DUMMYFUNCTION("""COMPUTED_VALUE"""),"08539338347") -> 08539338347
B55: =IFERROR(__xludf.DUMMYFUNCTION("""COMPUTED_VALUE"""),45011.177046620374) -> 45011.177 | D55: =IFERROR(__xludf.DUMMYFUNCTION("""COMPUTED_VALUE"""),44941.0) -> 44941 | E55: =IFERROR(__xludf.DUMMYFUNCTION("""COMPUTED_VALUE"""),"01Jan") -> 01Jan | F55: =IFERROR(__xludf.DUMMYFUNCTION("""COMPUTED_VALUE"""),"2023") -> 2023 | G55: =IFERROR(__xludf.DUMMYFUNCTION("""COMPUTED_VALUE"""),"ANGGA HENDHARSA") -> ANGGA HENDHARSA | H55: =IFERROR(__xludf.DUMMYFUNCTION("""COMPUTED_VALUE"""),"A9023010811") -> A9023010811 | I55: =IFERROR(__xludf.DUMMYFUNCTION("""COMPUTED_VALUE"""),36.0) -> 36 | J55: =IFERROR(__xludf.DUMMYFUNCTION("""COMPUTED_VALUE"""),"35-44 tahun") -> 35-44 tahun | K55: =IFERROR(__xludf.DUMMYFUNCTION("""COMPUTED_VALUE"""),33036.0) -> 33036 | L55: =IFERROR(__xludf.DUMMYFUNCTION("""COMPUTED_VALUE"""),"LAKI-LAKI") -> LAKI-LAKI | M55: =IFERROR(__xludf.DUMMYFUNCTION("""COMPUTED_VALUE"""),"JL. TANI MAKMUR GG. SAMBAS") -> JL. TANI MAKMUR GG. SAMBAS | R55: =IFERROR(__xludf.DUMMYFUNCTION("""COMPUTED_VALUE"""),"ISLAM") -> ISLAM | S55: =IFERROR(__xludf.DUMMYFUNCTION("""COMPUTED_VALUE"""),"DOSEN/GURU") -> DOSEN/GURU | T55: =IFERROR(__xludf.DUMMYFUNCTION("""COMPUTED_VALUE"""),"ANKLE KANAN") -> ANKLE KANAN | U55: =IFERROR(__xludf.DUMMYFUNCTION("""COMPUTED_VALUE"""),"BASKET") -> BASKET | V55: =IFERROR(__xludf.DUMMYFUNCTION("""COMPUTED_VALUE"""),"081253800811") -> 081253800811
B56: =IFERROR(__xludf.DUMMYFUNCTION("""COMPUTED_VALUE"""),44934.678935185184) -> 44934.679 | D56: =IFERROR(__xludf.DUMMYFUNCTION("""COMPUTED_VALUE"""),44941.0) -> 44941 | E56: =IFERROR(__xludf.DUMMYFUNCTION("""COMPUTED_VALUE"""),"01Jan") -> 01Jan | F56: =IFERROR(__xludf.DUMMYFUNCTION("""COMPUTED_VALUE"""),"2023") -> 2023 | G56: =IFERROR(__xludf.DUMMYFUNCTION("""COMPUTED_VALUE"""),"HELEN RANDY FEBRIANA") -> HELEN RANDY FEBRIANA | H56: =IFERROR(__xludf.DUMMYFUNCTION("""COMPUTED_VALUE"""),"H8723012002") -> H8723012002 | I56: =IFERROR(__xludf.DUMMYFUNCTION("""COMPUTED_VALUE"""),39.0) -> 39 | J56: =IFERROR(__xludf.DUMMYFUNCTION("""COMPUTED_VALUE"""),"35-44 tahun") -> 35-44 tahun | K56: =IFERROR(__xludf.DUMMYFUNCTION("""COMPUTED_VALUE"""),31828.0) -> 31828 | L56: =IFERROR(__xludf.DUMMYFUNCTION("""COMPUTED_VALUE"""),"PEREMPUAN") -> PEREMPUAN | M56: =IFERROR(__xludf.DUMMYFUNCTION("""COMPUTED_VALUE"""),"JL. PURNAMA II GG. PURNAMA SEDERHANA NO. 27") -> JL. PURNAMA II GG. PURNAMA SEDERHANA NO. 27 | R56: =IFERROR(__xludf.DUMMYFUNCTION("""COMPUTED_VALUE"""),"KATOLIK") -> KATOLIK | S56: =IFERROR(__xludf.DUMMYFUNCTION("""COMPUTED_VALUE"""),"BUMD") -> BUMD | T56: =IFERROR(__xludf.DUMMYFUNCTION("""COMPUTED_VALUE"""),"PUNGGUNG") -> PUNGGUNG | U56: =IFERROR(__xludf.DUMMYFUNCTION("""COMPUTED_VALUE"""),"") | V56: =IFERROR(__xludf.DUMMYFUNCTION("""COMPUTED_VALUE"""),"08115652002") -> 08115652002
B57: =IFERROR(__xludf.DUMMYFUNCTION("""COMPUTED_VALUE"""),45010.671064375) -> 45010.671 | D57: =IFERROR(__xludf.DUMMYFUNCTION("""COMPUTED_VALUE"""),44942.0) -> 44942 | E57: =IFERROR(__xludf.DUMMYFUNCTION("""COMPUTED_VALUE"""),"01Jan") -> 01Jan | F57: =IFERROR(__xludf.DUMMYFUNCTION("""COMPUTED_VALUE"""),"2023") -> 2023 | G57: =IFERROR(__xludf.DUMMYFUNCTION("""COMPUTED_VALUE"""),"ELFA MARTIAN") -> ELFA MARTIAN | H57: =IFERROR(__xludf.DUMMYFUNCTION("""COMPUTED_VALUE"""),"E8423012220") -> E8423012220 | I57: =IFERROR(__xludf.DUMMYFUNCTION("""COMPUTED_VALUE"""),42.0) -> 42 | J57: =IFERROR(__xludf.DUMMYFUNCTION("""COMPUTED_VALUE"""),"35-44 tahun") -> 35-44 tahun | K57: =IFERROR(__xludf.DUMMYFUNCTION("""COMPUTED_VALUE"""),30742.0) -> 30742 | L57: =IFERROR(__xludf.DUMMYFUNCTION("""COMPUTED_VALUE"""),"LAKI-LAKI") -> LAKI-LAKI | M57: =IFERROR(__xludf.DUMMYFUNCTION("""COMPUTED_VALUE"""),"JL. PURNAMA 2 GG. NURUL HASANAH") -> JL. PURNAMA 2 GG. NURUL HASANAH | R57: =IFERROR(__xludf.DUMMYFUNCTION("""COMPUTED_VALUE"""),"ISLAM") -> ISLAM | S57: =IFERROR(__xludf.DUMMYFUNCTION("""COMPUTED_VALUE"""),"SWASTA") -> SWASTA | U57: =IFERROR(__xludf.DUMMYFUNCTION("""COMPUTED_VALUE"""),"") | V57: =IFERROR(__xludf.DUMMYFUNCTION("""COMPUTED_VALUE"""),"08524522220") -> 08524522220
B58: =IFERROR(__xludf.DUMMYFUNCTION("""COMPUTED_VALUE"""),45006.88734743056) -> 45006.887 | D58: =IFERROR(__xludf.DUMMYFUNCTION("""COMPUTED_VALUE"""),44942.0) -> 44942 | E58: =IFERROR(__xludf.DUMMYFUNCTION("""COMPUTED_VALUE"""),"01Jan") -> 01Jan | F58: =IFERROR(__xludf.DUMMYFUNCTION("""COMPUTED_VALUE"""),"2023") -> 2023 | G58: =IFERROR(__xludf.DUMMYFUNCTION("""COMPUTED_VALUE"""),"M. ARKANA DISA AL MASRI") -> M. ARKANA DISA AL MASRI | H58: =IFERROR(__xludf.DUMMYFUNCTION("""COMPUTED_VALUE"""),"M1323013389") -> M1323013389 | I58: =IFERROR(__xludf.DUMMYFUNCTION("""COMPUTED_VALUE"""),13.0) -> 13 | J58: =IFERROR(__xludf.DUMMYFUNCTION("""COMPUTED_VALUE"""),"< 18 tahun") -> < 18 tahun | K58: =IFERROR(__xludf.DUMMYFUNCTION("""COMPUTED_VALUE"""),41413.0) -> 41413 | L58: =IFERROR(__xludf.DUMMYFUNCTION("""COMPUTED_VALUE"""),"LAKI-LAKI") -> LAKI-LAKI | M58: =IFERROR(__xludf.DUMMYFUNCTION("""COMPUTED_VALUE"""),"JLPROF M YAMIN GG KEMUNING JALUR 3 NO 55") -> JLPROF M YAMIN GG KEMUNING JALUR 3 NO 55 | R58: =IFERROR(__xludf.DUMMYFUNCTION("""COMPUTED_VALUE"""),"ISLAM") -> ISLAM | S58: =IFERROR(__xludf.DUMMYFUNCTION("""COMPUTED_VALUE"""),"PELAJAR/MAHASISWA") -> PELAJAR/MAHASISWA | T58: =IFERROR(__xludf.DUMMYFUNCTION("""COMPUTED_VALUE"""),"ANKLE") -> ANKLE | U58: =IFERROR(__xludf.DUMMYFUNCTION("""COMPUTED_VALUE"""),"-") -> - | V58: =IFERROR(__xludf.DUMMYFUNCTION("""COMPUTED_VALUE"""),"0816223389") -> 0816223389
B59: =IFERROR(__xludf.DUMMYFUNCTION("""COMPUTED_VALUE"""),44857.73925293981) -> 44857.739 | D59: =IFERROR(__xludf.DUMMYFUNCTION("""COMPUTED_VALUE"""),44942.0) -> 44942 | E59: =IFERROR(__xludf.DUMMYFUNCTION("""COMPUTED_VALUE"""),"01Jan") -> 01Jan | F59: =IFERROR(__xludf.DUMMYFUNCTION("""COMPUTED_VALUE"""),"2023") -> 2023 | G59: =IFERROR(__xludf.DUMMYFUNCTION("""COMPUTED_VALUE"""),"SRI MARTINI") -> SRI MARTINI | H59: =IFERROR(__xludf.DUMMYFUNCTION("""COMPUTED_VALUE"""),"S6123013882") -> S6123013882 | I59: =IFERROR(__xludf.DUMMYFUNCTION("""COMPUTED_VALUE"""),65.0) -> 65 | J59: =IFERROR(__xludf.DUMMYFUNCTION("""COMPUTED_VALUE"""),"> 44 tahun") -> > 44 tahun | K59: =IFERROR(__xludf.DUMMYFUNCTION("""COMPUTED_VALUE"""),22362.0) -> 22362 | L59: =IFERROR(__xludf.DUMMYFUNCTION("""COMPUTED_VALUE"""),"PEREMPUAN") -> PEREMPUAN | M59: =IFERROR(__xludf.DUMMYFUNCTION("""COMPUTED_VALUE"""),"JL PERDAMAIAN KOMP ALAM DAMAI INDAH 3 NO A16") -> JL PERDAMAIAN KOMP ALAM DAMAI INDAH 3 NO A16 | R59: =IFERROR(__xludf.DUMMYFUNCTION("""COMPUTED_VALUE"""),"ISLAM") -> ISLAM | S59: =IFERROR(__xludf.DUMMYFUNCTION("""COMPUTED_VALUE"""),"RUMAH TANGGA") -> RUMAH TANGGA | T59: =IFERROR(__xludf.DUMMYFUNCTION("""COMPUTED_VALUE"""),"BAHU") -> BAHU | U59: =IFERROR(__xludf.DUMMYFUNCTION("""COMPUTED_VALUE"""),"-") -> - | V59: =IFERROR(__xludf.DUMMYFUNCTION("""COMPUTED_VALUE"""),"081254483882") -> 081254483882
B60: =IFERROR(__xludf.DUMMYFUNCTION("""COMPUTED_VALUE"""),45010.52470618056) -> 45010.525 | D60: =IFERROR(__xludf.DUMMYFUNCTION("""COMPUTED_VALUE"""),44943.0) -> 44943 | E60: =IFERROR(__xludf.DUMMYFUNCTION("""COMPUTED_VALUE"""),"01Jan") -> 01Jan | F60: =IFERROR(__xludf.DUMMYFUNCTION("""COMPUTED_VALUE"""),"2023") -> 2023 | G60: =IFERROR(__xludf.DUMMYFUNCTION("""COMPUTED_VALUE"""),"AMINAH") -> AMINAH | H60: =IFERROR(__xludf.DUMMYFUNCTION("""COMPUTED_VALUE"""),"A6323017817") -> A6323017817 | I60: =IFERROR(__xludf.DUMMYFUNCTION("""COMPUTED_VALUE"""),62.0) -> 62 | J60: =IFERROR(__xludf.DUMMYFUNCTION("""COMPUTED_VALUE"""),"> 44 tahun") -> > 44 tahun | K60: =IFERROR(__xludf.DUMMYFUNCTION("""COMPUTED_VALUE"""),23320.0) -> 23320 | L60: =IFERROR(__xludf.DUMMYFUNCTION("""COMPUTED_VALUE"""),"PEREMPUAN") -> PEREMPUAN | M60: =IFERROR(__xludf.DUMMYFUNCTION("""COMPUTED_VALUE"""),"JL PERDAMAIAN") -> JL PERDAMAIAN | P60: =IFERROR(__xludf.DUMMYFUNCTION("""COMPUTED_VALUE"""),"") | R60: =IFERROR(__xludf.DUMMYFUNCTION("""COMPUTED_VALUE"""),"ISLAM") -> ISLAM | S60: =IFERROR(__xludf.DUMMYFUNCTION("""COMPUTED_VALUE"""),"DOSEN/GURU") -> DOSEN/GURU | T60: =IFERROR(__xludf.DUMMYFUNCTION("""COMPUTED_VALUE"""),"PAHA KIRI") -> PAHA KIRI | U60: =IFERROR(__xludf.DUMMYFUNCTION("""COMPUTED_VALUE"""),"-") -> - | V60: =IFERROR(__xludf.DUMMYFUNCTION("""COMPUTED_VALUE"""),"08988277817") -> 08988277817
B61: =IFERROR(__xludf.DUMMYFUNCTION("""COMPUTED_VALUE"""),45006.88642821759) -> 45006.886 | D61: =IFERROR(__xludf.DUMMYFUNCTION("""COMPUTED_VALUE"""),44943.0) -> 44943 | E61: =IFERROR(__xludf.DUMMYFUNCTION("""COMPUTED_VALUE"""),"01Jan") -> 01Jan | F61: =IFERROR(__xludf.DUMMYFUNCTION("""COMPUTED_VALUE"""),"2023") -> 2023 | G61: =IFERROR(__xludf.DUMMYFUNCTION("""COMPUTED_VALUE"""),"DIMAS ARYO BIMO") -> DIMAS ARYO BIMO | H61: =IFERROR(__xludf.DUMMYFUNCTION("""COMPUTED_VALUE"""),"D0523010337") -> D0523010337 | I61: =IFERROR(__xludf.DUMMYFUNCTION("""COMPUTED_VALUE"""),20.0) -> 20 | J61: =IFERROR(__xludf.DUMMYFUNCTION("""COMPUTED_VALUE"""),"18-24 tahun") -> 18-24 tahun | K61: =IFERROR(__xludf.DUMMYFUNCTION("""COMPUTED_VALUE"""),38581.0) -> 38581 | L61: =IFERROR(__xludf.DUMMYFUNCTION("""COMPUTED_VALUE"""),"LAKI-LAKI") -> LAKI-LAKI | M61: =IFERROR(__xludf.DUMMYFUNCTION("""COMPUTED_VALUE"""),"JL RE MARTADINATA NO 3") -> JL RE MARTADINATA NO 3 | R61: =IFERROR(__xludf.DUMMYFUNCTION("""COMPUTED_VALUE"""),"ISLAM") -> ISLAM | S61: =IFERROR(__xludf.DUMMYFUNCTION("""COMPUTED_VALUE"""),"PELAJAR/MAHASISWA") -> PELAJAR/MAHASISWA | T61: =IFERROR(__xludf.DUMMYFUNCTION("""COMPUTED_VALUE"""),"BAHU") -> BAHU | U61: =IFERROR(__xludf.DUMMYFUNCTION("""COMPUTED_VALUE"""),"-") -> - | V61: =IFERROR(__xludf.DUMMYFUNCTION("""COMPUTED_VALUE"""),"089694620337") -> 089694620337
B62: =IFERROR(__xludf.DUMMYFUNCTION("""COMPUTED_VALUE"""),45006.84579907407) -> 45006.846 | D62: =IFERROR(__xludf.DUMMYFUNCTION("""COMPUTED_VALUE"""),44943.0) -> 44943 | E62: =IFERROR(__xludf.DUMMYFUNCTION("""COMPUTED_VALUE"""),"01Jan") -> 01Jan | F62: =IFERROR(__xludf.DUMMYFUNCTION("""COMPUTED_VALUE"""),"2023") -> 2023 | G62: =IFERROR(__xludf.DUMMYFUNCTION("""COMPUTED_VALUE"""),"MARSIANA RITA") -> MARSIANA RITA | H62: =IFERROR(__xludf.DUMMYFUNCTION("""COMPUTED_VALUE"""),"M7623018071") -> M7623018071 | I62: =IFERROR(__xludf.DUMMYFUNCTION("""COMPUTED_VALUE"""),49.0) -> 49 | J62: =IFERROR(__xludf.DUMMYFUNCTION("""COMPUTED_VALUE"""),"> 44 tahun") -> > 44 tahun | K62: =IFERROR(__xludf.DUMMYFUNCTION("""COMPUTED_VALUE"""),28041.0) -> 28041 | L62: =IFERROR(__xludf.DUMMYFUNCTION("""COMPUTED_VALUE"""),"PEREMPUAN") -> PEREMPUAN | M62: =IFERROR(__xludf.DUMMYFUNCTION("""COMPUTED_VALUE"""),"SEI AMBAWANG") -> SEI AMBAWANG | R62: =IFERROR(__xludf.DUMMYFUNCTION("""COMPUTED_VALUE"""),"KATOLIK") -> KATOLIK | S62: =IFERROR(__xludf.DUMMYFUNCTION("""COMPUTED_VALUE"""),"RUMAH TANGGA") -> RUMAH TANGGA | T62: =IFERROR(__xludf.DUMMYFUNCTION("""COMPUTED_VALUE"""),"LENGAN") -> LENGAN | U62: =IFERROR(__xludf.DUMMYFUNCTION("""COMPUTED_VALUE"""),"-") -> - | V62: =IFERROR(__xludf.DUMMYFUNCTION("""COMPUTED_VALUE"""),"085705618071") -> 085705618071
B63: =IFERROR(__xludf.DUMMYFUNCTION("""COMPUTED_VALUE"""),44929.603310185186) -> 44929.603 | D63: =IFERROR(__xludf.DUMMYFUNCTION("""COMPUTED_VALUE"""),44943.0) -> 44943 | E63: =IFERROR(__xludf.DUMMYFUNCTION("""COMPUTED_VALUE"""),"01Jan") -> 01Jan | F63: =IFERROR(__xludf.DUMMYFUNCTION("""COMPUTED_VALUE"""),"2023") -> 2023 | G63: =IFERROR(__xludf.DUMMYFUNCTION("""COMPUTED_VALUE"""),"MARVELLA BENITA PUSPORINI") -> MARVELLA BENITA PUSPORINI | H63: =IFERROR(__xludf.DUMMYFUNCTION("""COMPUTED_VALUE"""),"M0423015817") -> M0423015817 | I63: =IFERROR(__xludf.DUMMYFUNCTION("""COMPUTED_VALUE"""),22.0) -> 22 | J63: =IFERROR(__xludf.DUMMYFUNCTION("""COMPUTED_VALUE"""),"18-24 tahun") -> 18-24 tahun | K63: =IFERROR(__xludf.DUMMYFUNCTION("""COMPUTED_VALUE"""),38052.0) -> 38052 | L63: =IFERROR(__xludf.DUMMYFUNCTION("""COMPUTED_VALUE"""),"PEREMPUAN") -> PEREMPUAN | M63: =IFERROR(__xludf.DUMMYFUNCTION("""COMPUTED_VALUE"""),"JL. DR. SUTOMO GG. KARYA") -> JL. DR. SUTOMO GG. KARYA | R63: =IFERROR(__xludf.DUMMYFUNCTION("""COMPUTED_VALUE"""),"KRISTEN") -> KRISTEN | S63: =IFERROR(__xludf.DUMMYFUNCTION("""COMPUTED_VALUE"""),"TIDAK ADA") -> TIDAK ADA | T63: =IFERROR(__xludf.DUMMYFUNCTION("""COMPUTED_VALUE"""),"KAKI X") -> KAKI X | U63: =IFERROR(__xludf.DUMMYFUNCTION("""COMPUTED_VALUE"""),"") | V63: =IFERROR(__xludf.DUMMYFUNCTION("""COMPUTED_VALUE"""),"08969425817") -> 08969425817
B64: =IFERROR(__xludf.DUMMYFUNCTION("""COMPUTED_VALUE"""),44990.70770967593) -> 44990.708 | D64: =IFERROR(__xludf.DUMMYFUNCTION("""COMPUTED_VALUE"""),44943.0) -> 44943 | E64: =IFERROR(__xludf.DUMMYFUNCTION("""COMPUTED_VALUE"""),"01Jan") -> 01Jan | F64: =IFERROR(__xludf.DUMMYFUNCTION("""COMPUTED_VALUE"""),"2023") -> 2023 | G64: =IFERROR(__xludf.DUMMYFUNCTION("""COMPUTED_VALUE"""),"NENI RIMBAWATI") -> NENI RIMBAWATI | H64: =IFERROR(__xludf.DUMMYFUNCTION("""COMPUTED_VALUE"""),"N7123011230") -> N7123011230 | I64: =IFERROR(__xludf.DUMMYFUNCTION("""COMPUTED_VALUE"""),54.0) -> 54 | J64: =IFERROR(__xludf.DUMMYFUNCTION("""COMPUTED_VALUE"""),"> 44 tahun") -> > 44 tahun | K64: =IFERROR(__xludf.DUMMYFUNCTION("""COMPUTED_VALUE"""),26227.0) -> 26227 | L64: =IFERROR(__xludf.DUMMYFUNCTION("""COMPUTED_VALUE"""),"PEREMPUAN") -> PEREMPUAN | M64: =IFERROR(__xludf.DUMMYFUNCTION("""COMPUTED_VALUE"""),"JL P HAJI HUSEIN 2 GG WANABHAKTI") -> JL P HAJI HUSEIN 2 GG WANABHAKTI | R64: =IFERROR(__xludf.DUMMYFUNCTION("""COMPUTED_VALUE"""),"ISLAM") -> ISLAM | S64: =IFERROR(__xludf.DUMMYFUNCTION("""COMPUTED_VALUE"""),"") | T64: =IFERROR(__xludf.DUMMYFUNCTION("""COMPUTED_VALUE"""),"STROKE") -> STROKE | U64: =IFERROR(__xludf.DUMMYFUNCTION("""COMPUTED_VALUE"""),"") | V64: =IFERROR(__xludf.DUMMYFUNCTION("""COMPUTED_VALUE"""),"082154581230") -> 082154581230
B65: =IFERROR(__xludf.DUMMYFUNCTION("""COMPUTED_VALUE"""),44973.3984375) -> 44973.398 | D65: =IFERROR(__xludf.DUMMYFUNCTION("""COMPUTED_VALUE"""),44943.0) -> 44943 | E65: =IFERROR(__xludf.DUMMYFUNCTION("""COMPUTED_VALUE"""),"01Jan") -> 01Jan | F65: =IFERROR(__xludf.DUMMYFUNCTION("""COMPUTED_VALUE"""),"2023") -> 2023 | G65: =IFERROR(__xludf.DUMMYFUNCTION("""COMPUTED_VALUE"""),"NOVI WINATA") -> NOVI WINATA | H65: =IFERROR(__xludf.DUMMYFUNCTION("""COMPUTED_VALUE"""),"N8723013099") -> N8723013099 | I65: =IFERROR(__xludf.DUMMYFUNCTION("""COMPUTED_VALUE"""),38.0) -> 38 | J65: =IFERROR(__xludf.DUMMYFUNCTION("""COMPUTED_VALUE"""),"35-44 tahun") -> 35-44 tahun | K65: =IFERROR(__xludf.DUMMYFUNCTION("""COMPUTED_VALUE"""),32083.0) -> 32083 | L65: =IFERROR(__xludf.DUMMYFUNCTION("""COMPUTED_VALUE"""),"PEREMPUAN") -> PEREMPUAN | M65: =IFERROR(__xludf.DUMMYFUNCTION("""COMPUTED_VALUE"""),"JL. SULTAN MUHAMMAD NO. 93") -> JL. SULTAN MUHAMMAD NO. 93 | R65: =IFERROR(__xludf.DUMMYFUNCTION("""COMPUTED_VALUE"""),"LAINNYA") -> LAINNYA | S65: =IFERROR(__xludf.DUMMYFUNCTION("""COMPUTED_VALUE"""),"WIRASWASTA") -> WIRASWASTA | T65: =IFERROR(__xludf.DUMMYFUNCTION("""COMPUTED_VALUE"""),"BAHU DAN LEHER") -> BAHU DAN LEHER | U65: =IFERROR(__xludf.DUMMYFUNCTION("""COMPUTED_VALUE"""),"-") -> - | V65: =IFERROR(__xludf.DUMMYFUNCTION("""COMPUTED_VALUE"""),"0811573099") -> 0811573099
B66: =IFERROR(__xludf.DUMMYFUNCTION("""COMPUTED_VALUE"""),45010.57859744213) -> 45010.579 | D66: =IFERROR(__xludf.DUMMYFUNCTION("""COMPUTED_VALUE"""),44943.0) -> 44943 | E66: =IFERROR(__xludf.DUMMYFUNCTION("""COMPUTED_VALUE"""),"01Jan") -> 01Jan | F66: =IFERROR(__xludf.DUMMYFUNCTION("""COMPUTED_VALUE"""),"2023") -> 2023 | G66: =IFERROR(__xludf.DUMMYFUNCTION("""COMPUTED_VALUE"""),"NURDIN") -> NURDIN | H66: =IFERROR(__xludf.DUMMYFUNCTION("""COMPUTED_VALUE"""),"N6423016044") -> N6423016044 | I66: =IFERROR(__xludf.DUMMYFUNCTION("""COMPUTED_VALUE"""),61.0) -> 61 | J66: =IFERROR(__xludf.DUMMYFUNCTION("""COMPUTED_VALUE"""),"> 44 tahun") -> > 44 tahun | K66: =IFERROR(__xludf.DUMMYFUNCTION("""COMPUTED_VALUE"""),23661.0) -> 23661 | L66: =IFERROR(__xludf.DUMMYFUNCTION("""COMPUTED_VALUE"""),"LAKI-LAKI") -> LAKI-LAKI | M66: =IFERROR(__xludf.DUMMYFUNCTION("""COMPUTED_VALUE"""),"JL. ADISUCIPTO GG. CEMPAKA PUTIH NO. 23") -> JL. ADISUCIPTO GG. CEMPAKA PUTIH NO. 23 | R66: =IFERROR(__xludf.DUMMYFUNCTION("""COMPUTED_VALUE"""),"ISLAM") -> ISLAM | S66: =IFERROR(__xludf.DUMMYFUNCTION("""COMPUTED_VALUE"""),"SWASTA") -> SWASTA | T66: =IFERROR(__xludf.DUMMYFUNCTION("""COMPUTED_VALUE"""),"PINGGANG") -> PINGGANG | U66: =IFERROR(__xludf.DUMMYFUNCTION("""COMPUTED_VALUE"""),"") | V66: =IFERROR(__xludf.DUMMYFUNCTION("""COMPUTED_VALUE"""),"089523686044") -> 089523686044
B67: =IFERROR(__xludf.DUMMYFUNCTION("""COMPUTED_VALUE"""),44983.47518518518) -> 44983.475 | D67: =IFERROR(__xludf.DUMMYFUNCTION("""COMPUTED_VALUE"""),44944.0) -> 44944 | E67: =IFERROR(__xludf.DUMMYFUNCTION("""COMPUTED_VALUE"""),"01Jan") -> 01Jan | F67: =IFERROR(__xludf.DUMMYFUNCTION("""COMPUTED_VALUE"""),"2023") -> 2023 | G67: =IFERROR(__xludf.DUMMYFUNCTION("""COMPUTED_VALUE"""),"ALDI") -> ALDI | H67: =IFERROR(__xludf.DUMMYFUNCTION("""COMPUTED_VALUE"""),"A0623017317") -> A0623017317 | I67: =IFERROR(__xludf.DUMMYFUNCTION("""COMPUTED_VALUE"""),19.0) -> 19 | J67: =IFERROR(__xludf.DUMMYFUNCTION("""COMPUTED_VALUE"""),"18-24 tahun") -> 18-24 tahun | K67: =IFERROR(__xludf.DUMMYFUNCTION("""COMPUTED_VALUE"""),39033.0) -> 39033 | L67: =IFERROR(__xludf.DUMMYFUNCTION("""COMPUTED_VALUE"""),"LAKI-LAKI") -> LAKI-LAKI | M67: =IFERROR(__xludf.DUMMYFUNCTION("""COMPUTED_VALUE"""),"JL DESA KAPUR KOMP ALDY MUTIARA RESIDENCE 2") -> JL DESA KAPUR KOMP ALDY MUTIARA RESIDENCE 2 | R67: =IFERROR(__xludf.DUMMYFUNCTION("""COMPUTED_VALUE"""),"ISLAM") -> ISLAM | S67: =IFERROR(__xludf.DUMMYFUNCTION("""COMPUTED_VALUE"""),"PELAJAR/MAHASISWA") -> PELAJAR/MAHASISWA | T67: =IFERROR(__xludf.DUMMYFUNCTION("""COMPUTED_VALUE"""),"BAHU") -> BAHU | U67: =IFERROR(__xludf.DUMMYFUNCTION("""COMPUTED_VALUE"""),"BASKET") -> BASKET | V67: =IFERROR(__xludf.DUMMYFUNCTION("""COMPUTED_VALUE"""),"089621567317") -> 089621567317
B68: =IFERROR(__xludf.DUMMYFUNCTION("""COMPUTED_VALUE"""),44947.81123842593) -> 44947.811 | D68: =IFERROR(__xludf.DUMMYFUNCTION("""COMPUTED_VALUE"""),44944.0) -> 44944 | E68: =IFERROR(__xludf.DUMMYFUNCTION("""COMPUTED_VALUE"""),"01Jan") -> 01Jan | F68: =IFERROR(__xludf.DUMMYFUNCTION("""COMPUTED_VALUE"""),"2023") -> 2023 | G68: =IFERROR(__xludf.DUMMYFUNCTION("""COMPUTED_VALUE"""),"NURHAYATI 55") -> NURHAYATI 55 | H68: =IFERROR(__xludf.DUMMYFUNCTION("""COMPUTED_VALUE"""),"N5523017792") -> N5523017792 | I68: =IFERROR(__xludf.DUMMYFUNCTION("""COMPUTED_VALUE"""),71.0) -> 71 | J68: =IFERROR(__xludf.DUMMYFUNCTION("""COMPUTED_VALUE"""),"> 44 tahun") -> > 44 tahun | K68: =IFERROR(__xludf.DUMMYFUNCTION("""COMPUTED_VALUE"""),20194.0) -> 20194 | L68: =IFERROR(__xludf.DUMMYFUNCTION("""COMPUTED_VALUE"""),"PEREMPUAN") -> PEREMPUAN | M68: =IFERROR(__xludf.DUMMYFUNCTION("""COMPUTED_VALUE"""),"JL PAIT TO'ADAM") -> JL PAIT TO'ADAM | R68: =IFERROR(__xludf.DUMMYFUNCTION("""COMPUTED_VALUE"""),"ISLAM") -> ISLAM | S68: =IFERROR(__xludf.DUMMYFUNCTION("""COMPUTED_VALUE"""),"") | T68: =IFERROR(__xludf.DUMMYFUNCTION("""COMPUTED_VALUE"""),"PANGKAL PAHA - TUNGKAI ATAS") -> PANGKAL PAHA - TUNGKAI ATAS | U68: =IFERROR(__xludf.DUMMYFUNCTION("""COMPUTED_VALUE"""),"") | V68: =IFERROR(__xludf.DUMMYFUNCTION("""COMPUTED_VALUE"""),"085828777792") -> 085828777792
B69: =IFERROR(__xludf.DUMMYFUNCTION("""COMPUTED_VALUE"""),45011.084269375) -> 45011.084 | D69: =IFERROR(__xludf.DUMMYFUNCTION("""COMPUTED_VALUE"""),44944.0) -> 44944 | E69: =IFERROR(__xludf.DUMMYFUNCTION("""COMPUTED_VALUE"""),"01Jan") -> 01Jan | F69: =IFERROR(__xludf.DUMMYFUNCTION("""COMPUTED_VALUE"""),"2023") -> 2023 | G69: =IFERROR(__xludf.DUMMYFUNCTION("""COMPUTED_VALUE"""),"RIZKI SAPUTRA") -> RIZKI SAPUTRA | H69: =IFERROR(__xludf.DUMMYFUNCTION("""COMPUTED_VALUE"""),"R0423012690") -> R0423012690 | I69: =IFERROR(__xludf.DUMMYFUNCTION("""COMPUTED_VALUE"""),21.0) -> 21 | J69: =IFERROR(__xludf.DUMMYFUNCTION("""COMPUTED_VALUE"""),"18-24 tahun") -> 18-24 tahun | K69: =IFERROR(__xludf.DUMMYFUNCTION("""COMPUTED_VALUE"""),38163.0) -> 38163 | L69: =IFERROR(__xludf.DUMMYFUNCTION("""COMPUTED_VALUE"""),"LAKI-LAKI") -> LAKI-LAKI | M69: =IFERROR(__xludf.DUMMYFUNCTION("""COMPUTED_VALUE"""),"JL. IMAM BONJOL") -> JL. IMAM BONJOL | R69: =IFERROR(__xludf.DUMMYFUNCTION("""COMPUTED_VALUE"""),"ISLAM") -> ISLAM | S69: =IFERROR(__xludf.DUMMYFUNCTION("""COMPUTED_VALUE"""),"PELAJAR/MAHASISWA") -> PELAJAR/MAHASISWA | T69: =IFERROR(__xludf.DUMMYFUNCTION("""COMPUTED_VALUE"""),"PUNGGUNG") -> PUNGGUNG | U69: =IFERROR(__xludf.DUMMYFUNCTION("""COMPUTED_VALUE"""),"") | V69: =IFERROR(__xludf.DUMMYFUNCTION("""COMPUTED_VALUE"""),"089692442690") -> 089692442690
B70: =IFERROR(__xludf.DUMMYFUNCTION("""COMPUTED_VALUE"""),45006.87163178241) -> 45006.872 | D70: =IFERROR(__xludf.DUMMYFUNCTION("""COMPUTED_VALUE"""),44944.0) -> 44944 | E70: =IFERROR(__xludf.DUMMYFUNCTION("""COMPUTED_VALUE"""),"01Jan") -> 01Jan | F70: =IFERROR(__xludf.DUMMYFUNCTION("""COMPUTED_VALUE"""),"2023") -> 2023 | G70: =IFERROR(__xludf.DUMMYFUNCTION("""COMPUTED_VALUE"""),"RONY LIUNG") -> RONY LIUNG | H70: =IFERROR(__xludf.DUMMYFUNCTION("""COMPUTED_VALUE"""),"R0123012900") -> R0123012900 | I70: =IFERROR(__xludf.DUMMYFUNCTION("""COMPUTED_VALUE"""),25.0) -> 25 | J70: =IFERROR(__xludf.DUMMYFUNCTION("""COMPUTED_VALUE"""),"25-34 tahun") -> 25-34 tahun | K70: =IFERROR(__xludf.DUMMYFUNCTION("""COMPUTED_VALUE"""),36945.0) -> 36945 | L70: =IFERROR(__xludf.DUMMYFUNCTION("""COMPUTED_VALUE"""),"LAKI-LAKI") -> LAKI-LAKI | M70: =IFERROR(__xludf.DUMMYFUNCTION("""COMPUTED_VALUE"""),"NANGA PINOH, MELAWI") -> NANGA PINOH, MELAWI | R70: =IFERROR(__xludf.DUMMYFUNCTION("""COMPUTED_VALUE"""),"BUDDHA") -> BUDDHA | S70: =IFERROR(__xludf.DUMMYFUNCTION("""COMPUTED_VALUE"""),"PELAJAR/MAHASISWA") -> PELAJAR/MAHASISWA | T70: =IFERROR(__xludf.DUMMYFUNCTION("""COMPUTED_VALUE"""),"ENGKEL KANAN") -> ENGKEL KANAN | U70: =IFERROR(__xludf.DUMMYFUNCTION("""COMPUTED_VALUE"""),"") | V70: =IFERROR(__xludf.DUMMYFUNCTION("""COMPUTED_VALUE"""),"085345172900") -> 085345172900
B71: =IFERROR(__xludf.DUMMYFUNCTION("""COMPUTED_VALUE"""),45006.87579710648) -> 45006.876 | D71: =IFERROR(__xludf.DUMMYFUNCTION("""COMPUTED_VALUE"""),44945.0) -> 44945 | E71: =IFERROR(__xludf.DUMMYFUNCTION("""COMPUTED_VALUE"""),"01Jan") -> 01Jan | F71: =IFERROR(__xludf.DUMMYFUNCTION("""COMPUTED_VALUE"""),"2023") -> 2023 | G71: =IFERROR(__xludf.DUMMYFUNCTION("""COMPUTED_VALUE"""),"NOVI ASMARANI") -> NOVI ASMARANI | H71: =IFERROR(__xludf.DUMMYFUNCTION("""COMPUTED_VALUE"""),"N8723015132") -> N8723015132 | I71: =IFERROR(__xludf.DUMMYFUNCTION("""COMPUTED_VALUE"""),38.0) -> 38 | J71: =IFERROR(__xludf.DUMMYFUNCTION("""COMPUTED_VALUE"""),"35-44 tahun") -> 35-44 tahun | K71: =IFERROR(__xludf.DUMMYFUNCTION("""COMPUTED_VALUE"""),32090.0) -> 32090 | L71: =IFERROR(__xludf.DUMMYFUNCTION("""COMPUTED_VALUE"""),"PEREMPUAN") -> PEREMPUAN | M71: =IFERROR(__xludf.DUMMYFUNCTION("""COMPUTED_VALUE"""),"JL. SUI JAWI GG. TIOKANDANG A NO. 41") -> JL. SUI JAWI GG. TIOKANDANG A NO. 41 | R71: =IFERROR(__xludf.DUMMYFUNCTION("""COMPUTED_VALUE"""),"ISLAM") -> ISLAM | S71: =IFERROR(__xludf.DUMMYFUNCTION("""COMPUTED_VALUE"""),"BUMD") -> BUMD | T71: =IFERROR(__xludf.DUMMYFUNCTION("""COMPUTED_VALUE"""),"ANKLE") -> ANKLE | U71: =IFERROR(__xludf.DUMMYFUNCTION("""COMPUTED_VALUE"""),"JOGING") -> JOGING | V71: =IFERROR(__xludf.DUMMYFUNCTION("""COMPUTED_VALUE"""),"08125795132") -> 08125795132
B72: =IFERROR(__xludf.DUMMYFUNCTION("""COMPUTED_VALUE"""),45006.84428109953) -> 45006.844 | D72: =IFERROR(__xludf.DUMMYFUNCTION("""COMPUTED_VALUE"""),44945.0) -> 44945 | E72: =IFERROR(__xludf.DUMMYFUNCTION("""COMPUTED_VALUE"""),"01Jan") -> 01Jan | F72: =IFERROR(__xludf.DUMMYFUNCTION("""COMPUTED_VALUE"""),"2023") -> 2023 | G72: =IFERROR(__xludf.DUMMYFUNCTION("""COMPUTED_VALUE"""),"SULISTIYOWATI") -> SULISTIYOWATI | H72: =IFERROR(__xludf.DUMMYFUNCTION("""COMPUTED_VALUE"""),"S7523014141") -> S7523014141 | I72: =IFERROR(__xludf.DUMMYFUNCTION("""COMPUTED_VALUE"""),51.0) -> 51 | J72: =IFERROR(__xludf.DUMMYFUNCTION("""COMPUTED_VALUE"""),"> 44 tahun") -> > 44 tahun | K72: =IFERROR(__xludf.DUMMYFUNCTION("""COMPUTED_VALUE"""),27467.0) -> 27467 | L72: =IFERROR(__xludf.DUMMYFUNCTION("""COMPUTED_VALUE"""),"PEREMPUAN") -> PEREMPUAN | M72: =IFERROR(__xludf.DUMMYFUNCTION("""COMPUTED_VALUE"""),"JL. KARYA KITA NO. 86") -> JL. KARYA KITA NO. 86 | R72: =IFERROR(__xludf.DUMMYFUNCTION("""COMPUTED_VALUE"""),"ISLAM") -> ISLAM | S72: =IFERROR(__xludf.DUMMYFUNCTION("""COMPUTED_VALUE"""),"BUMD") -> BUMD | T72: =IFERROR(__xludf.DUMMYFUNCTION("""COMPUTED_VALUE"""),"PINGGANG") -> PINGGANG | U72: =IFERROR(__xludf.DUMMYFUNCTION("""COMPUTED_VALUE"""),"DUDUK LAMA") -> DUDUK LAMA | V72: =IFERROR(__xludf.DUMMYFUNCTION("""COMPUTED_VALUE"""),"08125644141") -> 08125644141
B73: =IFERROR(__xludf.DUMMYFUNCTION("""COMPUTED_VALUE"""),45011.13040420139) -> 45011.13 | D73: =IFERROR(__xludf.DUMMYFUNCTION("""COMPUTED_VALUE"""),44947.0) -> 44947 | E73: =IFERROR(__xludf.DUMMYFUNCTION("""COMPUTED_VALUE"""),"01Jan") -> 01Jan | F73: =IFERROR(__xludf.DUMMYFUNCTION("""COMPUTED_VALUE"""),"2023") -> 2023 | G73: =IFERROR(__xludf.DUMMYFUNCTION("""COMPUTED_VALUE"""),"ARIFYANDI") -> ARIFYANDI | H73: =IFERROR(__xludf.DUMMYFUNCTION("""COMPUTED_VALUE"""),"A9923014697") -> A9923014697 | I73: =IFERROR(__xludf.DUMMYFUNCTION("""COMPUTED_VALUE"""),27.0) -> 27 | J73: =IFERROR(__xludf.DUMMYFUNCTION("""COMPUTED_VALUE"""),"25-34 tahun") -> 25-34 tahun | K73: =IFERROR(__xludf.DUMMYFUNCTION("""COMPUTED_VALUE"""),36235.0) -> 36235 | L73: =IFERROR(__xludf.DUMMYFUNCTION("""COMPUTED_VALUE"""),"LAKI-LAKI") -> LAKI-LAKI | M73: =IFERROR(__xludf.DUMMYFUNCTION("""COMPUTED_VALUE"""),"JL. PARIT TENGAH") -> JL. PARIT TENGAH | R73: =IFERROR(__xludf.DUMMYFUNCTION("""COMPUTED_VALUE"""),"PROTESTAN") -> PROTESTAN | S73: =IFERROR(__xludf.DUMMYFUNCTION("""COMPUTED_VALUE"""),"SWASTA") -> SWASTA | T73: =IFERROR(__xludf.DUMMYFUNCTION("""COMPUTED_VALUE"""),"PAHA SAMPING") -> PAHA SAMPING | U73: =IFERROR(__xludf.DUMMYFUNCTION("""COMPUTED_VALUE"""),"") | V73: =IFERROR(__xludf.DUMMYFUNCTION("""COMPUTED_VALUE"""),"089693694697") -> 089693694697
B74: =IFERROR(__xludf.DUMMYFUNCTION("""COMPUTED_VALUE"""),45006.850412141204) -> 45006.85 | D74: =IFERROR(__xludf.DUMMYFUNCTION("""COMPUTED_VALUE"""),44947.0) -> 44947 | E74: =IFERROR(__xludf.DUMMYFUNCTION("""COMPUTED_VALUE"""),"01Jan") -> 01Jan | F74: =IFERROR(__xludf.DUMMYFUNCTION("""COMPUTED_VALUE"""),"2023") -> 2023 | G74: =IFERROR(__xludf.DUMMYFUNCTION("""COMPUTED_VALUE"""),"KARTINAH") -> KARTINAH | H74: =IFERROR(__xludf.DUMMYFUNCTION("""COMPUTED_VALUE"""),"K6223018878") -> K6223018878 | I74: =IFERROR(__xludf.DUMMYFUNCTION("""COMPUTED_VALUE"""),64.0) -> 64 | J74: =IFERROR(__xludf.DUMMYFUNCTION("""COMPUTED_VALUE"""),"> 44 tahun") -> > 44 tahun | K74: =IFERROR(__xludf.DUMMYFUNCTION("""COMPUTED_VALUE"""),22813.0) -> 22813 | L74: =IFERROR(__xludf.DUMMYFUNCTION("""COMPUTED_VALUE"""),"PEREMPUAN") -> PEREMPUAN | M74: =IFERROR(__xludf.DUMMYFUNCTION("""COMPUTED_VALUE"""),"JL. DR. SUTOMO GG. PAK ABU NO. 43") -> JL. DR. SUTOMO GG. PAK ABU NO. 43 | R74: =IFERROR(__xludf.DUMMYFUNCTION("""COMPUTED_VALUE"""),"ISLAM") -> ISLAM | S74: =IFERROR(__xludf.DUMMYFUNCTION("""COMPUTED_VALUE"""),"PENSIUN") -> PENSIUN | U74: =IFERROR(__xludf.DUMMYFUNCTION("""COMPUTED_VALUE"""),"JAGA CUCU") -> JAGA CUCU | V74: =IFERROR(__xludf.DUMMYFUNCTION("""COMPUTED_VALUE"""),"0811568878") -> 0811568878
B75: =IFERROR(__xludf.DUMMYFUNCTION("""COMPUTED_VALUE"""),44952.82355324074) -> 44952.824 | D75: =IFERROR(__xludf.DUMMYFUNCTION("""COMPUTED_VALUE"""),44947.0) -> 44947 | E75: =IFERROR(__xludf.DUMMYFUNCTION("""COMPUTED_VALUE"""),"01Jan") -> 01Jan | F75: =IFERROR(__xludf.DUMMYFUNCTION("""COMPUTED_VALUE"""),"2023") -> 2023 | G75: =IFERROR(__xludf.DUMMYFUNCTION("""COMPUTED_VALUE"""),"KHARISMA RIZKI UTAMA") -> KHARISMA RIZKI UTAMA | H75: =IFERROR(__xludf.DUMMYFUNCTION("""COMPUTED_VALUE"""),"K9223011118") -> K9223011118 | I75: =IFERROR(__xludf.DUMMYFUNCTION("""COMPUTED_VALUE"""),33.0) -> 33 | J75: =IFERROR(__xludf.DUMMYFUNCTION("""COMPUTED_VALUE"""),"25-34 tahun") -> 25-34 tahun | K75: =IFERROR(__xludf.DUMMYFUNCTION("""COMPUTED_VALUE"""),33945.0) -> 33945 | L75: =IFERROR(__xludf.DUMMYFUNCTION("""COMPUTED_VALUE"""),"LAKI-LAKI") -> LAKI-LAKI | M75: =IFERROR(__xludf.DUMMYFUNCTION("""COMPUTED_VALUE"""),"GG. IKHSAN NO. 15") -> GG. IKHSAN NO. 15 | R75: =IFERROR(__xludf.DUMMYFUNCTION("""COMPUTED_VALUE"""),"ISLAM") -> ISLAM | S75: =IFERROR(__xludf.DUMMYFUNCTION("""COMPUTED_VALUE"""),"WIRASWASTA") -> WIRASWASTA | T75: =IFERROR(__xludf.DUMMYFUNCTION("""COMPUTED_VALUE"""),"KANAN") -> KANAN | U75: =IFERROR(__xludf.DUMMYFUNCTION("""COMPUTED_VALUE"""),"") | V75: =IFERROR(__xludf.DUMMYFUNCTION("""COMPUTED_VALUE"""),"08115781118") -> 08115781118
B76: =IFERROR(__xludf.DUMMYFUNCTION("""COMPUTED_VALUE"""),44950.536203703705) -> 44950.536 | D76: =IFERROR(__xludf.DUMMYFUNCTION("""COMPUTED_VALUE"""),44947.0) -> 44947 | E76: =IFERROR(__xludf.DUMMYFUNCTION("""COMPUTED_VALUE"""),"01Jan") -> 01Jan | F76: =IFERROR(__xludf.DUMMYFUNCTION("""COMPUTED_VALUE"""),"2023") -> 2023 | G76: =IFERROR(__xludf.DUMMYFUNCTION("""COMPUTED_VALUE"""),"M. ABDUL LATIEF LAZUARDI") -> M. ABDUL LATIEF LAZUARDI | H76: =IFERROR(__xludf.DUMMYFUNCTION("""COMPUTED_VALUE"""),"M0023019835") -> M0023019835 | I76: =IFERROR(__xludf.DUMMYFUNCTION("""COMPUTED_VALUE"""),25.0) -> 25 | J76: =IFERROR(__xludf.DUMMYFUNCTION("""COMPUTED_VALUE"""),"25-34 tahun") -> 25-34 tahun | K76: =IFERROR(__xludf.DUMMYFUNCTION("""COMPUTED_VALUE"""),36767.0) -> 36767 | L76: =IFERROR(__xludf.DUMMYFUNCTION("""COMPUTED_VALUE"""),"LAKI-LAKI") -> LAKI-LAKI | M76: =IFERROR(__xludf.DUMMYFUNCTION("""COMPUTED_VALUE"""),"JL. TABRANI AHMAD") -> JL. TABRANI AHMAD | R76: =IFERROR(__xludf.DUMMYFUNCTION("""COMPUTED_VALUE"""),"ISLAM") -> ISLAM | S76: =IFERROR(__xludf.DUMMYFUNCTION("""COMPUTED_VALUE"""),"PELAJAR/MAHASISWA") -> PELAJAR/MAHASISWA | T76: =IFERROR(__xludf.DUMMYFUNCTION("""COMPUTED_VALUE"""),"PINGGANG") -> PINGGANG | U76: =IFERROR(__xludf.DUMMYFUNCTION("""COMPUTED_VALUE"""),"-") -> - | V76: =IFERROR(__xludf.DUMMYFUNCTION("""COMPUTED_VALUE"""),"085950099835") -> 085950099835
B77: =IFERROR(__xludf.DUMMYFUNCTION("""COMPUTED_VALUE"""),45011.07816873843) -> 45011.078 | D77: =IFERROR(__xludf.DUMMYFUNCTION("""COMPUTED_VALUE"""),44947.0) -> 44947 | E77: =IFERROR(__xludf.DUMMYFUNCTION("""COMPUTED_VALUE"""),"01Jan") -> 01Jan | F77: =IFERROR(__xludf.DUMMYFUNCTION("""COMPUTED_VALUE"""),"2023") -> 2023 | G77: =IFERROR(__xludf.DUMMYFUNCTION("""COMPUTED_VALUE"""),"SUPINI") -> SUPINI | H77: =IFERROR(__xludf.DUMMYFUNCTION("""COMPUTED_VALUE"""),"S6923014949") -> S6923014949 | I77: =IFERROR(__xludf.DUMMYFUNCTION("""COMPUTED_VALUE"""),56.0) -> 56 | J77: =IFERROR(__xludf.DUMMYFUNCTION("""COMPUTED_VALUE"""),"> 44 tahun") -> > 44 tahun | K77: =IFERROR(__xludf.DUMMYFUNCTION("""COMPUTED_VALUE"""),25556.0) -> 25556 | L77: =IFERROR(__xludf.DUMMYFUNCTION("""COMPUTED_VALUE"""),"PEREMPUAN") -> PEREMPUAN | M77: =IFERROR(__xludf.DUMMYFUNCTION("""COMPUTED_VALUE"""),"JL. PROF. M. YAMIN GG. USAHA BARU III NO. 4") -> JL. PROF. M. YAMIN GG. USAHA BARU III NO. 4 | R77: =IFERROR(__xludf.DUMMYFUNCTION("""COMPUTED_VALUE"""),"ISLAM") -> ISLAM | S77: =IFERROR(__xludf.DUMMYFUNCTION("""COMPUTED_VALUE"""),"RUMAH TANGGA") -> RUMAH TANGGA | T77: =IFERROR(__xludf.DUMMYFUNCTION("""COMPUTED_VALUE"""),"KAKI") -> KAKI | U77: =IFERROR(__xludf.DUMMYFUNCTION("""COMPUTED_VALUE"""),"-") -> - | V77: =IFERROR(__xludf.DUMMYFUNCTION("""COMPUTED_VALUE"""),"0895335634949") -> 0895335634949
B78: =IFERROR(__xludf.DUMMYFUNCTION("""COMPUTED_VALUE"""),45011.131553287036) -> 45011.132 | D78: =IFERROR(__xludf.DUMMYFUNCTION("""COMPUTED_VALUE"""),44947.0) -> 44947 | E78: =IFERROR(__xludf.DUMMYFUNCTION("""COMPUTED_VALUE"""),"01Jan") -> 01Jan | F78: =IFERROR(__xludf.DUMMYFUNCTION("""COMPUTED_VALUE"""),"2023") -> 2023 | G78: =IFERROR(__xludf.DUMMYFUNCTION("""COMPUTED_VALUE"""),"TUKIJO") -> TUKIJO | H78: =IFERROR(__xludf.DUMMYFUNCTION("""COMPUTED_VALUE"""),"T5523016407") -> T5523016407 | I78: =IFERROR(__xludf.DUMMYFUNCTION("""COMPUTED_VALUE"""),70.0) -> 70 | J78: =IFERROR(__xludf.DUMMYFUNCTION("""COMPUTED_VALUE"""),"> 44 tahun") -> > 44 tahun | K78: =IFERROR(__xludf.DUMMYFUNCTION("""COMPUTED_VALUE"""),20451.0) -> 20451 | L78: =IFERROR(__xludf.DUMMYFUNCTION("""COMPUTED_VALUE"""),"LAKI-LAKI") -> LAKI-LAKI | M78: =IFERROR(__xludf.DUMMYFUNCTION("""COMPUTED_VALUE"""),"JL. HUSIN HAMZAH GG. MANDIRI PERMAI") -> JL. HUSIN HAMZAH GG. MANDIRI PERMAI | R78: =IFERROR(__xludf.DUMMYFUNCTION("""COMPUTED_VALUE"""),"ISLAM") -> ISLAM | S78: =IFERROR(__xludf.DUMMYFUNCTION("""COMPUTED_VALUE"""),"PENSIUN") -> PENSIUN | T78: =IFERROR(__xludf.DUMMYFUNCTION("""COMPUTED_VALUE"""),"BAHU") -> BAHU | U78: =IFERROR(__xludf.DUMMYFUNCTION("""COMPUTED_VALUE"""),"") | V78: =IFERROR(__xludf.DUMMYFUNCTION("""COMPUTED_VALUE"""),"081345726407") -> 081345726407
B79: =IFERROR(__xludf.DUMMYFUNCTION("""COMPUTED_VALUE"""),44937.80181712963) -> 44937.802 | D79: =IFERROR(__xludf.DUMMYFUNCTION("""COMPUTED_VALUE"""),44949.0) -> 44949 | E79: =IFERROR(__xludf.DUMMYFUNCTION("""COMPUTED_VALUE"""),"01Jan") -> 01Jan | F79: =IFERROR(__xludf.DUMMYFUNCTION("""COMPUTED_VALUE"""),"2023") -> 2023 | G79: =IFERROR(__xludf.DUMMYFUNCTION("""COMPUTED_VALUE"""),"FAHRIZAL") -> FAHRIZAL | H79: =IFERROR(__xludf.DUMMYFUNCTION("""COMPUTED_VALUE"""),"F7023014230") -> F7023014230 | I79: =IFERROR(__xludf.DUMMYFUNCTION("""COMPUTED_VALUE"""),55.0) -> 55 | J79: =IFERROR(__xludf.DUMMYFUNCTION("""COMPUTED_VALUE"""),"> 44 tahun") -> > 44 tahun | K79: =IFERROR(__xludf.DUMMYFUNCTION("""COMPUTED_VALUE"""),25899.0) -> 25899 | L79: =IFERROR(__xludf.DUMMYFUNCTION("""COMPUTED_VALUE"""),"LAKI-LAKI") -> LAKI-LAKI | M79: =IFERROR(__xludf.DUMMYFUNCTION("""COMPUTED_VALUE"""),"JL AMPERA KOMP ZAL KHATULISTIWA NO B12") -> JL AMPERA KOMP ZAL KHATULISTIWA NO B12 | R79: =IFERROR(__xludf.DUMMYFUNCTION("""COMPUTED_VALUE"""),"ISLAM") -> ISLAM | S79: =IFERROR(__xludf.DUMMYFUNCTION("""COMPUTED_VALUE"""),"SWASTA") -> SWASTA | U79: =IFERROR(__xludf.DUMMYFUNCTION("""COMPUTED_VALUE"""),"SEPEDA") -> SEPEDA | V79: =IFERROR(__xludf.DUMMYFUNCTION("""COMPUTED_VALUE"""),"082213414230") -> 082213414230
B80: =IFERROR(__xludf.DUMMYFUNCTION("""COMPUTED_VALUE"""),44931.624606481484) -> 44931.625 | D80: =IFERROR(__xludf.DUMMYFUNCTION("""COMPUTED_VALUE"""),44949.0) -> 44949 | E80: =IFERROR(__xludf.DUMMYFUNCTION("""COMPUTED_VALUE"""),"01Jan") -> 01Jan | F80: =IFERROR(__xludf.DUMMYFUNCTION("""COMPUTED_VALUE"""),"2023") -> 2023 | G80: =IFERROR(__xludf.DUMMYFUNCTION("""COMPUTED_VALUE"""),"INNOSENSIUS SILA") -> INNOSENSIUS SILA | H80: =IFERROR(__xludf.DUMMYFUNCTION("""COMPUTED_VALUE"""),"I0123017652") -> I0123017652 | I80: =IFERROR(__xludf.DUMMYFUNCTION("""COMPUTED_VALUE"""),25.0) -> 25 | J80: =IFERROR(__xludf.DUMMYFUNCTION("""COMPUTED_VALUE"""),"25-34 tahun") -> 25-34 tahun | K80: =IFERROR(__xludf.DUMMYFUNCTION("""COMPUTED_VALUE"""),36943.0) -> 36943 | L80: =IFERROR(__xludf.DUMMYFUNCTION("""COMPUTED_VALUE"""),"LAKI-LAKI") -> LAKI-LAKI | M80: =IFERROR(__xludf.DUMMYFUNCTION("""COMPUTED_VALUE"""),"JL SEPAKAT 2") -> JL SEPAKAT 2 | R80: =IFERROR(__xludf.DUMMYFUNCTION("""COMPUTED_VALUE"""),"KATOLIK") -> KATOLIK | S80: =IFERROR(__xludf.DUMMYFUNCTION("""COMPUTED_VALUE"""),"PELAJAR/MAHASISWA") -> PELAJAR/MAHASISWA | T80: =IFERROR(__xludf.DUMMYFUNCTION("""COMPUTED_VALUE"""),"KIRI") -> KIRI | U80: =IFERROR(__xludf.DUMMYFUNCTION("""COMPUTED_VALUE"""),"-") -> - | V80: =IFERROR(__xludf.DUMMYFUNCTION("""COMPUTED_VALUE"""),"081256617652") -> 081256617652
B81: =IFERROR(__xludf.DUMMYFUNCTION("""COMPUTED_VALUE"""),45006.94357319444) -> 45006.944 | D81: =IFERROR(__xludf.DUMMYFUNCTION("""COMPUTED_VALUE"""),44949.0) -> 44949 | E81: =IFERROR(__xludf.DUMMYFUNCTION("""COMPUTED_VALUE"""),"01Jan") -> 01Jan | F81: =IFERROR(__xludf.DUMMYFUNCTION("""COMPUTED_VALUE"""),"2023") -> 2023 | G81: =IFERROR(__xludf.DUMMYFUNCTION("""COMPUTED_VALUE"""),"PRIMA FARRET") -> PRIMA FARRET | H81: =IFERROR(__xludf.DUMMYFUNCTION("""COMPUTED_VALUE"""),"P8223015614") -> P8223015614 | I81: =IFERROR(__xludf.DUMMYFUNCTION("""COMPUTED_VALUE"""),43.0) -> 43 | J81: =IFERROR(__xludf.DUMMYFUNCTION("""COMPUTED_VALUE"""),"35-44 tahun") -> 35-44 tahun | K81: =IFERROR(__xludf.DUMMYFUNCTION("""COMPUTED_VALUE"""),30216.0) -> 30216 | L81: =IFERROR(__xludf.DUMMYFUNCTION("""COMPUTED_VALUE"""),"LAKI-LAKI") -> LAKI-LAKI | M81: =IFERROR(__xludf.DUMMYFUNCTION("""COMPUTED_VALUE"""),"JL KARYA BARU 7 NO 31") -> JL KARYA BARU 7 NO 31 | R81: =IFERROR(__xludf.DUMMYFUNCTION("""COMPUTED_VALUE"""),"ISLAM") -> ISLAM | S81: =IFERROR(__xludf.DUMMYFUNCTION("""COMPUTED_VALUE"""),"ASN") -> ASN | T81: =IFERROR(__xludf.DUMMYFUNCTION("""COMPUTED_VALUE"""),"SIKU") -> SIKU | U81: =IFERROR(__xludf.DUMMYFUNCTION("""COMPUTED_VALUE"""),"GYM") -> GYM | V81: =IFERROR(__xludf.DUMMYFUNCTION("""COMPUTED_VALUE"""),"08568975614") -> 08568975614
B82: =IFERROR(__xludf.DUMMYFUNCTION("""COMPUTED_VALUE"""),45006.949206226855) -> 45006.949 | D82: =IFERROR(__xludf.DUMMYFUNCTION("""COMPUTED_VALUE"""),44949.0) -> 44949 | E82: =IFERROR(__xludf.DUMMYFUNCTION("""COMPUTED_VALUE"""),"01Jan") -> 01Jan | F82: =IFERROR(__xludf.DUMMYFUNCTION("""COMPUTED_VALUE"""),"2023") -> 2023 | G82: =IFERROR(__xludf.DUMMYFUNCTION("""COMPUTED_VALUE"""),"SRI SURYATI") -> SRI SURYATI | H82: =IFERROR(__xludf.DUMMYFUNCTION("""COMPUTED_VALUE"""),"S5723017882") -> S5723017882 | I82: =IFERROR(__xludf.DUMMYFUNCTION("""COMPUTED_VALUE"""),69.0) -> 69 | J82: =IFERROR(__xludf.DUMMYFUNCTION("""COMPUTED_VALUE"""),"> 44 tahun") -> > 44 tahun | K82: =IFERROR(__xludf.DUMMYFUNCTION("""COMPUTED_VALUE"""),20903.0) -> 20903 | L82: =IFERROR(__xludf.DUMMYFUNCTION("""COMPUTED_VALUE"""),"PEREMPUAN") -> PEREMPUAN | M82: =IFERROR(__xludf.DUMMYFUNCTION("""COMPUTED_VALUE"""),"JL. ALIANYANG KOMP. PERTANIAN") -> JL. ALIANYANG KOMP. PERTANIAN | R82: =IFERROR(__xludf.DUMMYFUNCTION("""COMPUTED_VALUE"""),"ISLAM") -> ISLAM | S82: =IFERROR(__xludf.DUMMYFUNCTION("""COMPUTED_VALUE"""),"PENSIUN") -> PENSIUN | T82: =IFERROR(__xludf.DUMMYFUNCTION("""COMPUTED_VALUE"""),"LENGAN") -> LENGAN | U82: =IFERROR(__xludf.DUMMYFUNCTION("""COMPUTED_VALUE"""),"MASAK") -> MASAK | V82: =IFERROR(__xludf.DUMMYFUNCTION("""COMPUTED_VALUE"""),"082254257882") -> 082254257882
B83: =IFERROR(__xludf.DUMMYFUNCTION("""COMPUTED_VALUE"""),45006.61086997685) -> 45006.611 | D83: =IFERROR(__xludf.DUMMYFUNCTION("""COMPUTED_VALUE"""),44949.0) -> 44949 | E83: =IFERROR(__xludf.DUMMYFUNCTION("""COMPUTED_VALUE"""),"01Jan") -> 01Jan | F83: =IFERROR(__xludf.DUMMYFUNCTION("""COMPUTED_VALUE"""),"2023") -> 2023 | G83: =IFERROR(__xludf.DUMMYFUNCTION("""COMPUTED_VALUE"""),"SUADI") -> SUADI | H83: =IFERROR(__xludf.DUMMYFUNCTION("""COMPUTED_VALUE"""),"S6823014569") -> S6823014569 | I83: =IFERROR(__xludf.DUMMYFUNCTION("""COMPUTED_VALUE"""),58.0) -> 58 | J83: =IFERROR(__xludf.DUMMYFUNCTION("""COMPUTED_VALUE"""),"> 44 tahun") -> > 44 tahun | K83: =IFERROR(__xludf.DUMMYFUNCTION("""COMPUTED_VALUE"""),24931.0) -> 24931 | L83: =IFERROR(__xludf.DUMMYFUNCTION("""COMPUTED_VALUE"""),"LAKI-LAKI") -> LAKI-LAKI | M83: =IFERROR(__xludf.DUMMYFUNCTION("""COMPUTED_VALUE"""),"JL. M. YAMIN GG. BINA KARYA NO. 21A") -> JL. M. YAMIN GG. BINA KARYA NO. 21A | R83: =IFERROR(__xludf.DUMMYFUNCTION("""COMPUTED_VALUE"""),"ISLAM") -> ISLAM | S83: =IFERROR(__xludf.DUMMYFUNCTION("""COMPUTED_VALUE"""),"") | T83: =IFERROR(__xludf.DUMMYFUNCTION("""COMPUTED_VALUE"""),"STROKE") -> STROKE | U83: =IFERROR(__xludf.DUMMYFUNCTION("""COMPUTED_VALUE"""),"") | V83: =IFERROR(__xludf.DUMMYFUNCTION("""COMPUTED_VALUE"""),"081254814569") -> 081254814569
B84: =IFERROR(__xludf.DUMMYFUNCTION("""COMPUTED_VALUE"""),45011.15101350694) -> 45011.151 | D84: =IFERROR(__xludf.DUMMYFUNCTION("""COMPUTED_VALUE"""),44949.0) -> 44949 | E84: =IFERROR(__xludf.DUMMYFUNCTION("""COMPUTED_VALUE"""),"01Jan") -> 01Jan | F84: =IFERROR(__xludf.DUMMYFUNCTION("""COMPUTED_VALUE"""),"2023") -> 2023 | G84: =IFERROR(__xludf.DUMMYFUNCTION("""COMPUTED_VALUE"""),"TRIANI SEPTI") -> TRIANI SEPTI | H84: =IFERROR(__xludf.DUMMYFUNCTION("""COMPUTED_VALUE"""),"T9523019991") -> T9523019991 | I84: =IFERROR(__xludf.DUMMYFUNCTION("""COMPUTED_VALUE"""),30.0) -> 30 | J84: =IFERROR(__xludf.DUMMYFUNCTION("""COMPUTED_VALUE"""),"25-34 tahun") -> 25-34 tahun | K84: =IFERROR(__xludf.DUMMYFUNCTION("""COMPUTED_VALUE"""),34994.0) -> 34994 | L84: =IFERROR(__xludf.DUMMYFUNCTION("""COMPUTED_VALUE"""),"PEREMPUAN") -> PEREMPUAN | M84: =IFERROR(__xludf.DUMMYFUNCTION("""COMPUTED_VALUE"""),"JL. SERDAM") -> JL. SERDAM | R84: =IFERROR(__xludf.DUMMYFUNCTION("""COMPUTED_VALUE"""),"ISLAM") -> ISLAM | S84: =IFERROR(__xludf.DUMMYFUNCTION("""COMPUTED_VALUE"""),"ASN") -> ASN | T84: =IFERROR(__xludf.DUMMYFUNCTION("""COMPUTED_VALUE"""),"BAHU") -> BAHU | U84: =IFERROR(__xludf.DUMMYFUNCTION("""COMPUTED_VALUE"""),"") | V84: =IFERROR(__xludf.DUMMYFUNCTION("""COMPUTED_VALUE"""),"081312829991") -> 081312829991
B85: =IFERROR(__xludf.DUMMYFUNCTION("""COMPUTED_VALUE"""),45010.57534383102) -> 45010.575 | D85: =IFERROR(__xludf.DUMMYFUNCTION("""COMPUTED_VALUE"""),44949.0) -> 44949 | E85: =IFERROR(__xludf.DUMMYFUNCTION("""COMPUTED_VALUE"""),"01Jan") -> 01Jan | F85: =IFERROR(__xludf.DUMMYFUNCTION("""COMPUTED_VALUE"""),"2023") -> 2023 | G85: =IFERROR(__xludf.DUMMYFUNCTION("""COMPUTED_VALUE"""),"YUDHI PONCA MANALU") -> YUDHI PONCA MANALU | H85: =IFERROR(__xludf.DUMMYFUNCTION("""COMPUTED_VALUE"""),"Y8823015888") -> Y8823015888 | I85: =IFERROR(__xludf.DUMMYFUNCTION("""COMPUTED_VALUE"""),37.0) -> 37 | J85: =IFERROR(__xludf.DUMMYFUNCTION("""COMPUTED_VALUE"""),"35-44 tahun") -> 35-44 tahun | K85: =IFERROR(__xludf.DUMMYFUNCTION("""COMPUTED_VALUE"""),32329.0) -> 32329 | L85: =IFERROR(__xludf.DUMMYFUNCTION("""COMPUTED_VALUE"""),"LAKI-LAKI") -> LAKI-LAKI | M85: =IFERROR(__xludf.DUMMYFUNCTION("""COMPUTED_VALUE"""),"JL. PANCASILA GG. WASPADA") -> JL. PANCASILA GG. WASPADA | R85: =IFERROR(__xludf.DUMMYFUNCTION("""COMPUTED_VALUE"""),"LAINNYA") -> LAINNYA | S85: =IFERROR(__xludf.DUMMYFUNCTION("""COMPUTED_VALUE"""),"TNI/POLRI") -> TNI/POLRI | T85: =IFERROR(__xludf.DUMMYFUNCTION("""COMPUTED_VALUE"""),"PINGGANG") -> PINGGANG | U85: =IFERROR(__xludf.DUMMYFUNCTION("""COMPUTED_VALUE"""),"") | V85: =IFERROR(__xludf.DUMMYFUNCTION("""COMPUTED_VALUE"""),"082357365888") -> 082357365888
B86: =IFERROR(__xludf.DUMMYFUNCTION("""COMPUTED_VALUE"""),44952.810844907406) -> 44952.811 | D86: =IFERROR(__xludf.DUMMYFUNCTION("""COMPUTED_VALUE"""),44950.0) -> 44950 | E86: =IFERROR(__xludf.DUMMYFUNCTION("""COMPUTED_VALUE"""),"01Jan") -> 01Jan | F86: =IFERROR(__xludf.DUMMYFUNCTION("""COMPUTED_VALUE"""),"2023") -> 2023 | G86: =IFERROR(__xludf.DUMMYFUNCTION("""COMPUTED_VALUE"""),"DEDE ALFIANDI") -> DEDE ALFIANDI | H86: =IFERROR(__xludf.DUMMYFUNCTION("""COMPUTED_VALUE"""),"D8923011717") -> D8923011717 | I86: =IFERROR(__xludf.DUMMYFUNCTION("""COMPUTED_VALUE"""),37.0) -> 37 | J86: =IFERROR(__xludf.DUMMYFUNCTION("""COMPUTED_VALUE"""),"35-44 tahun") -> 35-44 tahun | K86: =IFERROR(__xludf.DUMMYFUNCTION("""COMPUTED_VALUE"""),32615.0) -> 32615 | L86: =IFERROR(__xludf.DUMMYFUNCTION("""COMPUTED_VALUE"""),"LAKI-LAKI") -> LAKI-LAKI | M86: =IFERROR(__xludf.DUMMYFUNCTION("""COMPUTED_VALUE"""),"JL DANAU SENTARUM GG WONOSOBO KOMP ANUGRAH INDAH 3 NO AA17") -> JL DANAU SENTARUM GG WONOSOBO KOMP ANUGRAH INDAH 3 NO AA17 | R86: =IFERROR(__xludf.DUMMYFUNCTION("""COMPUTED_VALUE"""),"ISLAM") -> ISLAM | S86: =IFERROR(__xludf.DUMMYFUNCTION("""COMPUTED_VALUE"""),"PERBANKAN") -> PERBANKAN | U86: =IFERROR(__xludf.DUMMYFUNCTION("""COMPUTED_VALUE"""),"FUTSAL") -> FUTSAL | V86: =IFERROR(__xludf.DUMMYFUNCTION("""COMPUTED_VALUE"""),"08115701717") -> 08115701717
B87: =IFERROR(__xludf.DUMMYFUNCTION("""COMPUTED_VALUE"""),45006.84053835648) -> 45006.841 | D87: =IFERROR(__xludf.DUMMYFUNCTION("""COMPUTED_VALUE"""),44950.0) -> 44950 | E87: =IFERROR(__xludf.DUMMYFUNCTION("""COMPUTED_VALUE"""),"01Jan") -> 01Jan | F87: =IFERROR(__xludf.DUMMYFUNCTION("""COMPUTED_VALUE"""),"2023") -> 2023 | G87: =IFERROR(__xludf.DUMMYFUNCTION("""COMPUTED_VALUE"""),"DENY SUMANTRI") -> DENY SUMANTRI | H87: =IFERROR(__xludf.DUMMYFUNCTION("""COMPUTED_VALUE"""),"D9523019981") -> D9523019981 | I87: =IFERROR(__xludf.DUMMYFUNCTION("""COMPUTED_VALUE"""),30.0) -> 30 | J87: =IFERROR(__xludf.DUMMYFUNCTION("""COMPUTED_VALUE"""),"25-34 tahun") -> 25-34 tahun | K87: =IFERROR(__xludf.DUMMYFUNCTION("""COMPUTED_VALUE"""),35043.0) -> 35043 | L87: =IFERROR(__xludf.DUMMYFUNCTION("""COMPUTED_VALUE"""),"LAKI-LAKI") -> LAKI-LAKI | M87: =IFERROR(__xludf.DUMMYFUNCTION("""COMPUTED_VALUE"""),"JL DANAU SENTARUM N0 1B") -> JL DANAU SENTARUM N0 1B | R87: =IFERROR(__xludf.DUMMYFUNCTION("""COMPUTED_VALUE"""),"ISLAM") -> ISLAM | S87: =IFERROR(__xludf.DUMMYFUNCTION("""COMPUTED_VALUE"""),"SWASTA") -> SWASTA | T87: =IFERROR(__xludf.DUMMYFUNCTION("""COMPUTED_VALUE"""),"SKOLIOSIS") -> SKOLIOSIS | U87: =IFERROR(__xludf.DUMMYFUNCTION("""COMPUTED_VALUE"""),"-") -> - | V87: =IFERROR(__xludf.DUMMYFUNCTION("""COMPUTED_VALUE"""),"089660029981") -> 089660029981
B88: =IFERROR(__xludf.DUMMYFUNCTION("""COMPUTED_VALUE"""),45006.6156609375) -> 45006.616 | D88: =IFERROR(__xludf.DUMMYFUNCTION("""COMPUTED_VALUE"""),44950.0) -> 44950 | E88: =IFERROR(__xludf.DUMMYFUNCTION("""COMPUTED_VALUE"""),"01Jan") -> 01Jan | F88: =IFERROR(__xludf.DUMMYFUNCTION("""COMPUTED_VALUE"""),"2023") -> 2023 | G88: =IFERROR(__xludf.DUMMYFUNCTION("""COMPUTED_VALUE"""),"ELO SINAGA") -> ELO SINAGA | H88: =IFERROR(__xludf.DUMMYFUNCTION("""COMPUTED_VALUE"""),"E1023019575") -> E1023019575 | I88: =IFERROR(__xludf.DUMMYFUNCTION("""COMPUTED_VALUE"""),15.0) -> 15 | J88: =IFERROR(__xludf.DUMMYFUNCTION("""COMPUTED_VALUE"""),"< 18 tahun") -> < 18 tahun | K88: =IFERROR(__xludf.DUMMYFUNCTION("""COMPUTED_VALUE"""),40432.0) -> 40432 | L88: =IFERROR(__xludf.DUMMYFUNCTION("""COMPUTED_VALUE"""),"LAKI-LAKI") -> LAKI-LAKI | M88: =IFERROR(__xludf.DUMMYFUNCTION("""COMPUTED_VALUE"""),"JL. PROF. M. YAMIN KOMP. AKI 6B") -> JL. PROF. M. YAMIN KOMP. AKI 6B | R88: =IFERROR(__xludf.DUMMYFUNCTION("""COMPUTED_VALUE"""),"PROTESTAN") -> PROTESTAN | S88: =IFERROR(__xludf.DUMMYFUNCTION("""COMPUTED_VALUE"""),"PELAJAR/MAHASISWA") -> PELAJAR/MAHASISWA | T88: =IFERROR(__xludf.DUMMYFUNCTION("""COMPUTED_VALUE"""),"TANGAN KIRI") -> TANGAN KIRI | U88: =IFERROR(__xludf.DUMMYFUNCTION("""COMPUTED_VALUE"""),"") | V88: =IFERROR(__xludf.DUMMYFUNCTION("""COMPUTED_VALUE"""),"081256059575") -> 081256059575
B89: =IFERROR(__xludf.DUMMYFUNCTION("""COMPUTED_VALUE"""),45006.9136353125) -> 45006.914 | D89: =IFERROR(__xludf.DUMMYFUNCTION("""COMPUTED_VALUE"""),44950.0) -> 44950 | E89: =IFERROR(__xludf.DUMMYFUNCTION("""COMPUTED_VALUE"""),"01Jan") -> 01Jan | F89: =IFERROR(__xludf.DUMMYFUNCTION("""COMPUTED_VALUE"""),"2023") -> 2023 | G89: =IFERROR(__xludf.DUMMYFUNCTION("""COMPUTED_VALUE"""),"FARIDA") -> FARIDA | H89: =IFERROR(__xludf.DUMMYFUNCTION("""COMPUTED_VALUE"""),"F6023018181") -> F6023018181 | I89: =IFERROR(__xludf.DUMMYFUNCTION("""COMPUTED_VALUE"""),65.0) -> 65 | J89: =IFERROR(__xludf.DUMMYFUNCTION("""COMPUTED_VALUE"""),"> 44 tahun") -> > 44 tahun | K89: =IFERROR(__xludf.DUMMYFUNCTION("""COMPUTED_VALUE"""),22185.0) -> 22185 | L89: =IFERROR(__xludf.DUMMYFUNCTION("""COMPUTED_VALUE"""),"PEREMPUAN") -> PEREMPUAN | M89: =IFERROR(__xludf.DUMMYFUNCTION("""COMPUTED_VALUE"""),"JL. PARIS 2 GG. MITRA NO. 19") -> JL. PARIS 2 GG. MITRA NO. 19 | R89: =IFERROR(__xludf.DUMMYFUNCTION("""COMPUTED_VALUE"""),"ISLAM") -> ISLAM | S89: =IFERROR(__xludf.DUMMYFUNCTION("""COMPUTED_VALUE"""),"RUMAH TANGGA") -> RUMAH TANGGA | T89: =IFERROR(__xludf.DUMMYFUNCTION("""COMPUTED_VALUE"""),"KAKI") -> KAKI | U89: =IFERROR(__xludf.DUMMYFUNCTION("""COMPUTED_VALUE"""),"") | V89: =IFERROR(__xludf.DUMMYFUNCTION("""COMPUTED_VALUE"""),"0816228181") -> 0816228181
B90: =IFERROR(__xludf.DUMMYFUNCTION("""COMPUTED_VALUE"""),45006.842721423614) -> 45006.843 | D90: =IFERROR(__xludf.DUMMYFUNCTION("""COMPUTED_VALUE"""),44950.0) -> 44950 | E90: =IFERROR(__xludf.DUMMYFUNCTION("""COMPUTED_VALUE"""),"01Jan") -> 01Jan | F90: =IFERROR(__xludf.DUMMYFUNCTION("""COMPUTED_VALUE"""),"2023") -> 2023 | G90: =IFERROR(__xludf.DUMMYFUNCTION("""COMPUTED_VALUE"""),"MAYSHA PUTRI LESMANA") -> MAYSHA PUTRI LESMANA | H90: =IFERROR(__xludf.DUMMYFUNCTION("""COMPUTED_VALUE"""),"M0823012188") -> M0823012188 | I90: =IFERROR(__xludf.DUMMYFUNCTION("""COMPUTED_VALUE"""),18.0) -> 18 | J90: =IFERROR(__xludf.DUMMYFUNCTION("""COMPUTED_VALUE"""),"< 18 tahun") -> < 18 tahun | K90: =IFERROR(__xludf.DUMMYFUNCTION("""COMPUTED_VALUE"""),39576.0) -> 39576 | L90: =IFERROR(__xludf.DUMMYFUNCTION("""COMPUTED_VALUE"""),"PEREMPUAN") -> PEREMPUAN | M90: =IFERROR(__xludf.DUMMYFUNCTION("""COMPUTED_VALUE"""),"JL. WONOBARU") -> JL. WONOBARU | R90: =IFERROR(__xludf.DUMMYFUNCTION("""COMPUTED_VALUE"""),"ISLAM") -> ISLAM | S90: =IFERROR(__xludf.DUMMYFUNCTION("""COMPUTED_VALUE"""),"TIDAK ADA") -> TIDAK ADA | T90: =IFERROR(__xludf.DUMMYFUNCTION("""COMPUTED_VALUE"""),"CEREBRAL PALLSY") -> CEREBRAL PALLSY | U90: =IFERROR(__xludf.DUMMYFUNCTION("""COMPUTED_VALUE"""),"") | V90: =IFERROR(__xludf.DUMMYFUNCTION("""COMPUTED_VALUE"""),"082150212188") -> 082150212188
B91: =IFERROR(__xludf.DUMMYFUNCTION("""COMPUTED_VALUE"""),44956.5574537037) -> 44956.557 | D91: =IFERROR(__xludf.DUMMYFUNCTION("""COMPUTED_VALUE"""),44950.0) -> 44950 | E91: =IFERROR(__xludf.DUMMYFUNCTION("""COMPUTED_VALUE"""),"01Jan") -> 01Jan | F91: =IFERROR(__xludf.DUMMYFUNCTION("""COMPUTED_VALUE"""),"2023") -> 2023 | G91: =IFERROR(__xludf.DUMMYFUNCTION("""COMPUTED_VALUE"""),"PRILANDA GILANG RADANNA") -> PRILANDA GILANG RADANNA | H91: =IFERROR(__xludf.DUMMYFUNCTION("""COMPUTED_VALUE"""),"P9823015565") -> P9823015565 | I91: =IFERROR(__xludf.DUMMYFUNCTION("""COMPUTED_VALUE"""),28.0) -> 28 | J91: =IFERROR(__xludf.DUMMYFUNCTION("""COMPUTED_VALUE"""),"25-34 tahun") -> 25-34 tahun | K91: =IFERROR(__xludf.DUMMYFUNCTION("""COMPUTED_VALUE"""),35898.0) -> 35898 | L91: =IFERROR(__xludf.DUMMYFUNCTION("""COMPUTED_VALUE"""),"LAKI-LAKI") -> LAKI-LAKI | M91: =IFERROR(__xludf.DUMMYFUNCTION("""COMPUTED_VALUE"""),"JALAN MESJID NO 20 KELURAHAN MELAYU SINGKAWANG") -> JALAN MESJID NO 20 KELURAHAN MELAYU SINGKAWANG | R91: =IFERROR(__xludf.DUMMYFUNCTION("""COMPUTED_VALUE"""),"ISLAM") -> ISLAM | S91: =IFERROR(__xludf.DUMMYFUNCTION("""COMPUTED_VALUE"""),"TIDAK ADA") -> TIDAK ADA | U91: =IFERROR(__xludf.DUMMYFUNCTION("""COMPUTED_VALUE"""),"FUTSAL") -> FUTSAL | V91: =IFERROR(__xludf.DUMMYFUNCTION("""COMPUTED_VALUE"""),"082155655565") -> 082155655565
B92: =IFERROR(__xludf.DUMMYFUNCTION("""COMPUTED_VALUE"""),45006.94566697917) -> 45006.946 | D92: =IFERROR(__xludf.DUMMYFUNCTION("""COMPUTED_VALUE"""),44950.0) -> 44950 | E92: =IFERROR(__xludf.DUMMYFUNCTION("""COMPUTED_VALUE"""),"01Jan") -> 01Jan | F92: =IFERROR(__xludf.DUMMYFUNCTION("""COMPUTED_VALUE"""),"2023") -> 2023 | G92: =IFERROR(__xludf.DUMMYFUNCTION("""COMPUTED_VALUE"""),"RAISAN FIQRI") -> RAISAN FIQRI | H92: =IFERROR(__xludf.DUMMYFUNCTION("""COMPUTED_VALUE"""),"R0423010268") -> R0423010268 | I92: =IFERROR(__xludf.DUMMYFUNCTION("""COMPUTED_VALUE"""),21.0) -> 21 | J92: =IFERROR(__xludf.DUMMYFUNCTION("""COMPUTED_VALUE"""),"18-24 tahun") -> 18-24 tahun | K92: =IFERROR(__xludf.DUMMYFUNCTION("""COMPUTED_VALUE"""),38209.0) -> 38209 | L92: =IFERROR(__xludf.DUMMYFUNCTION("""COMPUTED_VALUE"""),"LAKI-LAKI") -> LAKI-LAKI | M92: =IFERROR(__xludf.DUMMYFUNCTION("""COMPUTED_VALUE"""),"JL SUI RAYA DALAM KOMP KOSGORO") -> JL SUI RAYA DALAM KOMP KOSGORO | R92: =IFERROR(__xludf.DUMMYFUNCTION("""COMPUTED_VALUE"""),"ISLAM") -> ISLAM | S92: =IFERROR(__xludf.DUMMYFUNCTION("""COMPUTED_VALUE"""),"PELAJAR/MAHASISWA") -> PELAJAR/MAHASISWA | T92: =IFERROR(__xludf.DUMMYFUNCTION("""COMPUTED_VALUE"""),"PINGGUL") -> PINGGUL | U92: =IFERROR(__xludf.DUMMYFUNCTION("""COMPUTED_VALUE"""),"-") -> - | V92: =IFERROR(__xludf.DUMMYFUNCTION("""COMPUTED_VALUE"""),"085264090268") -> 085264090268
B93: =IFERROR(__xludf.DUMMYFUNCTION("""COMPUTED_VALUE"""),45010.59036170139) -> 45010.59 | D93: =IFERROR(__xludf.DUMMYFUNCTION("""COMPUTED_VALUE"""),44950.0) -> 44950 | E93: =IFERROR(__xludf.DUMMYFUNCTION("""COMPUTED_VALUE"""),"01Jan") -> 01Jan | F93: =IFERROR(__xludf.DUMMYFUNCTION("""COMPUTED_VALUE"""),"2023") -> 2023 | G93: =IFERROR(__xludf.DUMMYFUNCTION("""COMPUTED_VALUE"""),"REZA FERDIANSYAH") -> REZA FERDIANSYAH | H93: =IFERROR(__xludf.DUMMYFUNCTION("""COMPUTED_VALUE"""),"R0323019317") -> R0323019317 | I93: =IFERROR(__xludf.DUMMYFUNCTION("""COMPUTED_VALUE"""),23.0) -> 23 | J93: =IFERROR(__xludf.DUMMYFUNCTION("""COMPUTED_VALUE"""),"18-24 tahun") -> 18-24 tahun | K93: =IFERROR(__xludf.DUMMYFUNCTION("""COMPUTED_VALUE"""),37631.0) -> 37631 | L93: =IFERROR(__xludf.DUMMYFUNCTION("""COMPUTED_VALUE"""),"LAKI-LAKI") -> LAKI-LAKI | M93: =IFERROR(__xludf.DUMMYFUNCTION("""COMPUTED_VALUE"""),"JL SUMATERA GG SUDIMORO") -> JL SUMATERA GG SUDIMORO | R93: =IFERROR(__xludf.DUMMYFUNCTION("""COMPUTED_VALUE"""),"ISLAM") -> ISLAM | S93: =IFERROR(__xludf.DUMMYFUNCTION("""COMPUTED_VALUE"""),"PELAJAR/MAHASISWA") -> PELAJAR/MAHASISWA | T93: =IFERROR(__xludf.DUMMYFUNCTION("""COMPUTED_VALUE"""),"POSTUR") -> POSTUR | U93: =IFERROR(__xludf.DUMMYFUNCTION("""COMPUTED_VALUE"""),"-") -> - | V93: =IFERROR(__xludf.DUMMYFUNCTION("""COMPUTED_VALUE"""),"089529139317") -> 089529139317
B94: =IFERROR(__xludf.DUMMYFUNCTION("""COMPUTED_VALUE"""),44985.59226851852) -> 44985.592 | D94: =IFERROR(__xludf.DUMMYFUNCTION("""COMPUTED_VALUE"""),44950.0) -> 44950 | E94: =IFERROR(__xludf.DUMMYFUNCTION("""COMPUTED_VALUE"""),"01Jan") -> 01Jan | F94: =IFERROR(__xludf.DUMMYFUNCTION("""COMPUTED_VALUE"""),"2023") -> 2023 | G94: =IFERROR(__xludf.DUMMYFUNCTION("""COMPUTED_VALUE"""),"RIA") -> RIA | H94: =IFERROR(__xludf.DUMMYFUNCTION("""COMPUTED_VALUE"""),"R7723015689") -> R7723015689 | I94: =IFERROR(__xludf.DUMMYFUNCTION("""COMPUTED_VALUE"""),49.0) -> 49 | J94: =IFERROR(__xludf.DUMMYFUNCTION("""COMPUTED_VALUE"""),"> 44 tahun") -> > 44 tahun | K94: =IFERROR(__xludf.DUMMYFUNCTION("""COMPUTED_VALUE"""),28140.0) -> 28140 | L94: =IFERROR(__xludf.DUMMYFUNCTION("""COMPUTED_VALUE"""),"PEREMPUAN") -> PEREMPUAN | M94: =IFERROR(__xludf.DUMMYFUNCTION("""COMPUTED_VALUE"""),"JL. UJUNG PANDANG KOMP. VILLA BRATA INDAH") -> JL. UJUNG PANDANG KOMP. VILLA BRATA INDAH | R94: =IFERROR(__xludf.DUMMYFUNCTION("""COMPUTED_VALUE"""),"ISLAM") -> ISLAM | S94: =IFERROR(__xludf.DUMMYFUNCTION("""COMPUTED_VALUE"""),"SWASTA") -> SWASTA | T94: =IFERROR(__xludf.DUMMYFUNCTION("""COMPUTED_VALUE"""),"PINGGANG") -> PINGGANG | U94: =IFERROR(__xludf.DUMMYFUNCTION("""COMPUTED_VALUE"""),"") | V94: =IFERROR(__xludf.DUMMYFUNCTION("""COMPUTED_VALUE"""),"085391155689") -> 085391155689
B95: =IFERROR(__xludf.DUMMYFUNCTION("""COMPUTED_VALUE"""),45010.57722265046) -> 45010.577 | D95: =IFERROR(__xludf.DUMMYFUNCTION("""COMPUTED_VALUE"""),44950.0) -> 44950 | E95: =IFERROR(__xludf.DUMMYFUNCTION("""COMPUTED_VALUE"""),"01Jan") -> 01Jan | F95: =IFERROR(__xludf.DUMMYFUNCTION("""COMPUTED_VALUE"""),"2023") -> 2023 | G95: =IFERROR(__xludf.DUMMYFUNCTION("""COMPUTED_VALUE"""),"SYARIF ABDUL KHALID") -> SYARIF ABDUL KHALID | H95: =IFERROR(__xludf.DUMMYFUNCTION("""COMPUTED_VALUE"""),"S8823016365") -> S8823016365 | I95: =IFERROR(__xludf.DUMMYFUNCTION("""COMPUTED_VALUE"""),38.0) -> 38 | J95: =IFERROR(__xludf.DUMMYFUNCTION("""COMPUTED_VALUE"""),"35-44 tahun") -> 35-44 tahun | K95: =IFERROR(__xludf.DUMMYFUNCTION("""COMPUTED_VALUE"""),32233.0) -> 32233 | L95: =IFERROR(__xludf.DUMMYFUNCTION("""COMPUTED_VALUE"""),"LAKI-LAKI") -> LAKI-LAKI | M95: =IFERROR(__xludf.DUMMYFUNCTION("""COMPUTED_VALUE"""),"JL. HUSEIN HAMZAH GG. KRAKATAU") -> JL. HUSEIN HAMZAH GG. KRAKATAU | R95: =IFERROR(__xludf.DUMMYFUNCTION("""COMPUTED_VALUE"""),"ISLAM") -> ISLAM | S95: =IFERROR(__xludf.DUMMYFUNCTION("""COMPUTED_VALUE"""),"BUMD") -> BUMD | T95: =IFERROR(__xludf.DUMMYFUNCTION("""COMPUTED_VALUE"""),"POST OP. TULANG PINGGUL") -> POST OP. TULANG PINGGUL | U95: =IFERROR(__xludf.DUMMYFUNCTION("""COMPUTED_VALUE"""),"") | V95: =IFERROR(__xludf.DUMMYFUNCTION("""COMPUTED_VALUE"""),"085245236365") -> 085245236365
B96: =IFERROR(__xludf.DUMMYFUNCTION("""COMPUTED_VALUE"""),44951.8265625) -> 44951.827 | D96: =IFERROR(__xludf.DUMMYFUNCTION("""COMPUTED_VALUE"""),44950.0) -> 44950 | E96: =IFERROR(__xludf.DUMMYFUNCTION("""COMPUTED_VALUE"""),"01Jan") -> 01Jan | F96: =IFERROR(__xludf.DUMMYFUNCTION("""COMPUTED_VALUE"""),"2023") -> 2023 | G96: =IFERROR(__xludf.DUMMYFUNCTION("""COMPUTED_VALUE"""),"TITIK NURSIAH") -> TITIK NURSIAH | H96: =IFERROR(__xludf.DUMMYFUNCTION("""COMPUTED_VALUE"""),"T5423015410") -> T5423015410 | I96: =IFERROR(__xludf.DUMMYFUNCTION("""COMPUTED_VALUE"""),72.0) -> 72 | J96: =IFERROR(__xludf.DUMMYFUNCTION("""COMPUTED_VALUE"""),"> 44 tahun") -> > 44 tahun | K96: =IFERROR(__xludf.DUMMYFUNCTION("""COMPUTED_VALUE"""),19783.0) -> 19783 | L96: =IFERROR(__xludf.DUMMYFUNCTION("""COMPUTED_VALUE"""),"PEREMPUAN") -> PEREMPUAN | M96: =IFERROR(__xludf.DUMMYFUNCTION("""COMPUTED_VALUE"""),"JL MORODADI 5 NO 2") -> JL MORODADI 5 NO 2 | R96: =IFERROR(__xludf.DUMMYFUNCTION("""COMPUTED_VALUE"""),"ISLAM") -> ISLAM | S96: =IFERROR(__xludf.DUMMYFUNCTION("""COMPUTED_VALUE"""),"PENSIUN") -> PENSIUN | T96: =IFERROR(__xludf.DUMMYFUNCTION("""COMPUTED_VALUE"""),"PAHA") -> PAHA | U96: =IFERROR(__xludf.DUMMYFUNCTION("""COMPUTED_VALUE"""),"-") -> - | V96: =IFERROR(__xludf.DUMMYFUNCTION("""COMPUTED_VALUE"""),"085956115410") -> 085956115410
B97: =IFERROR(__xludf.DUMMYFUNCTION("""COMPUTED_VALUE"""),45006.841809571764) -> 45006.842 | D97: =IFERROR(__xludf.DUMMYFUNCTION("""COMPUTED_VALUE"""),44950.0) -> 44950 | E97: =IFERROR(__xludf.DUMMYFUNCTION("""COMPUTED_VALUE"""),"01Jan") -> 01Jan | F97: =IFERROR(__xludf.DUMMYFUNCTION("""COMPUTED_VALUE"""),"2023") -> 2023 | G97: =IFERROR(__xludf.DUMMYFUNCTION("""COMPUTED_VALUE"""),"YESSI ANDRIANI S") -> YESSI ANDRIANI S | H97: =IFERROR(__xludf.DUMMYFUNCTION("""COMPUTED_VALUE"""),"Y8523019223") -> Y8523019223 | I97: =IFERROR(__xludf.DUMMYFUNCTION("""COMPUTED_VALUE"""),40.0) -> 40 | J97: =IFERROR(__xludf.DUMMYFUNCTION("""COMPUTED_VALUE"""),"35-44 tahun") -> 35-44 tahun | K97: =IFERROR(__xludf.DUMMYFUNCTION("""COMPUTED_VALUE"""),31405.0) -> 31405 | L97: =IFERROR(__xludf.DUMMYFUNCTION("""COMPUTED_VALUE"""),"PEREMPUAN") -> PEREMPUAN | M97: =IFERROR(__xludf.DUMMYFUNCTION("""COMPUTED_VALUE"""),"JL KALIMAS HULU") -> JL KALIMAS HULU | R97: =IFERROR(__xludf.DUMMYFUNCTION("""COMPUTED_VALUE"""),"KATOLIK") -> KATOLIK | S97: =IFERROR(__xludf.DUMMYFUNCTION("""COMPUTED_VALUE"""),"DOSEN/GURU") -> DOSEN/GURU | U97: =IFERROR(__xludf.DUMMYFUNCTION("""COMPUTED_VALUE"""),"-") -> - | V97: =IFERROR(__xludf.DUMMYFUNCTION("""COMPUTED_VALUE"""),"085245539223") -> 085245539223
B98: =IFERROR(__xludf.DUMMYFUNCTION("""COMPUTED_VALUE"""),45006.636090740736) -> 45006.636 | D98: =IFERROR(__xludf.DUMMYFUNCTION("""COMPUTED_VALUE"""),44951.0) -> 44951 | E98: =IFERROR(__xludf.DUMMYFUNCTION("""COMPUTED_VALUE"""),"01Jan") -> 01Jan | F98: =IFERROR(__xludf.DUMMYFUNCTION("""COMPUTED_VALUE"""),"2023") -> 2023 | G98: =IFERROR(__xludf.DUMMYFUNCTION("""COMPUTED_VALUE"""),"AGUSTINUS SIMATUPANG") -> AGUSTINUS SIMATUPANG | H98: =IFERROR(__xludf.DUMMYFUNCTION("""COMPUTED_VALUE"""),"A8723018222") -> A8723018222 | I98: =IFERROR(__xludf.DUMMYFUNCTION("""COMPUTED_VALUE"""),38.0) -> 38 | J98: =IFERROR(__xludf.DUMMYFUNCTION("""COMPUTED_VALUE"""),"35-44 tahun") -> 35-44 tahun | K98: =IFERROR(__xludf.DUMMYFUNCTION("""COMPUTED_VALUE"""),32007.0) -> 32007 | L98: =IFERROR(__xludf.DUMMYFUNCTION("""COMPUTED_VALUE"""),"LAKI-LAKI") -> LAKI-LAKI | M98: =IFERROR(__xludf.DUMMYFUNCTION("""COMPUTED_VALUE"""),"JL. RAYA WAJOK HULU KM 7.5") -> JL. RAYA WAJOK HULU KM 7.5 | R98: =IFERROR(__xludf.DUMMYFUNCTION("""COMPUTED_VALUE"""),"PROTESTAN") -> PROTESTAN | S98: =IFERROR(__xludf.DUMMYFUNCTION("""COMPUTED_VALUE"""),"SWASTA") -> SWASTA | T98: =IFERROR(__xludf.DUMMYFUNCTION("""COMPUTED_VALUE"""),"ANKLE KANAN") -> ANKLE KANAN | U98: =IFERROR(__xludf.DUMMYFUNCTION("""COMPUTED_VALUE"""),"") | V98: =IFERROR(__xludf.DUMMYFUNCTION("""COMPUTED_VALUE"""),"082363888222") -> 082363888222
B99: =IFERROR(__xludf.DUMMYFUNCTION("""COMPUTED_VALUE"""),44937.72144675926) -> 44937.721 | D99: =IFERROR(__xludf.DUMMYFUNCTION("""COMPUTED_VALUE"""),44951.0) -> 44951 | E99: =IFERROR(__xludf.DUMMYFUNCTION("""COMPUTED_VALUE"""),"01Jan") -> 01Jan | F99: =IFERROR(__xludf.DUMMYFUNCTION("""COMPUTED_VALUE"""),"2023") -> 2023 | G99: =IFERROR(__xludf.DUMMYFUNCTION("""COMPUTED_VALUE"""),"EKO SUTRISTIYADI") -> EKO SUTRISTIYADI | H99: =IFERROR(__xludf.DUMMYFUNCTION("""COMPUTED_VALUE"""),"E9523011787") -> E9523011787 | I99: =IFERROR(__xludf.DUMMYFUNCTION("""COMPUTED_VALUE"""),31.0) -> 31 | J99: =IFERROR(__xludf.DUMMYFUNCTION("""COMPUTED_VALUE"""),"25-34 tahun") -> 25-34 tahun | K99: =IFERROR(__xludf.DUMMYFUNCTION("""COMPUTED_VALUE"""),34858.0) -> 34858 | L99: =IFERROR(__xludf.DUMMYFUNCTION("""COMPUTED_VALUE"""),"LAKI-LAKI") -> LAKI-LAKI | M99: =IFERROR(__xludf.DUMMYFUNCTION("""COMPUTED_VALUE"""),"JL URAY BAWADI NO 49") -> JL URAY BAWADI NO 49 | R99: =IFERROR(__xludf.DUMMYFUNCTION("""COMPUTED_VALUE"""),"ISLAM") -> ISLAM | S99: =IFERROR(__xludf.DUMMYFUNCTION("""COMPUTED_VALUE"""),"ASN") -> ASN | U99: =IFERROR(__xludf.DUMMYFUNCTION("""COMPUTED_VALUE"""),"-") -> - | V99: =IFERROR(__xludf.DUMMYFUNCTION("""COMPUTED_VALUE"""),"089693371787") -> 089693371787
B100: =IFERROR(__xludf.DUMMYFUNCTION("""COMPUTED_VALUE"""),44668.62266137732) -> 44668.623 | D100: =IFERROR(__xludf.DUMMYFUNCTION("""COMPUTED_VALUE"""),44951.0) -> 44951 | E100: =IFERROR(__xludf.DUMMYFUNCTION("""COMPUTED_VALUE"""),"01Jan") -> 01Jan | F100: =IFERROR(__xludf.DUMMYFUNCTION("""COMPUTED_VALUE"""),"2023") -> 2023 | G100: =IFERROR(__xludf.DUMMYFUNCTION("""COMPUTED_VALUE"""),"FIKRI RIPARTA HARAHAP") -> FIKRI RIPARTA HARAHAP | H100: =IFERROR(__xludf.DUMMYFUNCTION("""COMPUTED_VALUE"""),"F0523012509") -> F0523012509 | I100: =IFERROR(__xludf.DUMMYFUNCTION("""COMPUTED_VALUE"""),20.0) -> 20 | J100: =IFERROR(__xludf.DUMMYFUNCTION("""COMPUTED_VALUE"""),"18-24 tahun") -> 18-24 tahun | K100: =IFERROR(__xludf.DUMMYFUNCTION("""COMPUTED_VALUE"""),38532.0) -> 38532 | L100: =IFERROR(__xludf.DUMMYFUNCTION("""COMPUTED_VALUE"""),"LAKI-LAKI") -> LAKI-LAKI | M100: =IFERROR(__xludf.DUMMYFUNCTION("""COMPUTED_VALUE"""),"JL. PROF. M. YAMIN GG. USAHA MAJU JALUR D NO. 1") -> JL. PROF. M. YAMIN GG. USAHA MAJU JALUR D NO. 1 | R100: =IFERROR(__xludf.DUMMYFUNCTION("""COMPUTED_VALUE"""),"ISLAM") -> ISLAM | S100: =IFERROR(__xludf.DUMMYFUNCTION("""COMPUTED_VALUE"""),"PELAJAR/MAHASISWA") -> PELAJAR/MAHASISWA | T100: =IFERROR(__xludf.DUMMYFUNCTION("""COMPUTED_VALUE"""),"KAKI X") -> KAKI X | U100: =IFERROR(__xludf.DUMMYFUNCTION("""COMPUTED_VALUE"""),"BASKET") -> BASKET | V100: =IFERROR(__xludf.DUMMYFUNCTION("""COMPUTED_VALUE"""),"089692062509") -> 089692062509
...

Sheet Pivot Table 176

Sheet 📝 Kunjungan
X1: ⏳ LIHAT DATA SEMESTER LALU
B2: SHIFT | C2: TIM | D2: ADMIN | E2: TANGGAL | F2: TAHUN | G2: BULAN | H2: HARI | I2: JAM | J2: FISIO | K2: LAYANAN | L2: NAMA PASIEN | M2: NO. RM | N2: USIA | O2: JENIS KELAMIN | P2: AGAMA | Q2: PEKERJAAN | R2: KELUHAN | S2: HOBI/AKTIVITAS SEHARI-HARI | T2: KEHADIRAN | U2: NO. SESI | V2: KETERANGAN | W2: ✅ | X2: CATATAN ADMIN
B3: PAGI | C3: {=IFNA(XLOOKUP(J3,'⚙️ Pengaturan'!$H$5:$H1508,'⚙️ Pengaturan'!$I$5:$I1508),"")} -> TIM Y | D3: SUCI | E3: 45931 | F3: =IF($E3="","",TEXT($E3,"YYYY")) -> 2025 | G3: =IF($E3="","",TEXT($E3,"MM")&TEXT($E3,"MMM")) -> 10Okt | H3: =IF($E3="","",TEXT($E3,"DDDD")) -> Rabu | I3: 09.00 | J3: WAHYU | K3: TERAPI AWAL | L3: AFNUR RIKI AMRULLAH | M3: =IFNA(VLOOKUP(L3,'🙎‍♂️ Pasien'!G:V,2,FALSE),"") -> A9025092121 | N3: =IFNA(VLOOKUP(L3,'🙎‍♂️ Pasien'!G:L,3,FALSE),"") -> 36 | O3: =IFNA(VLOOKUP(L3,'🙎‍♂️ Pasien'!G:V,6,FALSE),"") -> LAKI-LAKI | P3: =IFNA(VLOOKUP(L3,'🙎‍♂️ Pasien'!G:V,12,FALSE),"") -> ISLAM | Q3: =IFNA(VLOOKUP(L3:L1508,'🙎‍♂️ Pasien'!G:V,13,FALSE),"") -> WIRASWASTA | R3: {=ifna(xlookup(L3,'🙎‍♂️ Pasien'!$G$5:$G1508,'🙎‍♂️ Pasien'!$T$5:$T1508),"")} -> PINGGANG KECETIT | S3: {=ifna(xlookup(L3,'🙎‍♂️ Pasien'!$G$5:$G1508,'🙎‍♂️ Pasien'!$U$5:$U1508),"")} -> - | T3: HADIR | U3: - | V3: SUAMI DELILLA | W3: TRUE
B4: PAGI | C4: {=IFNA(XLOOKUP(J4,'⚙️ Pengaturan'!$H$5:$H1508,'⚙️ Pengaturan'!$I$5:$I1508),"")} -> TIM A | D4: SUCI | E4: 45931 | F4: =IF($E4="","",TEXT($E4,"YYYY")) -> 2025 | G4: =IF($E4="","",TEXT($E4,"MM")&TEXT($E4,"MMM")) -> 10Okt | H4: =IF($E4="","",TEXT($E4,"DDDD")) -> Rabu | I4: 09.00 | J4: HENA | K4: PAKET TERAPI | L4: RUDI HARTONO | M4: =IFNA(VLOOKUP(L4,'🙎‍♂️ Pasien'!G:V,2,FALSE),"") -> R2525091389 | N4: =IFNA(VLOOKUP(L4,'🙎‍♂️ Pasien'!G:L,3,FALSE),"") -> 1 | O4: =IFNA(VLOOKUP(L4,'🙎‍♂️ Pasien'!G:V,6,FALSE),"") -> LAKI-LAKI | P4: =IFNA(VLOOKUP(L4,'🙎‍♂️ Pasien'!G:V,12,FALSE),"") -> PROTESTAN | Q4: =IFNA(VLOOKUP(L4:L1508,'🙎‍♂️ Pasien'!G:V,13,FALSE),"") -> KARYAWAN | R4: {=ifna(xlookup(L4,'🙎‍♂️ Pasien'!$G$5:$G1508,'🙎‍♂️ Pasien'!$T$5:$T1508),"")} -> FROZEN SHOULDER | S4: {=ifna(xlookup(L4,'🙎‍♂️ Pasien'!$G$5:$G1508,'🙎‍♂️ Pasien'!$U$5:$U1508),"")} -> TIDAK BISA MAIN BADMINTON | T4: HADIR | U4: 1 | W4: TRUE
B5: PAGI | C5: {=IFNA(XLOOKUP(J5,'⚙️ Pengaturan'!$H$5:$H1508,'⚙️ Pengaturan'!$I$5:$I1508),"")} -> TIM A | D5: SUCI | E5: 45931 | F5: =IF($E5="","",TEXT($E5,"YYYY")) -> 2025 | G5: =IF($E5="","",TEXT($E5,"MM")&TEXT($E5,"MMM")) -> 10Okt | H5: =IF($E5="","",TEXT($E5,"DDDD")) -> Rabu | I5: 10.00 | J5: HENA | K5: PAKET TERAPI | L5: GRACIA IVANA GOUWYN | M5: =IFNA(VLOOKUP(L5,'🙎‍♂️ Pasien'!G:V,2,FALSE),"") -> G0425088990 | N5: =IFNA(VLOOKUP(L5,'🙎‍♂️ Pasien'!G:L,3,FALSE),"") -> 21 | O5: =IFNA(VLOOKUP(L5,'🙎‍♂️ Pasien'!G:V,6,FALSE),"") -> PEREMPUAN | P5: =IFNA(VLOOKUP(L5,'🙎‍♂️ Pasien'!G:V,12,FALSE),"") -> PROTESTAN | Q5: =IFNA(VLOOKUP(L5:L1508,'🙎‍♂️ Pasien'!G:V,13,FALSE),"") -> BUSINESS OWNER | R5: {=ifna(xlookup(L5,'🙎‍♂️ Pasien'!$G$5:$G1508,'🙎‍♂️ Pasien'!$T$5:$T1508),"")} -> TANGAN | S5: {=ifna(xlookup(L5,'🙎‍♂️ Pasien'!$G$5:$G1508,'🙎‍♂️ Pasien'!$U$5:$U1508),"")} -> BERMAIN TENNIS | T5: TIDAK HADIR | U5: - | V5: MAU PINDAH HARI ADA AGENDA DADAKAN | W5: TRUE
B6: PAGI | C6: {=IFNA(XLOOKUP(J6,'⚙️ Pengaturan'!$H$5:$H1508,'⚙️ Pengaturan'!$I$5:$I1508),"")} -> TIM A | D6: SUCI | E6: 45931 | F6: =IF($E6="","",TEXT($E6,"YYYY")) -> 2025 | G6: =IF($E6="","",TEXT($E6,"MM")&TEXT($E6,"MMM")) -> 10Okt | H6: =IF($E6="","",TEXT($E6,"DDDD")) -> Rabu | I6: 10.00 | J6: HENA | K6: SESI TERAPI | L6: LILI JARIAH | M6: =IFNA(VLOOKUP(L6,'🙎‍♂️ Pasien'!G:V,2,FALSE),"") -> L8125099600 | N6: =IFNA(VLOOKUP(L6,'🙎‍♂️ Pasien'!G:L,3,FALSE),"") -> 45 | O6: =IFNA(VLOOKUP(L6,'🙎‍♂️ Pasien'!G:V,6,FALSE),"") -> PEREMPUAN | P6: =IFNA(VLOOKUP(L6,'🙎‍♂️ Pasien'!G:V,12,FALSE),"") -> ISLAM | Q6: =IFNA(VLOOKUP(L6:L1508,'🙎‍♂️ Pasien'!G:V,13,FALSE),"") -> IRT | R6: {=ifna(xlookup(L6,'🙎‍♂️ Pasien'!$G$5:$G1508,'🙎‍♂️ Pasien'!$T$5:$T1508),"")} -> SAKIT PINGGANG KIRI | S6: {=ifna(xlookup(L6,'🙎‍♂️ Pasien'!$G$5:$G1508,'🙎‍♂️ Pasien'!$U$5:$U1508),"")} -> CATERING | T6: HADIR | U6: - | W6: TRUE
B7: PAGI | C7: {=IFNA(XLOOKUP(J7,'⚙️ Pengaturan'!$H$5:$H1508,'⚙️ Pengaturan'!$I$5:$I1508),"")} -> TIM Y | D7: SUCI | E7: 45931 | F7: =IF($E7="","",TEXT($E7,"YYYY")) -> 2025 | G7: =IF($E7="","",TEXT($E7,"MM")&TEXT($E7,"MMM")) -> 10Okt | H7: =IF($E7="","",TEXT($E7,"DDDD")) -> Rabu | I7: 10.00 | J7: WAHYU | K7: TERAPI AWAL | L7: LIM OI KHIUN ALS RIANA | M7: =IFNA(VLOOKUP(L7,'🙎‍♂️ Pasien'!G:V,2,FALSE),"") -> L5925109995 | N7: =IFNA(VLOOKUP(L7,'🙎‍♂️ Pasien'!G:L,3,FALSE),"") -> 67 | O7: =IFNA(VLOOKUP(L7,'🙎‍♂️ Pasien'!G:V,6,FALSE),"") -> PEREMPUAN | P7: =IFNA(VLOOKUP(L7,'🙎‍♂️ Pasien'!G:V,12,FALSE),"") -> KATOLIK | Q7: =IFNA(VLOOKUP(L7:L1508,'🙎‍♂️ Pasien'!G:V,13,FALSE),"") -> WIRASWASTA | R7: {=ifna(xlookup(L7,'🙎‍♂️ Pasien'!$G$5:$G1508,'🙎‍♂️ Pasien'!$T$5:$T1508),"")} -> LUTUT | S7: {=ifna(xlookup(L7,'🙎‍♂️ Pasien'!$G$5:$G1508,'🙎‍♂️ Pasien'!$U$5:$U1508),"")} -> IBU RUMAH TANGGA | T7: HADIR | U7: - | W7: TRUE
B8: PAGI | C8: {=IFNA(XLOOKUP(J8,'⚙️ Pengaturan'!$H$5:$H1508,'⚙️ Pengaturan'!$I$5:$I1508),"")} -> TIM A | D8: SUCI | E8: 45931 | F8: =IF($E8="","",TEXT($E8,"YYYY")) -> 2025 | G8: =IF($E8="","",TEXT($E8,"MM")&TEXT($E8,"MMM")) -> 10Okt | H8: =IF($E8="","",TEXT($E8,"DDDD")) -> Rabu | I8: 10.00 | J8: HESTI | K8: PAKET TERAPI | L8: LIM OI SIP ALS ERNY | M8: =IFNA(VLOOKUP(L8,'🙎‍♂️ Pasien'!G:V,2,FALSE),"") -> L5325099995 | N8: =IFNA(VLOOKUP(L8,'🙎‍♂️ Pasien'!G:L,3,FALSE),"") -> 73 | O8: =IFNA(VLOOKUP(L8,'🙎‍♂️ Pasien'!G:V,6,FALSE),"") -> PEREMPUAN | P8: =IFNA(VLOOKUP(L8,'🙎‍♂️ Pasien'!G:V,12,FALSE),"") -> KATOLIK | Q8: =IFNA(VLOOKUP(L8:L1508,'🙎‍♂️ Pasien'!G:V,13,FALSE),"") -> KARYAWAN SWASTA | R8: {=ifna(xlookup(L8,'🙎‍♂️ Pasien'!$G$5:$G1508,'🙎‍♂️ Pasien'!$T$5:$T1508),"")} -> OPERASI LUTUT | S8: {=ifna(xlookup(L8,'🙎‍♂️ Pasien'!$G$5:$G1508,'🙎‍♂️ Pasien'!$U$5:$U1508),"")} -> JALAN SEHAT | T8: HADIR | U8: 1 | W8: TRUE
B9: PAGI | C9: {=IFNA(XLOOKUP(J9,'⚙️ Pengaturan'!$H$5:$H1508,'⚙️ Pengaturan'!$I$5:$I1508),"")} -> TIM Y | D9: SUCI | E9: 45931 | F9: =IF($E9="","",TEXT($E9,"YYYY")) -> 2025 | G9: =IF($E9="","",TEXT($E9,"MM")&TEXT($E9,"MMM")) -> 10Okt | H9: =IF($E9="","",TEXT($E9,"DDDD")) -> Rabu | I9: 11.00 | J9: WAHYU | K9: PAKET TERAPI | L9: EDY HARTONO | M9: =IFNA(VLOOKUP(L9,'🙎‍♂️ Pasien'!G:V,2,FALSE),"") -> E7525090355 | N9: =IFNA(VLOOKUP(L9,'🙎‍♂️ Pasien'!G:L,3,FALSE),"") -> 51 | O9: =IFNA(VLOOKUP(L9,'🙎‍♂️ Pasien'!G:V,6,FALSE),"") -> LAKI-LAKI | P9: =IFNA(VLOOKUP(L9,'🙎‍♂️ Pasien'!G:V,12,FALSE),"") -> PROTESTAN | Q9: =IFNA(VLOOKUP(L9:L1508,'🙎‍♂️ Pasien'!G:V,13,FALSE),"") -> WIRAUSAHA | R9: {=ifna(xlookup(L9,'🙎‍♂️ Pasien'!$G$5:$G1508,'🙎‍♂️ Pasien'!$T$5:$T1508),"")} -> SAKIT DI BAHU | S9: {=ifna(xlookup(L9,'🙎‍♂️ Pasien'!$G$5:$G1508,'🙎‍♂️ Pasien'!$U$5:$U1508),"")} -> KARENA PUSH UP | T9: HADIR | U9: 4 | W9: TRUE
B10: PAGI | C10: {=IFNA(XLOOKUP(J10,'⚙️ Pengaturan'!$H$5:$H1508,'⚙️ Pengaturan'!$I$5:$I1508),"")} -> TIM A | D10: SUCI | E10: 45931 | F10: =IF($E10="","",TEXT($E10,"YYYY")) -> 2025 | G10: =IF($E10="","",TEXT($E10,"MM")&TEXT($E10,"MMM")) -> 10Okt | H10: =IF($E10="","",TEXT($E10,"DDDD")) -> Rabu | I10: 13.00 | J10: HESTI | K10: PAKET TERAPI | L10: AHMAD DANY NOVALDI | M10: =IFNA(VLOOKUP(L10,'🙎‍♂️ Pasien'!G:V,2,FALSE),"") -> A0625085349 | N10: =IFNA(VLOOKUP(L10,'🙎‍♂️ Pasien'!G:L,3,FALSE),"") -> 19 | O10: =IFNA(VLOOKUP(L10,'🙎‍♂️ Pasien'!G:V,6,FALSE),"") -> LAKI-LAKI | P10: =IFNA(VLOOKUP(L10,'🙎‍♂️ Pasien'!G:V,12,FALSE),"") -> ISLAM | Q10: =IFNA(VLOOKUP(L10:L1508,'🙎‍♂️ Pasien'!G:V,13,FALSE),"") -> PELAJAR/MAHASISWA | R10: {=ifna(xlookup(L10,'🙎‍♂️ Pasien'!$G$5:$G1508,'🙎‍♂️ Pasien'!$T$5:$T1508),"")} -> BAHU | S10: {=ifna(xlookup(L10,'🙎‍♂️ Pasien'!$G$5:$G1508,'🙎‍♂️ Pasien'!$U$5:$U1508),"")} -> SILAT | T10: TIDAK HADIR | U10: 5 | V10: ADA JADWAL UTS | W10: TRUE
B11: PAGI | C11: {=IFNA(XLOOKUP(J11,'⚙️ Pengaturan'!$H$5:$H1508,'⚙️ Pengaturan'!$I$5:$I1508),"")} -> TIM A | D11: SUCI | E11: 45931 | F11: =IF($E11="","",TEXT($E11,"YYYY")) -> 2025 | G11: =IF($E11="","",TEXT($E11,"MM")&TEXT($E11,"MMM")) -> 10Okt | H11: =IF($E11="","",TEXT($E11,"DDDD")) -> Rabu | I11: 13.00 | J11: OKTA | K11: PAKET TERAPI | L11: LENY SUMANTRI | M11: =IFNA(VLOOKUP(L11,'🙎‍♂️ Pasien'!G:V,2,FALSE),"") -> L8725094767 | N11: =IFNA(VLOOKUP(L11,'🙎‍♂️ Pasien'!G:L,3,FALSE),"") -> 38 | O11: =IFNA(VLOOKUP(L11,'🙎‍♂️ Pasien'!G:V,6,FALSE),"") -> PEREMPUAN | P11: =IFNA(VLOOKUP(L11,'🙎‍♂️ Pasien'!G:V,12,FALSE),"") -> KATOLIK | Q11: =IFNA(VLOOKUP(L11:L1508,'🙎‍♂️ Pasien'!G:V,13,FALSE),"") -> IBU RUMAH TANGGA | R11: {=ifna(xlookup(L11,'🙎‍♂️ Pasien'!$G$5:$G1508,'🙎‍♂️ Pasien'!$T$5:$T1508),"")} -> NYERI LEHER | S11: {=ifna(xlookup(L11,'🙎‍♂️ Pasien'!$G$5:$G1508,'🙎‍♂️ Pasien'!$U$5:$U1508),"")} -> KURANG GERAK | T11: HADIR | U11: 1 | W11: TRUE
B12: PAGI | C12: {=IFNA(XLOOKUP(J12,'⚙️ Pengaturan'!$H$5:$H1508,'⚙️ Pengaturan'!$I$5:$I1508),"")} -> MANAJEMEN | D12: SUCI | E12: 45931 | F12: =IF($E12="","",TEXT($E12,"YYYY")) -> 2025 | G12: =IF($E12="","",TEXT($E12,"MM")&TEXT($E12,"MMM")) -> 10Okt | H12: =IF($E12="","",TEXT($E12,"DDDD")) -> Rabu | I12: 13.00 | J12: EDO | K12: TERAPI AWAL | L12: SUHERDIYANTO, S.PD | M12: =IFNA(VLOOKUP(L12,'🙎‍♂️ Pasien'!G:V,2,FALSE),"") -> S8025102353 | N12: =IFNA(VLOOKUP(L12,'🙎‍♂️ Pasien'!G:L,3,FALSE),"") -> 46 | O12: =IFNA(VLOOKUP(L12,'🙎‍♂️ Pasien'!G:V,6,FALSE),"") -> LAKI-LAKI | P12: =IFNA(VLOOKUP(L12,'🙎‍♂️ Pasien'!G:V,12,FALSE),"") -> ISLAM | Q12: =IFNA(VLOOKUP(L12:L1508,'🙎‍♂️ Pasien'!G:V,13,FALSE),"") -> KARYAWAN HONORER | R12: {=ifna(xlookup(L12,'🙎‍♂️ Pasien'!$G$5:$G1508,'🙎‍♂️ Pasien'!$T$5:$T1508),"")} -> PINGGANG SAMPAI KAKI | S12: {=ifna(xlookup(L12,'🙎‍♂️ Pasien'!$G$5:$G1508,'🙎‍♂️ Pasien'!$U$5:$U1508),"")} -> SEPEDA DAN BULU TANGKIS | T12: HADIR | U12: - | W12: TRUE
B13: PAGI | C13: {=IFNA(XLOOKUP(J13,'⚙️ Pengaturan'!$H$5:$H1508,'⚙️ Pengaturan'!$I$5:$I1508),"")} -> TIM A | D13: SUCI | E13: 45931 | F13: =IF($E13="","",TEXT($E13,"YYYY")) -> 2025 | G13: =IF($E13="","",TEXT($E13,"MM")&TEXT($E13,"MMM")) -> 10Okt | H13: =IF($E13="","",TEXT($E13,"DDDD")) -> Rabu | I13: 14.00 | J13: HENA | K13: PAKET TERAPI | L13: MARIYAM | M13: =IFNA(VLOOKUP(L13,'🙎‍♂️ Pasien'!G:V,2,FALSE),"") -> M6825093469 | N13: =IFNA(VLOOKUP(L13,'🙎‍♂️ Pasien'!G:L,3,FALSE),"") -> 58 | O13: =IFNA(VLOOKUP(L13,'🙎‍♂️ Pasien'!G:V,6,FALSE),"") -> PEREMPUAN | P13: =IFNA(VLOOKUP(L13,'🙎‍♂️ Pasien'!G:V,12,FALSE),"") -> ISLAM | Q13: =IFNA(VLOOKUP(L13:L1508,'🙎‍♂️ Pasien'!G:V,13,FALSE),"") -> IBU RUMAH TANGGA | R13: {=ifna(xlookup(L13,'🙎‍♂️ Pasien'!$G$5:$G1508,'🙎‍♂️ Pasien'!$T$5:$T1508),"")} -> KAKI SAKIT SEKALI BERJALAN.. AWALNYA HANYA SATU KAKI YANG SAKIT PAS PULANG UMROH KAKI YANG TIDAK SAKIT JADI SAKIT SEKALI DAN SANGAT KESULITAN UNTUK BERJALAN DAN SAKITNYA SAMPE KE PINGGANG | S13: {=ifna(xlookup(L13,'🙎‍♂️ Pasien'!$G$5:$G1508,'🙎‍♂️ Pasien'!$U$5:$U1508),"")} -> ORANG YANG ULET, SUKA BEBERES, MASAK, NYIRAM TANAMAN, NYAPU, NGEPEL | T13: HADIR | U13: 3 | W13: TRUE
B14: SORE | C14: {=IFNA(XLOOKUP(J14,'⚙️ Pengaturan'!$H$5:$H1508,'⚙️ Pengaturan'!$I$5:$I1508),"")} -> TIM Y | D14: NOPI | E14: 45931 | F14: =IF($E14="","",TEXT($E14,"YYYY")) -> 2025 | G14: =IF($E14="","",TEXT($E14,"MM")&TEXT($E14,"MMM")) -> 10Okt | H14: =IF($E14="","",TEXT($E14,"DDDD")) -> Rabu | I14: 15.00 | J14: ORY | K14: SESI TERAPI | L14: FATI ARIFAH | M14: =IFNA(VLOOKUP(L14,'🙎‍♂️ Pasien'!G:V,2,FALSE),"") -> F1025103034 | N14: =IFNA(VLOOKUP(L14,'🙎‍♂️ Pasien'!G:L,3,FALSE),"") -> 16 | O14: =IFNA(VLOOKUP(L14,'🙎‍♂️ Pasien'!G:V,6,FALSE),"") -> PEREMPUAN | P14: =IFNA(VLOOKUP(L14,'🙎‍♂️ Pasien'!G:V,12,FALSE),"") -> ISLAM | Q14: =IFNA(VLOOKUP(L14:L1508,'🙎‍♂️ Pasien'!G:V,13,FALSE),"") -> MASIH SEKOLAH | R14: {=ifna(xlookup(L14,'🙎‍♂️ Pasien'!$G$5:$G1508,'🙎‍♂️ Pasien'!$T$5:$T1508),"")} -> PADA SAAT JALAN DEKAT MATA KAKI TERASA SAKIT | S14: {=ifna(xlookup(L14,'🙎‍♂️ Pasien'!$G$5:$G1508,'🙎‍♂️ Pasien'!$U$5:$U1508),"")} -> SILAT | T14: HADIR | U14: - | V14: BEASISWA BANG EDO | W14: TRUE
B15: SORE | C15: {=IFNA(XLOOKUP(J15,'⚙️ Pengaturan'!$H$5:$H1508,'⚙️ Pengaturan'!$I$5:$I1508),"")} -> TIM Y | D15: NOPI | E15: 45931 | F15: =IF($E15="","",TEXT($E15,"YYYY")) -> 2025 | G15: =IF($E15="","",TEXT($E15,"MM")&TEXT($E15,"MMM")) -> 10Okt | H15: =IF($E15="","",TEXT($E15,"DDDD")) -> Rabu | I15: 15.00 | J15: DESTY | K15: PAKET TERAPI | L15: HO HIAN KI | M15: =IFNA(VLOOKUP(L15,'🙎‍♂️ Pasien'!G:V,2,FALSE),"") -> H5024091565 | N15: =IFNA(VLOOKUP(L15,'🙎‍♂️ Pasien'!G:L,3,FALSE),"") -> 75 | O15: =IFNA(VLOOKUP(L15,'🙎‍♂️ Pasien'!G:V,6,FALSE),"") -> PEREMPUAN | P15: =IFNA(VLOOKUP(L15,'🙎‍♂️ Pasien'!G:V,12,FALSE),"") -> BUDDHA | Q15: =IFNA(VLOOKUP(L15:L1508,'🙎‍♂️ Pasien'!G:V,13,FALSE),"") -> RUMAH TANGGA | R15: {=ifna(xlookup(L15,'🙎‍♂️ Pasien'!$G$5:$G1508,'🙎‍♂️ Pasien'!$T$5:$T1508),"")} -> NYERI/KESEMUTAN DI PAHA KIRI | S15: {=ifna(xlookup(L15,'🙎‍♂️ Pasien'!$G$5:$G1508,'🙎‍♂️ Pasien'!$U$5:$U1508),"")} -> MENANAM BUNGA | T15: HADIR | U15: 6 | W15: TRUE
B16: SORE | C16: {=IFNA(XLOOKUP(J16,'⚙️ Pengaturan'!$H$5:$H1508,'⚙️ Pengaturan'!$I$5:$I1508),"")} -> TIM Y | D16: NOPI | E16: 45931 | F16: =IF($E16="","",TEXT($E16,"YYYY")) -> 2025 | G16: =IF($E16="","",TEXT($E16,"MM")&TEXT($E16,"MMM")) -> 10Okt | H16: =IF($E16="","",TEXT($E16,"DDDD")) -> Rabu | I16: 16.00 | J16: DESTY | K16: PAKET TERAPI | L16: AISHA NAJWA AQILA | M16: =IFNA(VLOOKUP(L16,'🙎‍♂️ Pasien'!G:V,2,FALSE),"") -> A0825098780 | N16: =IFNA(VLOOKUP(L16,'🙎‍♂️ Pasien'!G:L,3,FALSE),"") -> 18 | O16: =IFNA(VLOOKUP(L16,'🙎‍♂️ Pasien'!G:V,6,FALSE),"") -> PEREMPUAN | P16: =IFNA(VLOOKUP(L16,'🙎‍♂️ Pasien'!G:V,12,FALSE),"") -> ISLAM | Q16: =IFNA(VLOOKUP(L16:L1508,'🙎‍♂️ Pasien'!G:V,13,FALSE),"") -> PELAJAR | R16: {=ifna(xlookup(L16,'🙎‍♂️ Pasien'!$G$5:$G1508,'🙎‍♂️ Pasien'!$T$5:$T1508),"")} -> SAKIT DI LUTUT | S16: {=ifna(xlookup(L16,'🙎‍♂️ Pasien'!$G$5:$G1508,'🙎‍♂️ Pasien'!$U$5:$U1508),"")} -> MAIN BASKET | T16: HADIR | U16: 2 | W16: TRUE
B17: SORE | C17: {=IFNA(XLOOKUP(J17,'⚙️ Pengaturan'!$H$5:$H1508,'⚙️ Pengaturan'!$I$5:$I1508),"")} -> TIM Y | D17: NOPI | E17: 45931 | F17: =IF($E17="","",TEXT($E17,"YYYY")) -> 2025 | G17: =IF($E17="","",TEXT($E17,"MM")&TEXT($E17,"MMM")) -> 10Okt | H17: =IF($E17="","",TEXT($E17,"DDDD")) -> Rabu | I17: 17.00 | J17: ORY | K17: PAKET TERAPI | L17: ALBYAN RAFIF MAHESWARA | M17: =IFNA(VLOOKUP(L17,'🙎‍♂️ Pasien'!G:V,2,FALSE),"") -> A0925094650 | N17: =IFNA(VLOOKUP(L17,'🙎‍♂️ Pasien'!G:L,3,FALSE),"") -> 17 | O17: =IFNA(VLOOKUP(L17,'🙎‍♂️ Pasien'!G:V,6,FALSE),"") -> LAKI-LAKI | P17: =IFNA(VLOOKUP(L17,'🙎‍♂️ Pasien'!G:V,12,FALSE),"") -> ISLAM | Q17: =IFNA(VLOOKUP(L17:L1508,'🙎‍♂️ Pasien'!G:V,13,FALSE),"") -> PELAJAR | R17: {=ifna(xlookup(L17,'🙎‍♂️ Pasien'!$G$5:$G1508,'🙎‍♂️ Pasien'!$T$5:$T1508),"")} -> LUTUT | S17: {=ifna(xlookup(L17,'🙎‍♂️ Pasien'!$G$5:$G1508,'🙎‍♂️ Pasien'!$U$5:$U1508),"")} -> FUTSAL | T17: HADIR | U17: 5 | W17: TRUE
B18: SORE | C18: {=IFNA(XLOOKUP(J18,'⚙️ Pengaturan'!$H$5:$H1508,'⚙️ Pengaturan'!$I$5:$I1508),"")} -> TIM Y | D18: NOPI | E18: 45931 | F18: =IF($E18="","",TEXT($E18,"YYYY")) -> 2025 | G18: =IF($E18="","",TEXT($E18,"MM")&TEXT($E18,"MMM")) -> 10Okt | H18: =IF($E18="","",TEXT($E18,"DDDD")) -> Rabu | I18: 19.00 | J18: ORY | K18: PAKET TERAPI | L18: LICA | M18: =IFNA(VLOOKUP(L18,'🙎‍♂️ Pasien'!G:V,2,FALSE),"") -> L9925048099 | N18: =IFNA(VLOOKUP(L18,'🙎‍♂️ Pasien'!G:L,3,FALSE),"") -> 26 | O18: =IFNA(VLOOKUP(L18,'🙎‍♂️ Pasien'!G:V,6,FALSE),"") -> PEREMPUAN | P18: =IFNA(VLOOKUP(L18,'🙎‍♂️ Pasien'!G:V,12,FALSE),"") -> KATOLIK | Q18: =IFNA(VLOOKUP(L18:L1508,'🙎‍♂️ Pasien'!G:V,13,FALSE),"") -> ACCOUNTING | R18: {=ifna(xlookup(L18,'🙎‍♂️ Pasien'!$G$5:$G1508,'🙎‍♂️ Pasien'!$T$5:$T1508),"")} -> NYERI TULANG BELAKANG SAMPAI KAKI, NYERI DI BAGIAN LUTUT JUGA | S18: {=ifna(xlookup(L18,'🙎‍♂️ Pasien'!$G$5:$G1508,'🙎‍♂️ Pasien'!$U$5:$U1508),"")} -> BANYAK DUDUK | T18: HADIR | U18: 5 | W18: TRUE
B19: SORE | C19: {=IFNA(XLOOKUP(J19,'⚙️ Pengaturan'!$H$5:$H1508,'⚙️ Pengaturan'!$I$5:$I1508),"")} -> TIM Y | D19: NOPI | E19: 45931 | F19: =IF($E19="","",TEXT($E19,"YYYY")) -> 2025 | G19: =IF($E19="","",TEXT($E19,"MM")&TEXT($E19,"MMM")) -> 10Okt | H19: =IF($E19="","",TEXT($E19,"DDDD")) -> Rabu | I19: 20.00 | J19: ORY | K19: PAKET TERAPI | L19: A. SYUKUR H. JAFRI | M19: =IFNA(VLOOKUP(L19,'🙎‍♂️ Pasien'!G:V,2,FALSE),"") -> A6125094370 | N19: =IFNA(VLOOKUP(L19,'🙎‍♂️ Pasien'!G:L,3,FALSE),"") -> 64 | O19: =IFNA(VLOOKUP(L19,'🙎‍♂️ Pasien'!G:V,6,FALSE),"") -> LAKI-LAKI | P19: =IFNA(VLOOKUP(L19,'🙎‍♂️ Pasien'!G:V,12,FALSE),"") -> ISLAM | Q19: =IFNA(VLOOKUP(L19:L1508,'🙎‍♂️ Pasien'!G:V,13,FALSE),"") -> WIRASWASTA | R19: {=ifna(xlookup(L19,'🙎‍♂️ Pasien'!$G$5:$G1508,'🙎‍♂️ Pasien'!$T$5:$T1508),"")} -> NYERI DI SENDI BAHU, SAKIT KETIKA DI ANGKAT AGAK TINGGI | S19: {=ifna(xlookup(L19,'🙎‍♂️ Pasien'!$G$5:$G1508,'🙎‍♂️ Pasien'!$U$5:$U1508),"")} -> TERKADANG ANGKAT2 BARANG, TP TIDAK SETIAP HARI. ADA RIWAYAT JATUH | T19: HADIR | U19: 3 | W19: TRUE
B20: PAGI | C20: {=IFNA(XLOOKUP(J20,'⚙️ Pengaturan'!$H$5:$H1508,'⚙️ Pengaturan'!$I$5:$I1508),"")} -> MANAJEMEN | D20: NOPI | E20: 45932 | F20: =IF($E20="","",TEXT($E20,"YYYY")) -> 2025 | G20: =IF($E20="","",TEXT($E20,"MM")&TEXT($E20,"MMM")) -> 10Okt | H20: =IF($E20="","",TEXT($E20,"DDDD")) -> Kamis | I20: 09.00 | J20: DANI | K20: PAKET TERAPI | L20: BOBY ANTA MAULANA | M20: =IFNA(VLOOKUP(L20,'🙎‍♂️ Pasien'!G:V,2,FALSE),"") -> B8525075344 | N20: =IFNA(VLOOKUP(L20,'🙎‍♂️ Pasien'!G:L,3,FALSE),"") -> 40 | O20: =IFNA(VLOOKUP(L20,'🙎‍♂️ Pasien'!G:V,6,FALSE),"") -> LAKI-LAKI | P20: =IFNA(VLOOKUP(L20,'🙎‍♂️ Pasien'!G:V,12,FALSE),"") -> ISLAM | Q20: =IFNA(VLOOKUP(L20:L1508,'🙎‍♂️ Pasien'!G:V,13,FALSE),"") -> WIRAUSAHA | R20: {=ifna(xlookup(L20,'🙎‍♂️ Pasien'!$G$5:$G1508,'🙎‍♂️ Pasien'!$T$5:$T1508),"")} -> NYERI LUTUT | S20: {=ifna(xlookup(L20,'🙎‍♂️ Pasien'!$G$5:$G1508,'🙎‍♂️ Pasien'!$U$5:$U1508),"")} -> JOGGING | T20: TIDAK HADIR | U20: 10 | V20: EVAL/ 09.30/ADA HAL MENDADAK | W20: TRUE
B21: PAGI | C21: {=IFNA(XLOOKUP(J21,'⚙️ Pengaturan'!$H$5:$H1508,'⚙️ Pengaturan'!$I$5:$I1508),"")} -> TIM Y | D21: NOPI | E21: 45932 | F21: =IF($E21="","",TEXT($E21,"YYYY")) -> 2025 | G21: =IF($E21="","",TEXT($E21,"MM")&TEXT($E21,"MMM")) -> 10Okt | H21: =IF($E21="","",TEXT($E21,"DDDD")) -> Kamis | I21: 09.00 | J21: ORY | K21: PAKET TERAPI | L21: FRANKY WILLIAM | M21: =IFNA(VLOOKUP(L21,'🙎‍♂️ Pasien'!G:V,2,FALSE),"") -> F4925091811 | N21: =IFNA(VLOOKUP(L21,'🙎‍♂️ Pasien'!G:L,3,FALSE),"") -> 76 | O21: =IFNA(VLOOKUP(L21,'🙎‍♂️ Pasien'!G:V,6,FALSE),"") -> LAKI-LAKI | P21: =IFNA(VLOOKUP(L21,'🙎‍♂️ Pasien'!G:V,12,FALSE),"") -> KHONGHUCU | Q21: =IFNA(VLOOKUP(L21:L1508,'🙎‍♂️ Pasien'!G:V,13,FALSE),"") -> PENSIUN | R21: {=ifna(xlookup(L21,'🙎‍♂️ Pasien'!$G$5:$G1508,'🙎‍♂️ Pasien'!$T$5:$T1508),"")} -> KAKI GA KUAT | S21: {=ifna(xlookup(L21,'🙎‍♂️ Pasien'!$G$5:$G1508,'🙎‍♂️ Pasien'!$U$5:$U1508),"")} -> BERJALAN MENGGUNAKAN TONGKAT | T21: HADIR | U21: 2 | W21: TRUE
B22: PAGI | C22: {=IFNA(XLOOKUP(J22,'⚙️ Pengaturan'!$H$5:$H1508,'⚙️ Pengaturan'!$I$5:$I1508),"")} -> TIM Y | D22: NOPI | E22: 45932 | F22: =IF($E22="","",TEXT($E22,"YYYY")) -> 2025 | G22: =IF($E22="","",TEXT($E22,"MM")&TEXT($E22,"MMM")) -> 10Okt | H22: =IF($E22="","",TEXT($E22,"DDDD")) -> Kamis | I22: 09.00 | J22: DESTY | K22: TERAPI AWAL | L22: LISA MEGASARI | M22: =IFNA(VLOOKUP(L22,'🙎‍♂️ Pasien'!G:V,2,FALSE),"") -> L8625105331 | N22: =IFNA(VLOOKUP(L22,'🙎‍♂️ Pasien'!G:L,3,FALSE),"") -> 39 | O22: =IFNA(VLOOKUP(L22,'🙎‍♂️ Pasien'!G:V,6,FALSE),"") -> PEREMPUAN | P22: =IFNA(VLOOKUP(L22,'🙎‍♂️ Pasien'!G:V,12,FALSE),"") -> ISLAM | Q22: =IFNA(VLOOKUP(L22:L1508,'🙎‍♂️ Pasien'!G:V,13,FALSE),"") -> SWASTA | R22: {=ifna(xlookup(L22,'🙎‍♂️ Pasien'!$G$5:$G1508,'🙎‍♂️ Pasien'!$T$5:$T1508),"")} -> BENUA MELAYU LAUT | S22: {=ifna(xlookup(L22,'🙎‍♂️ Pasien'!$G$5:$G1508,'🙎‍♂️ Pasien'!$U$5:$U1508),"")} -> BERJALAN | T22: TIDAK HADIR | U22: - | V22: KEL KAKI/ PINDAH JAM 15.00 | W22: TRUE
B23: PAGI | C23: {=IFNA(XLOOKUP(J23,'⚙️ Pengaturan'!$H$5:$H1508,'⚙️ Pengaturan'!$I$5:$I1508),"")} -> TIM Y | D23: NOPI | E23: 45932 | F23: =IF($E23="","",TEXT($E23,"YYYY")) -> 2025 | G23: =IF($E23="","",TEXT($E23,"MM")&TEXT($E23,"MMM")) -> 10Okt | H23: =IF($E23="","",TEXT($E23,"DDDD")) -> Kamis | I23: 10.00 | J23: PRITY | K23: PAKET TERAPI | L23: ANDRIANI | M23: =IFNA(VLOOKUP(L23,'🙎‍♂️ Pasien'!G:V,2,FALSE),"") -> A5625092572 | N23: =IFNA(VLOOKUP(L23,'🙎‍♂️ Pasien'!G:L,3,FALSE),"") -> 69 | O23: =IFNA(VLOOKUP(L23,'🙎‍♂️ Pasien'!G:V,6,FALSE),"") -> PEREMPUAN | P23: =IFNA(VLOOKUP(L23,'🙎‍♂️ Pasien'!G:V,12,FALSE),"") -> ISLAM | Q23: =IFNA(VLOOKUP(L23:L1508,'🙎‍♂️ Pasien'!G:V,13,FALSE),"") -> IRT | R23: {=ifna(xlookup(L23,'🙎‍♂️ Pasien'!$G$5:$G1508,'🙎‍♂️ Pasien'!$T$5:$T1508),"")} -> PINGGANG DAN KAKI | S23: {=ifna(xlookup(L23,'🙎‍♂️ Pasien'!$G$5:$G1508,'🙎‍♂️ Pasien'!$U$5:$U1508),"")} -> - | T23: HADIR | U23: 3 | V23: PELUNASAN 250K | W23: TRUE
B24: PAGI | C24: {=IFNA(XLOOKUP(J24,'⚙️ Pengaturan'!$H$5:$H1508,'⚙️ Pengaturan'!$I$5:$I1508),"")} -> TIM Y | D24: NOPI | E24: 45932 | F24: =IF($E24="","",TEXT($E24,"YYYY")) -> 2025 | G24: =IF($E24="","",TEXT($E24,"MM")&TEXT($E24,"MMM")) -> 10Okt | H24: =IF($E24="","",TEXT($E24,"DDDD")) -> Kamis | I24: 11.00 | J24: DESTY | K24: PAKET TERAPI | L24: ERLIN NURLIAWATY | M24: =IFNA(VLOOKUP(L24,'🙎‍♂️ Pasien'!G:V,2,FALSE),"") -> E8425098000 | N24: =IFNA(VLOOKUP(L24,'🙎‍♂️ Pasien'!G:L,3,FALSE),"") -> 41 | O24: =IFNA(VLOOKUP(L24,'🙎‍♂️ Pasien'!G:V,6,FALSE),"") -> PEREMPUAN | P24: =IFNA(VLOOKUP(L24,'🙎‍♂️ Pasien'!G:V,12,FALSE),"") -> BUDDHA | Q24: =IFNA(VLOOKUP(L24:L1508,'🙎‍♂️ Pasien'!G:V,13,FALSE),"") -> IRT | R24: {=ifna(xlookup(L24,'🙎‍♂️ Pasien'!$G$5:$G1508,'🙎‍♂️ Pasien'!$T$5:$T1508),"")} -> TANGAN KESEMUTAN | S24: {=ifna(xlookup(L24,'🙎‍♂️ Pasien'!$G$5:$G1508,'🙎‍♂️ Pasien'!$U$5:$U1508),"")} -> - | T24: TIDAK HADIR | U24: 2 | V24: RESCEDUE SENIN | W24: TRUE
B25: PAGI | C25: {=IFNA(XLOOKUP(J25,'⚙️ Pengaturan'!$H$5:$H1508,'⚙️ Pengaturan'!$I$5:$I1508),"")} -> TIM Y | D25: NOPI | E25: 45932 | F25: =IF($E25="","",TEXT($E25,"YYYY")) -> 2025 | G25: =IF($E25="","",TEXT($E25,"MM")&TEXT($E25,"MMM")) -> 10Okt | H25: =IF($E25="","",TEXT($E25,"DDDD")) -> Kamis | I25: 11.00 | J25: ORY | K25: PAKET TERAPI | L25: SUYONO | M25: =IFNA(VLOOKUP(L25,'🙎‍♂️ Pasien'!G:V,2,FALSE),"") -> S7125096750 | N25: =IFNA(VLOOKUP(L25,'🙎‍♂️ Pasien'!G:L,3,FALSE),"") -> 55 | O25: =IFNA(VLOOKUP(L25,'🙎‍♂️ Pasien'!G:V,6,FALSE),"") -> LAKI-LAKI | P25: =IFNA(VLOOKUP(L25,'🙎‍♂️ Pasien'!G:V,12,FALSE),"") -> ISLAM | Q25: =IFNA(VLOOKUP(L25:L1508,'🙎‍♂️ Pasien'!G:V,13,FALSE),"") -> KARYAWAN | R25: {=ifna(xlookup(L25,'🙎‍♂️ Pasien'!$G$5:$G1508,'🙎‍♂️ Pasien'!$T$5:$T1508),"")} -> OTOT LENGAN KANAN | S25: {=ifna(xlookup(L25,'🙎‍♂️ Pasien'!$G$5:$G1508,'🙎‍♂️ Pasien'!$U$5:$U1508),"")} -> TENIS | T25: HADIR | U25: 3 | W25: TRUE
B26: PAGI | C26: {=IFNA(XLOOKUP(J26,'⚙️ Pengaturan'!$H$5:$H1508,'⚙️ Pengaturan'!$I$5:$I1508),"")} -> TIM Y | D26: NOPI | E26: 45932 | F26: =IF($E26="","",TEXT($E26,"YYYY")) -> 2025 | G26: =IF($E26="","",TEXT($E26,"MM")&TEXT($E26,"MMM")) -> 10Okt | H26: =IF($E26="","",TEXT($E26,"DDDD")) -> Kamis | I26: 13.00 | J26: DESTY | K26: PAKET TERAPI | L26: HENG KENG SENG | M26: =IFNA(VLOOKUP(L26,'🙎‍♂️ Pasien'!G:V,2,FALSE),"") -> H5325098176 | N26: =IFNA(VLOOKUP(L26,'🙎‍♂️ Pasien'!G:L,3,FALSE),"") -> 73 | O26: =IFNA(VLOOKUP(L26,'🙎‍♂️ Pasien'!G:V,6,FALSE),"") -> LAKI-LAKI | P26: =IFNA(VLOOKUP(L26,'🙎‍♂️ Pasien'!G:V,12,FALSE),"") -> BUDDHA | Q26: =IFNA(VLOOKUP(L26:L1508,'🙎‍♂️ Pasien'!G:V,13,FALSE),"") -> PENSIUN | R26: {=ifna(xlookup(L26,'🙎‍♂️ Pasien'!$G$5:$G1508,'🙎‍♂️ Pasien'!$T$5:$T1508),"")} -> KAKI GAK BISA JONGKOK | S26: {=ifna(xlookup(L26,'🙎‍♂️ Pasien'!$G$5:$G1508,'🙎‍♂️ Pasien'!$U$5:$U1508),"")} -> —— | T26: TIDAK HADIR | U26: 2 | V26: FISIO SAKIT, JADI PINDAH SABTU | W26: TRUE
B27: PAGI | C27: {=IFNA(XLOOKUP(J27,'⚙️ Pengaturan'!$H$5:$H1508,'⚙️ Pengaturan'!$I$5:$I1508),"")} -> TIM Y | D27: NOPI | E27: 45932 | F27: =IF($E27="","",TEXT($E27,"YYYY")) -> 2025 | G27: =IF($E27="","",TEXT($E27,"MM")&TEXT($E27,"MMM")) -> 10Okt | H27: =IF($E27="","",TEXT($E27,"DDDD")) -> Kamis | I27: 13.00 | J27: ORY | K27: TERAPI AWAL | L27: SHAOUQI NASHUHA | M27: =IFNA(VLOOKUP(L27,'🙎‍♂️ Pasien'!G:V,2,FALSE),"") -> S9625108010 | N27: =IFNA(VLOOKUP(L27,'🙎‍♂️ Pasien'!G:L,3,FALSE),"") -> 29 | O27: =IFNA(VLOOKUP(L27,'🙎‍♂️ Pasien'!G:V,6,FALSE),"") -> LAKI-LAKI | P27: =IFNA(VLOOKUP(L27,'🙎‍♂️ Pasien'!G:V,12,FALSE),"") -> ISLAM | Q27: =IFNA(VLOOKUP(L27:L1508,'🙎‍♂️ Pasien'!G:V,13,FALSE),"") -> MARKETING | R27: {=ifna(xlookup(L27,'🙎‍♂️ Pasien'!$G$5:$G1508,'🙎‍♂️ Pasien'!$T$5:$T1508),"")} -> ANKLE SPRAIN | S27: {=ifna(xlookup(L27,'🙎‍♂️ Pasien'!$G$5:$G1508,'🙎‍♂️ Pasien'!$U$5:$U1508),"")} -> TENNIS | T27: HADIR | U27: - | W27: TRUE
B28: PAGI | C28: {=IFNA(XLOOKUP(J28,'⚙️ Pengaturan'!$H$5:$H1508,'⚙️ Pengaturan'!$I$5:$I1508),"")} -> TIM Y | D28: NOPI | E28: 45932 | F28: =IF($E28="","",TEXT($E28,"YYYY")) -> 2025 | G28: =IF($E28="","",TEXT($E28,"MM")&TEXT($E28,"MMM")) -> 10Okt | H28: =IF($E28="","",TEXT($E28,"DDDD")) -> Kamis | I28: 14.00 | J28: PRITY | K28: PAKET TERAPI | L28: HELIE | M28: =IFNA(VLOOKUP(L28,'🙎‍♂️ Pasien'!G:V,2,FALSE),"") -> H7825098625 | N28: =IFNA(VLOOKUP(L28,'🙎‍♂️ Pasien'!G:L,3,FALSE),"") -> 47 | O28: =IFNA(VLOOKUP(L28,'🙎‍♂️ Pasien'!G:V,6,FALSE),"") -> LAKI-LAKI | P28: =IFNA(VLOOKUP(L28,'🙎‍♂️ Pasien'!G:V,12,FALSE),"") -> KHONGHUCU | Q28: =IFNA(VLOOKUP(L28:L1508,'🙎‍♂️ Pasien'!G:V,13,FALSE),"") -> WIRASWASTA | R28: {=ifna(xlookup(L28,'🙎‍♂️ Pasien'!$G$5:$G1508,'🙎‍♂️ Pasien'!$T$5:$T1508),"")} -> SIANTAN | S28: {=ifna(xlookup(L28,'🙎‍♂️ Pasien'!$G$5:$G1508,'🙎‍♂️ Pasien'!$U$5:$U1508),"")} -> GYM | T28: HADIR | U28: 2 | W28: TRUE
B29: PAGI | C29: {=IFNA(XLOOKUP(J29,'⚙️ Pengaturan'!$H$5:$H1508,'⚙️ Pengaturan'!$I$5:$I1508),"")} -> TIM Y | D29: NOPI | E29: 45932 | F29: =IF($E29="","",TEXT($E29,"YYYY")) -> 2025 | G29: =IF($E29="","",TEXT($E29,"MM")&TEXT($E29,"MMM")) -> 10Okt | H29: =IF($E29="","",TEXT($E29,"DDDD")) -> Kamis | I29: 14.00 | J29: DESTY | K29: PAKET TERAPI | L29: MASDIARTI | M29: =IFNA(VLOOKUP(L29,'🙎‍♂️ Pasien'!G:V,2,FALSE),"") -> M7525052841 | N29: =IFNA(VLOOKUP(L29,'🙎‍♂️ Pasien'!G:L,3,FALSE),"") -> 50 | O29: =IFNA(VLOOKUP(L29,'🙎‍♂️ Pasien'!G:V,6,FALSE),"") -> PEREMPUAN | P29: =IFNA(VLOOKUP(L29,'🙎‍♂️ Pasien'!G:V,12,FALSE),"") -> ISLAM | Q29: =IFNA(VLOOKUP(L29:L1508,'🙎‍♂️ Pasien'!G:V,13,FALSE),"") -> IBU RUMAH TANGGA | R29: {=ifna(xlookup(L29,'🙎‍♂️ Pasien'!$G$5:$G1508,'🙎‍♂️ Pasien'!$T$5:$T1508),"")} -> RHUMBOID PAIN, CARPAL TUNNEL SYNDROME, PIRIFORMIS SYNDROME | S29: {=ifna(xlookup(L29,'🙎‍♂️ Pasien'!$G$5:$G1508,'🙎‍♂️ Pasien'!$U$5:$U1508),"")} -> AKTIVITAS RUMAH TANGGA (CUCI DAN SETRIKA PAKAIAN) | T29: TIDAK HADIR | U29: 5 | V29: EVAL/ PINDAH JAM 20.00 | W29: TRUE
B30: SORE | C30: {=IFNA(XLOOKUP(J30,'⚙️ Pengaturan'!$H$5:$H1508,'⚙️ Pengaturan'!$I$5:$I1508),"")} -> TIM Y | D30: SUCI | E30: 45932 | F30: =IF($E30="","",TEXT($E30,"YYYY")) -> 2025 | G30: =IF($E30="","",TEXT($E30,"MM")&TEXT($E30,"MMM")) -> 10Okt | H30: =IF($E30="","",TEXT($E30,"DDDD")) -> Kamis | I30: 15.00 | J30: WAHYU | K30: PAKET TERAPI | L30: HARDJONO | M30: =IFNA(VLOOKUP(L30,'🙎‍♂️ Pasien'!G:V,2,FALSE),"") -> H4623015667 | N30: =IFNA(VLOOKUP(L30,'🙎‍♂️ Pasien'!G:L,3,FALSE),"") -> 80 | O30: =IFNA(VLOOKUP(L30,'🙎‍♂️ Pasien'!G:V,6,FALSE),"") -> LAKI-LAKI | P30: =IFNA(VLOOKUP(L30,'🙎‍♂️ Pasien'!G:V,12,FALSE),"") -> ISLAM | Q30: =IFNA(VLOOKUP(L30:L1508,'🙎‍♂️ Pasien'!G:V,13,FALSE),"") -> PENSIUN | R30: {=ifna(xlookup(L30,'🙎‍♂️ Pasien'!$G$5:$G1508,'🙎‍♂️ Pasien'!$T$5:$T1508),"")} -> STROKE | S30: {=ifna(xlookup(L30,'🙎‍♂️ Pasien'!$G$5:$G1508,'🙎‍♂️ Pasien'!$U$5:$U1508),"")} | T30: HADIR | U30: 8 | W30: TRUE
B31: SORE | C31: {=IFNA(XLOOKUP(J31,'⚙️ Pengaturan'!$H$5:$H1508,'⚙️ Pengaturan'!$I$5:$I1508),"")} -> TIM A | D31: SUCI | E31: 45932 | F31: =IF($E31="","",TEXT($E31,"YYYY")) -> 2025 | G31: =IF($E31="","",TEXT($E31,"MM")&TEXT($E31,"MMM")) -> 10Okt | H31: =IF($E31="","",TEXT($E31,"DDDD")) -> Kamis | I31: 15.00 | J31: HESTI | K31: TERAPI AWAL | L31: LISA MEGASARI | M31: =IFNA(VLOOKUP(L31,'🙎‍♂️ Pasien'!G:V,2,FALSE),"") -> L8625105331 | N31: =IFNA(VLOOKUP(L31,'🙎‍♂️ Pasien'!G:L,3,FALSE),"") -> 39 | O31: =IFNA(VLOOKUP(L31,'🙎‍♂️ Pasien'!G:V,6,FALSE),"") -> PEREMPUAN | P31: =IFNA(VLOOKUP(L31,'🙎‍♂️ Pasien'!G:V,12,FALSE),"") -> ISLAM | Q31: =IFNA(VLOOKUP(L31:L1508,'🙎‍♂️ Pasien'!G:V,13,FALSE),"") -> SWASTA | R31: {=ifna(xlookup(L31,'🙎‍♂️ Pasien'!$G$5:$G1508,'🙎‍♂️ Pasien'!$T$5:$T1508),"")} -> BENUA MELAYU LAUT | S31: {=ifna(xlookup(L31,'🙎‍♂️ Pasien'!$G$5:$G1508,'🙎‍♂️ Pasien'!$U$5:$U1508),"")} -> BERJALAN | T31: TIDAK HADIR | U31: - | V31: KEL KAKI/ pindah jam 19.00 | W31: TRUE
B32: SORE | C32: {=IFNA(XLOOKUP(J32,'⚙️ Pengaturan'!$H$5:$H1508,'⚙️ Pengaturan'!$I$5:$I1508),"")} -> TIM A | D32: SUCI | E32: 45932 | F32: =IF($E32="","",TEXT($E32,"YYYY")) -> 2025 | G32: =IF($E32="","",TEXT($E32,"MM")&TEXT($E32,"MMM")) -> 10Okt | H32: =IF($E32="","",TEXT($E32,"DDDD")) -> Kamis | I32: 15.00 | J32: HESTI | K32: TERAPI AWAL | L32: ROBINSON NAINGGOLAN | M32: =IFNA(VLOOKUP(L32,'🙎‍♂️ Pasien'!G:V,2,FALSE),"") -> R9625100137 | N32: =IFNA(VLOOKUP(L32,'🙎‍♂️ Pasien'!G:L,3,FALSE),"") -> 29 | O32: =IFNA(VLOOKUP(L32,'🙎‍♂️ Pasien'!G:V,6,FALSE),"") -> LAKI-LAKI | P32: =IFNA(VLOOKUP(L32,'🙎‍♂️ Pasien'!G:V,12,FALSE),"") -> KATOLIK | Q32: =IFNA(VLOOKUP(L32:L1508,'🙎‍♂️ Pasien'!G:V,13,FALSE),"") -> SWASTA | R32: {=ifna(xlookup(L32,'🙎‍♂️ Pasien'!$G$5:$G1508,'🙎‍♂️ Pasien'!$T$5:$T1508),"")} -> CEDERA DI LUTUT | S32: {=ifna(xlookup(L32,'🙎‍♂️ Pasien'!$G$5:$G1508,'🙎‍♂️ Pasien'!$U$5:$U1508),"")} -> OLAHRAGA SEPAK BOLA , FUTSAL | T32: HADIR | U32: - | W32: TRUE
B33: SORE | C33: {=IFNA(XLOOKUP(J33,'⚙️ Pengaturan'!$H$5:$H1508,'⚙️ Pengaturan'!$I$5:$I1508),"")} -> TIM A | D33: SUCI | E33: 45932 | F33: =IF($E33="","",TEXT($E33,"YYYY")) -> 2025 | G33: =IF($E33="","",TEXT($E33,"MM")&TEXT($E33,"MMM")) -> 10Okt | H33: =IF($E33="","",TEXT($E33,"DDDD")) -> Kamis | I33: 16.00 | J33: HENA | K33: TERAPI AWAL | L33: AYDA RIANI JOHAR | M33: =IFNA(VLOOKUP(L33,'🙎‍♂️ Pasien'!G:V,2,FALSE),"") -> A0025068439 | N33: =IFNA(VLOOKUP(L33,'🙎‍♂️ Pasien'!G:L,3,FALSE),"") -> 25 | O33: =IFNA(VLOOKUP(L33,'🙎‍♂️ Pasien'!G:V,6,FALSE),"") -> PEREMPUAN | P33: =IFNA(VLOOKUP(L33,'🙎‍♂️ Pasien'!G:V,12,FALSE),"") -> BUDDHA | Q33: =IFNA(VLOOKUP(L33:L1508,'🙎‍♂️ Pasien'!G:V,13,FALSE),"") -> PEKERJA LEPAS/ FREELANCE | R33: {=ifna(xlookup(L33,'🙎‍♂️ Pasien'!$G$5:$G1508,'🙎‍♂️ Pasien'!$T$5:$T1508),"")} -> LUTUT SAKIT KARENA SALAH SQUAD/ JONGKOK DI OLAHRAGA/ GYM. | S33: {=ifna(xlookup(L33,'🙎‍♂️ Pasien'!$G$5:$G1508,'🙎‍♂️ Pasien'!$U$5:$U1508),"")} -> OLAHRAGA FITNESS/ GYM, MENYETIR MOBIL (KEGIATAN YANG SERING MENGGUNAKAN KAKI KANAN) | T33: HADIR | U33: - | V33: KEL BARU/ BAHU/ POSISI TIDUR SALAH BERKEPANJANGAN | W33: TRUE
B34: SORE | C34: {=IFNA(XLOOKUP(J34,'⚙️ Pengaturan'!$H$5:$H1508,'⚙️ Pengaturan'!$I$5:$I1508),"")} -> TIM Y | D34: SUCI | E34: 45932 | F34: =IF($E34="","",TEXT($E34,"YYYY")) -> 2025 | G34: =IF($E34="","",TEXT($E34,"MM")&TEXT($E34,"MMM")) -> 10Okt | H34: =IF($E34="","",TEXT($E34,"DDDD")) -> Kamis | I34: 16.00 | J34: WAHYU | K34: PAKET TERAPI | L34: FIKRI AKIFA PERMANA | M34: =IFNA(VLOOKUP(L34,'🙎‍♂️ Pasien'!G:V,2,FALSE),"") -> F0423083055 | N34: =IFNA(VLOOKUP(L34,'🙎‍♂️ Pasien'!G:L,3,FALSE),"") -> 21 | O34: =IFNA(VLOOKUP(L34,'🙎‍♂️ Pasien'!G:V,6,FALSE),"") -> LAKI-LAKI | P34: =IFNA(VLOOKUP(L34,'🙎‍♂️ Pasien'!G:V,12,FALSE),"") -> ISLAM | Q34: =IFNA(VLOOKUP(L34:L1508,'🙎‍♂️ Pasien'!G:V,13,FALSE),"") -> PELAJAR/MAHASISWA | R34: {=ifna(xlookup(L34,'🙎‍♂️ Pasien'!$G$5:$G1508,'🙎‍♂️ Pasien'!$T$5:$T1508),"")} -> SAKIT DAN NGERI DI BAGIAN KAKI | S34: {=ifna(xlookup(L34,'🙎‍♂️ Pasien'!$G$5:$G1508,'🙎‍♂️ Pasien'!$U$5:$U1508),"")} -> OLAHRAGA | T34: HADIR | U34: 5 | V34: EVAL | W34: TRUE
B35: SORE | C35: {=IFNA(XLOOKUP(J35,'⚙️ Pengaturan'!$H$5:$H1508,'⚙️ Pengaturan'!$I$5:$I1508),"")} -> TIM A | D35: SUCI | E35: 45932 | F35: =IF($E35="","",TEXT($E35,"YYYY")) -> 2025 | G35: =IF($E35="","",TEXT($E35,"MM")&TEXT($E35,"MMM")) -> 10Okt | H35: =IF($E35="","",TEXT($E35,"DDDD")) -> Kamis | I35: 16.00 | J35: HESTI | K35: PAKET TERAPI | L35: YOSIA GALANG PUTRA BORNEO | M35: =IFNA(VLOOKUP(L35,'🙎‍♂️ Pasien'!G:V,2,FALSE),"") -> Y0825082296 | N35: =IFNA(VLOOKUP(L35,'🙎‍♂️ Pasien'!G:L,3,FALSE),"") -> 17 | O35: =IFNA(VLOOKUP(L35,'🙎‍♂️ Pasien'!G:V,6,FALSE),"") -> LAKI-LAKI | P35: =IFNA(VLOOKUP(L35,'🙎‍♂️ Pasien'!G:V,12,FALSE),"") -> LAINNYA | Q35: =IFNA(VLOOKUP(L35:L1508,'🙎‍♂️ Pasien'!G:V,13,FALSE),"") -> PELAJAR | R35: {=ifna(xlookup(L35,'🙎‍♂️ Pasien'!$G$5:$G1508,'🙎‍♂️ Pasien'!$T$5:$T1508),"")} -> LUTUT | S35: {=ifna(xlookup(L35,'🙎‍♂️ Pasien'!$G$5:$G1508,'🙎‍♂️ Pasien'!$U$5:$U1508),"")} -> - | T35: TIDAK HADIR | U35: 5 | V35: EVAL/RESCEDULE JAM | W35: TRUE
B36: SORE | C36: {=IFNA(XLOOKUP(J36,'⚙️ Pengaturan'!$H$5:$H1508,'⚙️ Pengaturan'!$I$5:$I1508),"")} -> TIM A | D36: SUCI | E36: 45932 | F36: =IF($E36="","",TEXT($E36,"YYYY")) -> 2025 | G36: =IF($E36="","",TEXT($E36,"MM")&TEXT($E36,"MMM")) -> 10Okt | H36: =IF($E36="","",TEXT($E36,"DDDD")) -> Kamis | I36: 17.00 | J36: OKTA | K36: PAKET TERAPI | L36: ATIKA MUFLIHA | M36: =IFNA(VLOOKUP(L36,'🙎‍♂️ Pasien'!G:V,2,FALSE),"") -> A9725086020 | N36: =IFNA(VLOOKUP(L36,'🙎‍♂️ Pasien'!G:L,3,FALSE),"") -> 28 | O36: =IFNA(VLOOKUP(L36,'🙎‍♂️ Pasien'!G:V,6,FALSE),"") -> PEREMPUAN | P36: =IFNA(VLOOKUP(L36,'🙎‍♂️ Pasien'!G:V,12,FALSE),"") -> ISLAM | Q36: =IFNA(VLOOKUP(L36:L1508,'🙎‍♂️ Pasien'!G:V,13,FALSE),"") -> PNS | R36: {=ifna(xlookup(L36,'🙎‍♂️ Pasien'!$G$5:$G1508,'🙎‍♂️ Pasien'!$T$5:$T1508),"")} -> SAKIT BAGIAN PAHA DAN PANGGUL | S36: {=ifna(xlookup(L36,'🙎‍♂️ Pasien'!$G$5:$G1508,'🙎‍♂️ Pasien'!$U$5:$U1508),"")} -> VOLI DAN BEKERJA | T36: HADIR | U36: 2 | W36: TRUE
B37: SORE | C37: {=IFNA(XLOOKUP(J37,'⚙️ Pengaturan'!$H$5:$H1508,'⚙️ Pengaturan'!$I$5:$I1508),"")} -> TIM A | D37: SUCI | E37: 45932 | F37: =IF($E37="","",TEXT($E37,"YYYY")) -> 2025 | G37: =IF($E37="","",TEXT($E37,"MM")&TEXT($E37,"MMM")) -> 10Okt | H37: =IF($E37="","",TEXT($E37,"DDDD")) -> Kamis | I37: 19.00 | J37: HESTI | K37: PAKET TERAPI | L37: DEVIN PANGESTU | M37: =IFNA(VLOOKUP(L37,'🙎‍♂️ Pasien'!G:V,2,FALSE),"") -> D1025091558 | N37: =IFNA(VLOOKUP(L37,'🙎‍♂️ Pasien'!G:L,3,FALSE),"") -> 16 | O37: =IFNA(VLOOKUP(L37,'🙎‍♂️ Pasien'!G:V,6,FALSE),"") -> LAKI-LAKI | P37: =IFNA(VLOOKUP(L37,'🙎‍♂️ Pasien'!G:V,12,FALSE),"") -> PROTESTAN | Q37: =IFNA(VLOOKUP(L37:L1508,'🙎‍♂️ Pasien'!G:V,13,FALSE),"") -> MASI SEKOLAH | R37: {=ifna(xlookup(L37,'🙎‍♂️ Pasien'!$G$5:$G1508,'🙎‍♂️ Pasien'!$T$5:$T1508),"")} -> SAKIT DI BAGIAN LUTUT | S37: {=ifna(xlookup(L37,'🙎‍♂️ Pasien'!$G$5:$G1508,'🙎‍♂️ Pasien'!$U$5:$U1508),"")} -> BASKET | T37: HADIR | U37: 1 | W37: TRUE
B38: SORE | C38: {=IFNA(XLOOKUP(J38,'⚙️ Pengaturan'!$H$5:$H1508,'⚙️ Pengaturan'!$I$5:$I1508),"")} -> TIM A | D38: SUCI | E38: 45932 | F38: =IF($E38="","",TEXT($E38,"YYYY")) -> 2025 | G38: =IF($E38="","",TEXT($E38,"MM")&TEXT($E38,"MMM")) -> 10Okt | H38: =IF($E38="","",TEXT($E38,"DDDD")) -> Kamis | I38: 19.00 | J38: OKTA | K38: SESI TERAPI | L38: IRFAN APRISON | M38: =IFNA(VLOOKUP(L38,'🙎‍♂️ Pasien'!G:V,2,FALSE),"") -> I9525090 | N38: =IFNA(VLOOKUP(L38,'🙎‍♂️ Pasien'!G:L,3,FALSE),"") -> 30 | O38: =IFNA(VLOOKUP(L38,'🙎‍♂️ Pasien'!G:V,6,FALSE),"") -> LAKI-LAKI | P38: =IFNA(VLOOKUP(L38,'🙎‍♂️ Pasien'!G:V,12,FALSE),"") -> ISLAM | Q38: =IFNA(VLOOKUP(L38:L1508,'🙎‍♂️ Pasien'!G:V,13,FALSE),"") -> PNS | R38: {=ifna(xlookup(L38,'🙎‍♂️ Pasien'!$G$5:$G1508,'🙎‍♂️ Pasien'!$T$5:$T1508),"")} -> ANKLE | S38: {=ifna(xlookup(L38,'🙎‍♂️ Pasien'!$G$5:$G1508,'🙎‍♂️ Pasien'!$U$5:$U1508),"")} -> - | T38: HADIR | U38: - | W38: TRUE
B39: SORE | C39: {=IFNA(XLOOKUP(J39,'⚙️ Pengaturan'!$H$5:$H1508,'⚙️ Pengaturan'!$I$5:$I1508),"")} -> TIM A | D39: SUCI | E39: 45932 | F39: =IF($E39="","",TEXT($E39,"YYYY")) -> 2025 | G39: =IF($E39="","",TEXT($E39,"MM")&TEXT($E39,"MMM")) -> 10Okt | H39: =IF($E39="","",TEXT($E39,"DDDD")) -> Kamis | I39: 19.00 | J39: HENA | K39: TERAPI AWAL | L39: LISA MEGASARI | M39: =IFNA(VLOOKUP(L39,'🙎‍♂️ Pasien'!G:V,2,FALSE),"") -> L8625105331 | N39: =IFNA(VLOOKUP(L39,'🙎‍♂️ Pasien'!G:L,3,FALSE),"") -> 39 | O39: =IFNA(VLOOKUP(L39,'🙎‍♂️ Pasien'!G:V,6,FALSE),"") -> PEREMPUAN | P39: =IFNA(VLOOKUP(L39,'🙎‍♂️ Pasien'!G:V,12,FALSE),"") -> ISLAM | Q39: =IFNA(VLOOKUP(L39:L1508,'🙎‍♂️ Pasien'!G:V,13,FALSE),"") -> SWASTA | R39: {=ifna(xlookup(L39,'🙎‍♂️ Pasien'!$G$5:$G1508,'🙎‍♂️ Pasien'!$T$5:$T1508),"")} -> BENUA MELAYU LAUT | S39: {=ifna(xlookup(L39,'🙎‍♂️ Pasien'!$G$5:$G1508,'🙎‍♂️ Pasien'!$U$5:$U1508),"")} -> BERJALAN | T39: HADIR | U39: - | V39: KEL KAKI | W39: TRUE
B40: SORE | C40: {=IFNA(XLOOKUP(J40,'⚙️ Pengaturan'!$H$5:$H1508,'⚙️ Pengaturan'!$I$5:$I1508),"")} -> TIM A | D40: SUCI | E40: 45932 | F40: =IF($E40="","",TEXT($E40,"YYYY")) -> 2025 | G40: =IF($E40="","",TEXT($E40,"MM")&TEXT($E40,"MMM")) -> 10Okt | H40: =IF($E40="","",TEXT($E40,"DDDD")) -> Kamis | I40: 19.00 | J40: HENA | K40: PAKET TERAPI | L40: RYUDINATA WILLIAM | M40: =IFNA(VLOOKUP(L40,'🙎‍♂️ Pasien'!G:V,2,FALSE),"") -> R1225091811 | N40: =IFNA(VLOOKUP(L40,'🙎‍♂️ Pasien'!G:L,3,FALSE),"") -> 13 | O40: =IFNA(VLOOKUP(L40,'🙎‍♂️ Pasien'!G:V,6,FALSE),"") -> LAKI-LAKI | P40: =IFNA(VLOOKUP(L40,'🙎‍♂️ Pasien'!G:V,12,FALSE),"") -> KATOLIK | Q40: =IFNA(VLOOKUP(L40:L1508,'🙎‍♂️ Pasien'!G:V,13,FALSE),"") -> SISWA | R40: {=ifna(xlookup(L40,'🙎‍♂️ Pasien'!$G$5:$G1508,'🙎‍♂️ Pasien'!$T$5:$T1508),"")} -> BUNGKUK | S40: {=ifna(xlookup(L40,'🙎‍♂️ Pasien'!$G$5:$G1508,'🙎‍♂️ Pasien'!$U$5:$U1508),"")} -> SEKOLAH | T40: TIDAK HADIR | U40: 1 | V40: PINDAH JAM 14.00 | W40: TRUE
B41: SORE | C41: {=IFNA(XLOOKUP(J41,'⚙️ Pengaturan'!$H$5:$H1508,'⚙️ Pengaturan'!$I$5:$I1508),"")} -> TIM A | D41: SUCI | E41: 45932 | F41: =IF($E41="","",TEXT($E41,"YYYY")) -> 2025 | G41: =IF($E41="","",TEXT($E41,"MM")&TEXT($E41,"MMM")) -> 10Okt | H41: =IF($E41="","",TEXT($E41,"DDDD")) -> Kamis | I41: 20.00 | J41: HESTI | K41: PAKET TERAPI | L41: MASDIARTI | M41: =IFNA(VLOOKUP(L41,'🙎‍♂️ Pasien'!G:V,2,FALSE),"") -> M7525052841 | N41: =IFNA(VLOOKUP(L41,'🙎‍♂️ Pasien'!G:L,3,FALSE),"") -> 50 | O41: =IFNA(VLOOKUP(L41,'🙎‍♂️ Pasien'!G:V,6,FALSE),"") -> PEREMPUAN | P41: =IFNA(VLOOKUP(L41,'🙎‍♂️ Pasien'!G:V,12,FALSE),"") -> ISLAM | Q41: =IFNA(VLOOKUP(L41:L1508,'🙎‍♂️ Pasien'!G:V,13,FALSE),"") -> IBU RUMAH TANGGA | R41: {=ifna(xlookup(L41,'🙎‍♂️ Pasien'!$G$5:$G1508,'🙎‍♂️ Pasien'!$T$5:$T1508),"")} -> RHUMBOID PAIN, CARPAL TUNNEL SYNDROME, PIRIFORMIS SYNDROME | S41: {=ifna(xlookup(L41,'🙎‍♂️ Pasien'!$G$5:$G1508,'🙎‍♂️ Pasien'!$U$5:$U1508),"")} -> AKTIVITAS RUMAH TANGGA (CUCI DAN SETRIKA PAKAIAN) | T41: HADIR | U41: 5 | V41: EVAL | W41: TRUE
B42: SORE | C42: {=IFNA(XLOOKUP(J42,'⚙️ Pengaturan'!$H$5:$H1508,'⚙️ Pengaturan'!$I$5:$I1508),"")} -> MANAJEMEN | D42: LAINNYA | E42: 45933 | F42: =IF($E42="","",TEXT($E42,"YYYY")) -> 2025 | G42: =IF($E42="","",TEXT($E42,"MM")&TEXT($E42,"MMM")) -> 10Okt | H42: =IF($E42="","",TEXT($E42,"DDDD")) -> Jumat | I42: 15.00 | J42: DANI | K42: PAKET/SESI | L42: HARRY FURQAN | M42: =IFNA(VLOOKUP(L42,'🙎‍♂️ Pasien'!G:V,2,FALSE),"") -> H9025092496 | N42: =IFNA(VLOOKUP(L42,'🙎‍♂️ Pasien'!G:L,3,FALSE),"") -> 35 | O42: =IFNA(VLOOKUP(L42,'🙎‍♂️ Pasien'!G:V,6,FALSE),"") -> LAKI-LAKI | P42: =IFNA(VLOOKUP(L42,'🙎‍♂️ Pasien'!G:V,12,FALSE),"") -> ISLAM | Q42: =IFNA(VLOOKUP(L42:L1508,'🙎‍♂️ Pasien'!G:V,13,FALSE),"") -> SWASTA | R42: {=ifna(xlookup(L42,'🙎‍♂️ Pasien'!$G$5:$G1508,'🙎‍♂️ Pasien'!$T$5:$T1508),"")} -> KAKI KIRI SAKIT | S42: {=ifna(xlookup(L42,'🙎‍♂️ Pasien'!$G$5:$G1508,'🙎‍♂️ Pasien'!$U$5:$U1508),"")} -> LATIHAN LATI | T42: TIDAK HADIR | U42: - | V42: DEMAM | W42: TRUE | X42: -
B43: SORE | C43: {=IFNA(XLOOKUP(J43,'⚙️ Pengaturan'!$H$5:$H1508,'⚙️ Pengaturan'!$I$5:$I1508),"")} -> TIM Y | D43: LAINNYA | E43: 45933 | F43: =IF($E43="","",TEXT($E43,"YYYY")) -> 2025 | G43: =IF($E43="","",TEXT($E43,"MM")&TEXT($E43,"MMM")) -> 10Okt | H43: =IF($E43="","",TEXT($E43,"DDDD")) -> Jumat | I43: 15.00 | J43: WAHYU | K43: PAKET TERAPI | L43: YUBANADI | M43: =IFNA(VLOOKUP(L43,'🙎‍♂️ Pasien'!G:V,2,FALSE),"") -> Y5125088477 | N43: =IFNA(VLOOKUP(L43,'🙎‍♂️ Pasien'!G:L,3,FALSE),"") -> 75 | O43: =IFNA(VLOOKUP(L43,'🙎‍♂️ Pasien'!G:V,6,FALSE),"") -> LAKI-LAKI | P43: =IFNA(VLOOKUP(L43,'🙎‍♂️ Pasien'!G:V,12,FALSE),"") -> ISLAM | Q43: =IFNA(VLOOKUP(L43:L1508,'🙎‍♂️ Pasien'!G:V,13,FALSE),"") -> PENSIUNAN PLN | R43: {=ifna(xlookup(L43,'🙎‍♂️ Pasien'!$G$5:$G1508,'🙎‍♂️ Pasien'!$T$5:$T1508),"")} -> STROKE SEBELAH KANAN | S43: {=ifna(xlookup(L43,'🙎‍♂️ Pasien'!$G$5:$G1508,'🙎‍♂️ Pasien'!$U$5:$U1508),"")} -> TIDAK ADA | T43: HADIR | U43: 6 | W43: TRUE | X43: PASIEN MINTA SELASA SIANG
B44: SORE | C44: {=IFNA(XLOOKUP(J44,'⚙️ Pengaturan'!$H$5:$H1508,'⚙️ Pengaturan'!$I$5:$I1508),"")} -> TIM Y | D44: LAINNYA | E44: 45933 | F44: =IF($E44="","",TEXT($E44,"YYYY")) -> 2025 | G44: =IF($E44="","",TEXT($E44,"MM")&TEXT($E44,"MMM")) -> 10Okt | H44: =IF($E44="","",TEXT($E44,"DDDD")) -> Jumat | I44: 16.00 | J44: WAHYU | K44: PAKET TERAPI | L44: ALBYAN RAFIF MAHESWARA | M44: =IFNA(VLOOKUP(L44,'🙎‍♂️ Pasien'!G:V,2,FALSE),"") -> A0925094650 | N44: =IFNA(VLOOKUP(L44,'🙎‍♂️ Pasien'!G:L,3,FALSE),"") -> 17 | O44: =IFNA(VLOOKUP(L44,'🙎‍♂️ Pasien'!G:V,6,FALSE),"") -> LAKI-LAKI | P44: =IFNA(VLOOKUP(L44,'🙎‍♂️ Pasien'!G:V,12,FALSE),"") -> ISLAM | Q44: =IFNA(VLOOKUP(L44:L1508,'🙎‍♂️ Pasien'!G:V,13,FALSE),"") -> PELAJAR | R44: {=ifna(xlookup(L44,'🙎‍♂️ Pasien'!$G$5:$G1508,'🙎‍♂️ Pasien'!$T$5:$T1508),"")} -> LUTUT | S44: {=ifna(xlookup(L44,'🙎‍♂️ Pasien'!$G$5:$G1508,'🙎‍♂️ Pasien'!$U$5:$U1508),"")} -> FUTSAL | T44: HADIR | U44: 6 | W44: TRUE | X44: NANTI DI WA COCOKKAN JADWAL SEKOLAH
B45: SORE | C45: {=IFNA(XLOOKUP(J45,'⚙️ Pengaturan'!$H$5:$H1508,'⚙️ Pengaturan'!$I$5:$I1508),"")} -> TIM Y | D45: LAINNYA | E45: 45933 | F45: =IF($E45="","",TEXT($E45,"YYYY")) -> 2025 | G45: =IF($E45="","",TEXT($E45,"MM")&TEXT($E45,"MMM")) -> 10Okt | H45: =IF($E45="","",TEXT($E45,"DDDD")) -> Jumat | I45: 19.00 | J45: WAHYU | K45: TERAPI AWAL | L45: RAHMAD PUNGKI WALUYO | M45: =IFNA(VLOOKUP(L45,'🙎‍♂️ Pasien'!G:V,2,FALSE),"") -> R7925105884 | N45: =IFNA(VLOOKUP(L45,'🙎‍♂️ Pasien'!G:L,3,FALSE),"") -> 46 | O45: =IFNA(VLOOKUP(L45,'🙎‍♂️ Pasien'!G:V,6,FALSE),"") -> LAKI-LAKI | P45: =IFNA(VLOOKUP(L45,'🙎‍♂️ Pasien'!G:V,12,FALSE),"") -> ISLAM | Q45: =IFNA(VLOOKUP(L45:L1508,'🙎‍♂️ Pasien'!G:V,13,FALSE),"") -> GURU | R45: {=ifna(xlookup(L45,'🙎‍♂️ Pasien'!$G$5:$G1508,'🙎‍♂️ Pasien'!$T$5:$T1508),"")} -> CIDERA OTOT BAGIAN LUTUT | S45: {=ifna(xlookup(L45,'🙎‍♂️ Pasien'!$G$5:$G1508,'🙎‍♂️ Pasien'!$U$5:$U1508),"")} -> SEPAKBOLA MINI SOCCER | T45: HADIR | U45: - | V45: PEMBAYARAN TUNAI | W45: TRUE | X45: DISARANKAN SENIN/SELASA
B46: SORE | C46: {=IFNA(XLOOKUP(J46,'⚙️ Pengaturan'!$H$5:$H1508,'⚙️ Pengaturan'!$I$5:$I1508),"")} -> TIM Y | D46: LAINNYA | E46: 45933 | F46: =IF($E46="","",TEXT($E46,"YYYY")) -> 2025 | G46: =IF($E46="","",TEXT($E46,"MM")&TEXT($E46,"MMM")) -> 10Okt | H46: =IF($E46="","",TEXT($E46,"DDDD")) -> Jumat | I46: 20.00 | J46: WAHYU | K46: TERAPI AWAL | L46: LENI DIANTAMI | M46: =IFNA(VLOOKUP(L46,'🙎‍♂️ Pasien'!G:V,2,FALSE),"") -> L2525104585 | N46: =IFNA(VLOOKUP(L46,'🙎‍♂️ Pasien'!G:L,3,FALSE),"") -> 0 | O46: =IFNA(VLOOKUP(L46,'🙎‍♂️ Pasien'!G:V,6,FALSE),"") -> PEREMPUAN | P46: =IFNA(VLOOKUP(L46,'🙎‍♂️ Pasien'!G:V,12,FALSE),"") -> ISLAM | Q46: =IFNA(VLOOKUP(L46:L1508,'🙎‍♂️ Pasien'!G:V,13,FALSE),"") -> ANGGOTA DPRD KOTA PONTIANAK | R46: {=ifna(xlookup(L46,'🙎‍♂️ Pasien'!$G$5:$G1508,'🙎‍♂️ Pasien'!$T$5:$T1508),"")} -> CEDERA BAHU | S46: {=ifna(xlookup(L46,'🙎‍♂️ Pasien'!$G$5:$G1508,'🙎‍♂️ Pasien'!$U$5:$U1508),"")} -> GYM | T46: HADIR | U46: - | V46: PEMBAYARAN TRF | W46: TRUE | X46: DISARANKAN MINGGU/SENIN. RENCANA PAKET
B47: PAGI | C47: {=IFNA(XLOOKUP(J47,'⚙️ Pengaturan'!$H$5:$H1508,'⚙️ Pengaturan'!$I$5:$I1508),"")} -> TIM Y | D47: SUCI | E47: 45934 | F47: =IF($E47="","",TEXT($E47,"YYYY")) -> 2025 | G47: =IF($E47="","",TEXT($E47,"MM")&TEXT($E47,"MMM")) -> 10Okt | H47: =IF($E47="","",TEXT($E47,"DDDD")) -> Sabtu | I47: 09.00 | J47: ORY | K47: PAKET TERAPI | L47: A. SYUKUR H. JAFRI | M47: =IFNA(VLOOKUP(L47,'🙎‍♂️ Pasien'!G:V,2,FALSE),"") -> A6125094370 | N47: =IFNA(VLOOKUP(L47,'🙎‍♂️ Pasien'!G:L,3,FALSE),"") -> 64 | O47: =IFNA(VLOOKUP(L47,'🙎‍♂️ Pasien'!G:V,6,FALSE),"") -> LAKI-LAKI | P47: =IFNA(VLOOKUP(L47,'🙎‍♂️ Pasien'!G:V,12,FALSE),"") -> ISLAM | Q47: =IFNA(VLOOKUP(L47:L1508,'🙎‍♂️ Pasien'!G:V,13,FALSE),"") -> WIRASWASTA | R47: {=ifna(xlookup(L47,'🙎‍♂️ Pasien'!$G$5:$G1508,'🙎‍♂️ Pasien'!$T$5:$T1508),"")} -> NYERI DI SENDI BAHU, SAKIT KETIKA DI ANGKAT AGAK TINGGI | S47: {=ifna(xlookup(L47,'🙎‍♂️ Pasien'!$G$5:$G1508,'🙎‍♂️ Pasien'!$U$5:$U1508),"")} -> TERKADANG ANGKAT2 BARANG, TP TIDAK SETIAP HARI. ADA RIWAYAT JATUH | T47: HADIR | U47: 4 | W47: TRUE
B48: PAGI | C48: {=IFNA(XLOOKUP(J48,'⚙️ Pengaturan'!$H$5:$H1508,'⚙️ Pengaturan'!$I$5:$I1508),"")} -> TIM Y | D48: SUCI | E48: 45934 | F48: =IF($E48="","",TEXT($E48,"YYYY")) -> 2025 | G48: =IF($E48="","",TEXT($E48,"MM")&TEXT($E48,"MMM")) -> 10Okt | H48: =IF($E48="","",TEXT($E48,"DDDD")) -> Sabtu | I48: 09.00 | J48: PRITY | K48: PAKET TERAPI | L48: PUJI MULYANI | M48: =IFNA(VLOOKUP(L48,'🙎‍♂️ Pasien'!G:V,2,FALSE),"") -> P7525096189 | N48: =IFNA(VLOOKUP(L48,'🙎‍♂️ Pasien'!G:L,3,FALSE),"") -> 51 | O48: =IFNA(VLOOKUP(L48,'🙎‍♂️ Pasien'!G:V,6,FALSE),"") -> PEREMPUAN | P48: =IFNA(VLOOKUP(L48,'🙎‍♂️ Pasien'!G:V,12,FALSE),"") -> ISLAM | Q48: =IFNA(VLOOKUP(L48:L1508,'🙎‍♂️ Pasien'!G:V,13,FALSE),"") -> PNS | R48: {=ifna(xlookup(L48,'🙎‍♂️ Pasien'!$G$5:$G1508,'🙎‍♂️ Pasien'!$T$5:$T1508),"")} -> SAKIT PADA KAKI | S48: {=ifna(xlookup(L48,'🙎‍♂️ Pasien'!$G$5:$G1508,'🙎‍♂️ Pasien'!$U$5:$U1508),"")} -> OLAH RAGA (JALAN KAKI) | T48: TIDAK HADIR | U48: 5 | V48: EVAL/ FISIONYA SAKIT | W48: TRUE
B49: PAGI | C49: {=IFNA(XLOOKUP(J49,'⚙️ Pengaturan'!$H$5:$H1508,'⚙️ Pengaturan'!$I$5:$I1508),"")} -> TIM Y | D49: SUCI | E49: 45934 | F49: =IF($E49="","",TEXT($E49,"YYYY")) -> 2025 | G49: =IF($E49="","",TEXT($E49,"MM")&TEXT($E49,"MMM")) -> 10Okt | H49: =IF($E49="","",TEXT($E49,"DDDD")) -> Sabtu | I49: 10.00 | J49: DESTY | K49: PAKET TERAPI | L49: SEKAR KINANTI HERPRADANTI | M49: =IFNA(VLOOKUP(L49,'🙎‍♂️ Pasien'!G:V,2,FALSE),"") -> S9825058991 | N49: =IFNA(VLOOKUP(L49,'🙎‍♂️ Pasien'!G:L,3,FALSE),"") -> 27 | O49: =IFNA(VLOOKUP(L49,'🙎‍♂️ Pasien'!G:V,6,FALSE),"") -> PEREMPUAN | P49: =IFNA(VLOOKUP(L49,'🙎‍♂️ Pasien'!G:V,12,FALSE),"") -> ISLAM | Q49: =IFNA(VLOOKUP(L49:L1508,'🙎‍♂️ Pasien'!G:V,13,FALSE),"") -> SWASTA | R49: {=ifna(xlookup(L49,'🙎‍♂️ Pasien'!$G$5:$G1508,'🙎‍♂️ Pasien'!$T$5:$T1508),"")} -> HNP LUMBAL/SARAF KEJEPIT | S49: {=ifna(xlookup(L49,'🙎‍♂️ Pasien'!$G$5:$G1508,'🙎‍♂️ Pasien'!$U$5:$U1508),"")} -> BEKERJA KANTORAN | T49: HADIR | U49: 10 | V49: EVAL | W49: TRUE
B50: PAGI | C50: {=IFNA(XLOOKUP(J50,'⚙️ Pengaturan'!$H$5:$H1508,'⚙️ Pengaturan'!$I$5:$I1508),"")} -> TIM Y | D50: SUCI | E50: 45934 | F50: =IF($E50="","",TEXT($E50,"YYYY")) -> 2025 | G50: =IF($E50="","",TEXT($E50,"MM")&TEXT($E50,"MMM")) -> 10Okt | H50: =IF($E50="","",TEXT($E50,"DDDD")) -> Sabtu | I50: 10.00 | J50: PRITY | K50: PAKET TERAPI | L50: YUNI ISHAFIZA | M50: =IFNA(VLOOKUP(L50,'🙎‍♂️ Pasien'!G:V,2,FALSE),"") -> Y6625092191 | N50: =IFNA(VLOOKUP(L50,'🙎‍♂️ Pasien'!G:L,3,FALSE),"") -> 59 | O50: =IFNA(VLOOKUP(L50,'🙎‍♂️ Pasien'!G:V,6,FALSE),"") -> PEREMPUAN | P50: =IFNA(VLOOKUP(L50,'🙎‍♂️ Pasien'!G:V,12,FALSE),"") -> ISLAM | Q50: =IFNA(VLOOKUP(L50:L1508,'🙎‍♂️ Pasien'!G:V,13,FALSE),"") -> PENSIUNAN PNS | R50: {=ifna(xlookup(L50,'🙎‍♂️ Pasien'!$G$5:$G1508,'🙎‍♂️ Pasien'!$T$5:$T1508),"")} -> KAKI KIRI SAKIT, NYER JUGA NGILU KARENA HABIS TABRAKAN | S50: {=ifna(xlookup(L50,'🙎‍♂️ Pasien'!$G$5:$G1508,'🙎‍♂️ Pasien'!$U$5:$U1508),"")} -> HARI JUMAT KEMARIN HABIS TABRAKAN | T50: TIDAK HADIR | U50: 2 | V50: PINDAH MALAM/FISIONYA SAKIT | W50: TRUE
B51: PAGI | C51: {=IFNA(XLOOKUP(J51,'⚙️ Pengaturan'!$H$5:$H1508,'⚙️ Pengaturan'!$I$5:$I1508),"")} -> TIM Y | D51: SUCI | E51: 45934 | F51: =IF($E51="","",TEXT($E51,"YYYY")) -> 2025 | G51: =IF($E51="","",TEXT($E51,"MM")&TEXT($E51,"MMM")) -> 10Okt | H51: =IF($E51="","",TEXT($E51,"DDDD")) -> Sabtu | I51: 11.00 | J51: DESTY | K51: PAKET TERAPI | L51: HENG KENG SENG | M51: =IFNA(VLOOKUP(L51,'🙎‍♂️ Pasien'!G:V,2,FALSE),"") -> H5325098176 | N51: =IFNA(VLOOKUP(L51,'🙎‍♂️ Pasien'!G:L,3,FALSE),"") -> 73 | O51: =IFNA(VLOOKUP(L51,'🙎‍♂️ Pasien'!G:V,6,FALSE),"") -> LAKI-LAKI | P51: =IFNA(VLOOKUP(L51,'🙎‍♂️ Pasien'!G:V,12,FALSE),"") -> BUDDHA | Q51: =IFNA(VLOOKUP(L51:L1508,'🙎‍♂️ Pasien'!G:V,13,FALSE),"") -> PENSIUN | R51: {=ifna(xlookup(L51,'🙎‍♂️ Pasien'!$G$5:$G1508,'🙎‍♂️ Pasien'!$T$5:$T1508),"")} -> KAKI GAK BISA JONGKOK | S51: {=ifna(xlookup(L51,'🙎‍♂️ Pasien'!$G$5:$G1508,'🙎‍♂️ Pasien'!$U$5:$U1508),"")} -> —— | T51: HADIR | U51: 2 | W51: TRUE
B52: PAGI | C52: {=IFNA(XLOOKUP(J52,'⚙️ Pengaturan'!$H$5:$H1508,'⚙️ Pengaturan'!$I$5:$I1508),"")} -> TIM Y | D52: SUCI | E52: 45934 | F52: =IF($E52="","",TEXT($E52,"YYYY")) -> 2025 | G52: =IF($E52="","",TEXT($E52,"MM")&TEXT($E52,"MMM")) -> 10Okt | H52: =IF($E52="","",TEXT($E52,"DDDD")) -> Sabtu | I52: 11.00 | J52: ORY | K52: TERAPI AWAL | L52: OZZY GUARDIOLA FITTIFALDY | M52: =IFNA(VLOOKUP(L52,'🙎‍♂️ Pasien'!G:V,2,FALSE),"") -> O9424013019 | N52: =IFNA(VLOOKUP(L52,'🙎‍♂️ Pasien'!G:L,3,FALSE),"") -> 31 | O52: =IFNA(VLOOKUP(L52,'🙎‍♂️ Pasien'!G:V,6,FALSE),"") -> LAKI-LAKI | P52: =IFNA(VLOOKUP(L52,'🙎‍♂️ Pasien'!G:V,12,FALSE),"") -> ISLAM | Q52: =IFNA(VLOOKUP(L52:L1508,'🙎‍♂️ Pasien'!G:V,13,FALSE),"") -> BUMD | R52: {=ifna(xlookup(L52,'🙎‍♂️ Pasien'!$G$5:$G1508,'🙎‍♂️ Pasien'!$T$5:$T1508),"")} -> Ketarik sehabis long run | S52: {=ifna(xlookup(L52,'🙎‍♂️ Pasien'!$G$5:$G1508,'🙎‍♂️ Pasien'!$U$5:$U1508),"")} -> Lari | T52: HADIR | U52: - | W52: TRUE
B53: PAGI | C53: {=IFNA(XLOOKUP(J53,'⚙️ Pengaturan'!$H$5:$H1508,'⚙️ Pengaturan'!$I$5:$I1508),"")} -> TIM Y | D53: SUCI | E53: 45934 | F53: =IF($E53="","",TEXT($E53,"YYYY")) -> 2025 | G53: =IF($E53="","",TEXT($E53,"MM")&TEXT($E53,"MMM")) -> 10Okt | H53: =IF($E53="","",TEXT($E53,"DDDD")) -> Sabtu | I53: 13.00 | J53: DESTY | K53: PAKET TERAPI | L53: AHMAD DANY NOVALDI | M53: =IFNA(VLOOKUP(L53,'🙎‍♂️ Pasien'!G:V,2,FALSE),"") -> A0625085349 | N53: =IFNA(VLOOKUP(L53,'🙎‍♂️ Pasien'!G:L,3,FALSE),"") -> 19 | O53: =IFNA(VLOOKUP(L53,'🙎‍♂️ Pasien'!G:V,6,FALSE),"") -> LAKI-LAKI | P53: =IFNA(VLOOKUP(L53,'🙎‍♂️ Pasien'!G:V,12,FALSE),"") -> ISLAM | Q53: =IFNA(VLOOKUP(L53:L1508,'🙎‍♂️ Pasien'!G:V,13,FALSE),"") -> PELAJAR/MAHASISWA | R53: {=ifna(xlookup(L53,'🙎‍♂️ Pasien'!$G$5:$G1508,'🙎‍♂️ Pasien'!$T$5:$T1508),"")} -> BAHU | S53: {=ifna(xlookup(L53,'🙎‍♂️ Pasien'!$G$5:$G1508,'🙎‍♂️ Pasien'!$U$5:$U1508),"")} -> SILAT | T53: HADIR | U53: 5 | V53: EVAL | W53: TRUE
B54: PAGI | C54: {=IFNA(XLOOKUP(J54,'⚙️ Pengaturan'!$H$5:$H1508,'⚙️ Pengaturan'!$I$5:$I1508),"")} -> TIM Y | D54: SUCI | E54: 45934 | F54: =IF($E54="","",TEXT($E54,"YYYY")) -> 2025 | G54: =IF($E54="","",TEXT($E54,"MM")&TEXT($E54,"MMM")) -> 10Okt | H54: =IF($E54="","",TEXT($E54,"DDDD")) -> Sabtu | I54: 13.00 | J54: PRITY | K54: PAKET TERAPI | L54: SRI ESRI | M54: =IFNA(VLOOKUP(L54,'🙎‍♂️ Pasien'!G:V,2,FALSE),"") -> S6225086797 | N54: =IFNA(VLOOKUP(L54,'🙎‍♂️ Pasien'!G:L,3,FALSE),"") -> 63 | O54: =IFNA(VLOOKUP(L54,'🙎‍♂️ Pasien'!G:V,6,FALSE),"") -> PEREMPUAN | P54: =IFNA(VLOOKUP(L54,'🙎‍♂️ Pasien'!G:V,12,FALSE),"") -> ISLAM | Q54: =IFNA(VLOOKUP(L54:L1508,'🙎‍♂️ Pasien'!G:V,13,FALSE),"") -> - | R54: {=ifna(xlookup(L54,'🙎‍♂️ Pasien'!$G$5:$G1508,'🙎‍♂️ Pasien'!$T$5:$T1508),"")} -> TANGAN KANAN BAGIAN ATAS, SAKIT SAAT DIGERAKKAN | S54: {=ifna(xlookup(L54,'🙎‍♂️ Pasien'!$G$5:$G1508,'🙎‍♂️ Pasien'!$U$5:$U1508),"")} -> PEKERJAAN RUMAH TANGGA | T54: TIDAK HADIR | U54: 5 | V54: EVAL / PINDA RABU FISIONYA SAKIT | W54: TRUE
B55: PAGI | C55: {=IFNA(XLOOKUP(J55,'⚙️ Pengaturan'!$H$5:$H1508,'⚙️ Pengaturan'!$I$5:$I1508),"")} -> TIM Y | D55: SUCI | E55: 45934 | F55: =IF($E55="","",TEXT($E55,"YYYY")) -> 2025 | G55: =IF($E55="","",TEXT($E55,"MM")&TEXT($E55,"MMM")) -> 10Okt | H55: =IF($E55="","",TEXT($E55,"DDDD")) -> Sabtu | I55: 14.00 | J55: ORY | K55: SESI TERAPI | L55: HAMDAN IDRIS | M55: =IFNA(VLOOKUP(L55,'🙎‍♂️ Pasien'!G:V,2,FALSE),"") -> H5325012017 | N55: =IFNA(VLOOKUP(L55,'🙎‍♂️ Pasien'!G:L,3,FALSE),"") -> 72 | O55: =IFNA(VLOOKUP(L55,'🙎‍♂️ Pasien'!G:V,6,FALSE),"") -> LAKI-LAKI | P55: =IFNA(VLOOKUP(L55,'🙎‍♂️ Pasien'!G:V,12,FALSE),"") -> ISLAM | Q55: =IFNA(VLOOKUP(L55:L1508,'🙎‍♂️ Pasien'!G:V,13,FALSE),"") -> PENSIUN | R55: {=ifna(xlookup(L55,'🙎‍♂️ Pasien'!$G$5:$G1508,'🙎‍♂️ Pasien'!$T$5:$T1508),"")} -> Kaki terasa nyeri jika dibawa berdiri lama atau berjalan jauh | S55: {=ifna(xlookup(L55,'🙎‍♂️ Pasien'!$G$5:$G1508,'🙎‍♂️ Pasien'!$U$5:$U1508),"")} -> Tidak ada | T55: HADIR | U55: - | W55: TRUE
B56: PAGI | C56: {=IFNA(XLOOKUP(J56,'⚙️ Pengaturan'!$H$5:$H1508,'⚙️ Pengaturan'!$I$5:$I1508),"")} -> TIM Y | D56: SUCI | E56: 45934 | F56: =IF($E56="","",TEXT($E56,"YYYY")) -> 2025 | G56: =IF($E56="","",TEXT($E56,"MM")&TEXT($E56,"MMM")) -> 10Okt | H56: =IF($E56="","",TEXT($E56,"DDDD")) -> Sabtu | I56: 14.00 | J56: DESTY | K56: PAKET TERAPI | L56: HO HIAN KI | M56: =IFNA(VLOOKUP(L56,'🙎‍♂️ Pasien'!G:V,2,FALSE),"") -> H5024091565 | N56: =IFNA(VLOOKUP(L56,'🙎‍♂️ Pasien'!G:L,3,FALSE),"") -> 75 | O56: =IFNA(VLOOKUP(L56,'🙎‍♂️ Pasien'!G:V,6,FALSE),"") -> PEREMPUAN | P56: =IFNA(VLOOKUP(L56,'🙎‍♂️ Pasien'!G:V,12,FALSE),"") -> BUDDHA | Q56: =IFNA(VLOOKUP(L56:L1508,'🙎‍♂️ Pasien'!G:V,13,FALSE),"") -> RUMAH TANGGA | R56: {=ifna(xlookup(L56,'🙎‍♂️ Pasien'!$G$5:$G1508,'🙎‍♂️ Pasien'!$T$5:$T1508),"")} -> NYERI/KESEMUTAN DI PAHA KIRI | S56: {=ifna(xlookup(L56,'🙎‍♂️ Pasien'!$G$5:$G1508,'🙎‍♂️ Pasien'!$U$5:$U1508),"")} -> MENANAM BUNGA | T56: HADIR | U56: 7 | W56: TRUE
B57: PAGI | C57: {=IFNA(XLOOKUP(J57,'⚙️ Pengaturan'!$H$5:$H1508,'⚙️ Pengaturan'!$I$5:$I1508),"")} -> TIM Y | D57: SUCI | E57: 45934 | F57: =IF($E57="","",TEXT($E57,"YYYY")) -> 2025 | G57: =IF($E57="","",TEXT($E57,"MM")&TEXT($E57,"MMM")) -> 10Okt | H57: =IF($E57="","",TEXT($E57,"DDDD")) -> Sabtu | I57: 14.00 | J57: PRITY | K57: PAKET TERAPI | L57: SOFHIA LEKA | M57: =IFNA(VLOOKUP(L57,'🙎‍♂️ Pasien'!G:V,2,FALSE),"") -> S9025083777 | N57: =IFNA(VLOOKUP(L57,'🙎‍♂️ Pasien'!G:L,3,FALSE),"") -> 35 | O57: =IFNA(VLOOKUP(L57,'🙎‍♂️ Pasien'!G:V,6,FALSE),"") -> PEREMPUAN | P57: =IFNA(VLOOKUP(L57,'🙎‍♂️ Pasien'!G:V,12,FALSE),"") -> PROTESTAN | Q57: =IFNA(VLOOKUP(L57:L1508,'🙎‍♂️ Pasien'!G:V,13,FALSE),"") -> KARYAWAN SWASTA | R57: {=ifna(xlookup(L57,'🙎‍♂️ Pasien'!$G$5:$G1508,'🙎‍♂️ Pasien'!$T$5:$T1508),"")} -> SAKIT SIKU | S57: {=ifna(xlookup(L57,'🙎‍♂️ Pasien'!$G$5:$G1508,'🙎‍♂️ Pasien'!$U$5:$U1508),"")} -> TENNIS | T57: TIDAK HADIR | U57: 5 | V57: EVAL/ JADWALKAN ULANG | W57: TRUE
B58: SORE | C58: {=IFNA(XLOOKUP(J58,'⚙️ Pengaturan'!$H$5:$H1508,'⚙️ Pengaturan'!$I$5:$I1508),"")} -> TIM A | D58: NOPI | E58: 45934 | F58: =IF($E58="","",TEXT($E58,"YYYY")) -> 2025 | G58: =IF($E58="","",TEXT($E58,"MM")&TEXT($E58,"MMM")) -> 10Okt | H58: =IF($E58="","",TEXT($E58,"DDDD")) -> Sabtu | I58: 15.00 | J58: HESTI | K58: PAKET TERAPI | L58: AISHA NAJWA AQILA | M58: =IFNA(VLOOKUP(L58,'🙎‍♂️ Pasien'!G:V,2,FALSE),"") -> A0825098780 | N58: =IFNA(VLOOKUP(L58,'🙎‍♂️ Pasien'!G:L,3,FALSE),"") -> 18 | O58: =IFNA(VLOOKUP(L58,'🙎‍♂️ Pasien'!G:V,6,FALSE),"") -> PEREMPUAN | P58: =IFNA(VLOOKUP(L58,'🙎‍♂️ Pasien'!G:V,12,FALSE),"") -> ISLAM | Q58: =IFNA(VLOOKUP(L58:L1508,'🙎‍♂️ Pasien'!G:V,13,FALSE),"") -> PELAJAR | R58: {=ifna(xlookup(L58,'🙎‍♂️ Pasien'!$G$5:$G1508,'🙎‍♂️ Pasien'!$T$5:$T1508),"")} -> SAKIT DI LUTUT | S58: {=ifna(xlookup(L58,'🙎‍♂️ Pasien'!$G$5:$G1508,'🙎‍♂️ Pasien'!$U$5:$U1508),"")} -> MAIN BASKET | T58: HADIR | U58: 3 | W58: TRUE
B59: SORE | C59: {=IFNA(XLOOKUP(J59,'⚙️ Pengaturan'!$H$5:$H1508,'⚙️ Pengaturan'!$I$5:$I1508),"")} -> TIM A | D59: NOPI | E59: 45934 | F59: =IF($E59="","",TEXT($E59,"YYYY")) -> 2025 | G59: =IF($E59="","",TEXT($E59,"MM")&TEXT($E59,"MMM")) -> 10Okt | H59: =IF($E59="","",TEXT($E59,"DDDD")) -> Sabtu | I59: 15.00 | J59: OKTA | K59: SESI TERAPI | L59: FATI ARIFAH | M59: =IFNA(VLOOKUP(L59,'🙎‍♂️ Pasien'!G:V,2,FALSE),"") -> F1025103034 | N59: =IFNA(VLOOKUP(L59,'🙎‍♂️ Pasien'!G:L,3,FALSE),"") -> 16 | O59: =IFNA(VLOOKUP(L59,'🙎‍♂️ Pasien'!G:V,6,FALSE),"") -> PEREMPUAN | P59: =IFNA(VLOOKUP(L59,'🙎‍♂️ Pasien'!G:V,12,FALSE),"") -> ISLAM | Q59: =IFNA(VLOOKUP(L59:L1508,'🙎‍♂️ Pasien'!G:V,13,FALSE),"") -> MASIH SEKOLAH | R59: {=ifna(xlookup(L59,'🙎‍♂️ Pasien'!$G$5:$G1508,'🙎‍♂️ Pasien'!$T$5:$T1508),"")} -> PADA SAAT JALAN DEKAT MATA KAKI TERASA SAKIT | S59: {=ifna(xlookup(L59,'🙎‍♂️ Pasien'!$G$5:$G1508,'🙎‍♂️ Pasien'!$U$5:$U1508),"")} -> SILAT | T59: TIDAK HADIR | U59: - | V59: BATAL HADIR | W59: TRUE
B60: SORE | C60: {=IFNA(XLOOKUP(J60,'⚙️ Pengaturan'!$H$5:$H1508,'⚙️ Pengaturan'!$I$5:$I1508),"")} -> TIM Y | D60: NOPI | E60: 45934 | F60: =IF($E60="","",TEXT($E60,"YYYY")) -> 2025 | G60: =IF($E60="","",TEXT($E60,"MM")&TEXT($E60,"MMM")) -> 10Okt | H60: =IF($E60="","",TEXT($E60,"DDDD")) -> Sabtu | I60: 16.00 | J60: WAHYU | K60: SESI TERAPI | L60: AFNUR RIKI AMRULLAH | M60: =IFNA(VLOOKUP(L60,'🙎‍♂️ Pasien'!G:V,2,FALSE),"") -> A9025092121 | N60: =IFNA(VLOOKUP(L60,'🙎‍♂️ Pasien'!G:L,3,FALSE),"") -> 36 | O60: =IFNA(VLOOKUP(L60,'🙎‍♂️ Pasien'!G:V,6,FALSE),"") -> LAKI-LAKI | P60: =IFNA(VLOOKUP(L60,'🙎‍♂️ Pasien'!G:V,12,FALSE),"") -> ISLAM | Q60: =IFNA(VLOOKUP(L60:L1508,'🙎‍♂️ Pasien'!G:V,13,FALSE),"") -> WIRASWASTA | R60: {=ifna(xlookup(L60,'🙎‍♂️ Pasien'!$G$5:$G1508,'🙎‍♂️ Pasien'!$T$5:$T1508),"")} -> PINGGANG KECETIT | S60: {=ifna(xlookup(L60,'🙎‍♂️ Pasien'!$G$5:$G1508,'🙎‍♂️ Pasien'!$U$5:$U1508),"")} -> - | T60: HADIR | U60: - | W60: TRUE
B61: SORE | C61: {=IFNA(XLOOKUP(J61,'⚙️ Pengaturan'!$H$5:$H1508,'⚙️ Pengaturan'!$I$5:$I1508),"")} -> TIM A | D61: NOPI | E61: 45934 | F61: =IF($E61="","",TEXT($E61,"YYYY")) -> 2025 | G61: =IF($E61="","",TEXT($E61,"MM")&TEXT($E61,"MMM")) -> 10Okt | H61: =IF($E61="","",TEXT($E61,"DDDD")) -> Sabtu | I61: 16.00 | J61: HENA | K61: PAKET TERAPI | L61: RUDI HARTONO | M61: =IFNA(VLOOKUP(L61,'🙎‍♂️ Pasien'!G:V,2,FALSE),"") -> R2525091389 | N61: =IFNA(VLOOKUP(L61,'🙎‍♂️ Pasien'!G:L,3,FALSE),"") -> 1 | O61: =IFNA(VLOOKUP(L61,'🙎‍♂️ Pasien'!G:V,6,FALSE),"") -> LAKI-LAKI | P61: =IFNA(VLOOKUP(L61,'🙎‍♂️ Pasien'!G:V,12,FALSE),"") -> PROTESTAN | Q61: =IFNA(VLOOKUP(L61:L1508,'🙎‍♂️ Pasien'!G:V,13,FALSE),"") -> KARYAWAN | R61: {=ifna(xlookup(L61,'🙎‍♂️ Pasien'!$G$5:$G1508,'🙎‍♂️ Pasien'!$T$5:$T1508),"")} -> FROZEN SHOULDER | S61: {=ifna(xlookup(L61,'🙎‍♂️ Pasien'!$G$5:$G1508,'🙎‍♂️ Pasien'!$U$5:$U1508),"")} -> TIDAK BISA MAIN BADMINTON | T61: HADIR | U61: 2 | W61: TRUE
B62: SORE | C62: {=IFNA(XLOOKUP(J62,'⚙️ Pengaturan'!$H$5:$H1508,'⚙️ Pengaturan'!$I$5:$I1508),"")} -> TIM A | D62: NOPI | E62: 45934 | F62: =IF($E62="","",TEXT($E62,"YYYY")) -> 2025 | G62: =IF($E62="","",TEXT($E62,"MM")&TEXT($E62,"MMM")) -> 10Okt | H62: =IF($E62="","",TEXT($E62,"DDDD")) -> Sabtu | I62: 17.00 | J62: OKTA | K62: PAKET TERAPI | L62: ATIKA MUFLIHA | M62: =IFNA(VLOOKUP(L62,'🙎‍♂️ Pasien'!G:V,2,FALSE),"") -> A9725086020 | N62: =IFNA(VLOOKUP(L62,'🙎‍♂️ Pasien'!G:L,3,FALSE),"") -> 28 | O62: =IFNA(VLOOKUP(L62,'🙎‍♂️ Pasien'!G:V,6,FALSE),"") -> PEREMPUAN | P62: =IFNA(VLOOKUP(L62,'🙎‍♂️ Pasien'!G:V,12,FALSE),"") -> ISLAM | Q62: =IFNA(VLOOKUP(L62:L1508,'🙎‍♂️ Pasien'!G:V,13,FALSE),"") -> PNS | R62: {=ifna(xlookup(L62,'🙎‍♂️ Pasien'!$G$5:$G1508,'🙎‍♂️ Pasien'!$T$5:$T1508),"")} -> SAKIT BAGIAN PAHA DAN PANGGUL | S62: {=ifna(xlookup(L62,'🙎‍♂️ Pasien'!$G$5:$G1508,'🙎‍♂️ Pasien'!$U$5:$U1508),"")} -> VOLI DAN BEKERJA | T62: HADIR | U62: 3 | W62: TRUE
B63: SORE | C63: {=IFNA(XLOOKUP(J63,'⚙️ Pengaturan'!$H$5:$H1508,'⚙️ Pengaturan'!$I$5:$I1508),"")} -> TIM A | D63: NOPI | E63: 45934 | F63: =IF($E63="","",TEXT($E63,"YYYY")) -> 2025 | G63: =IF($E63="","",TEXT($E63,"MM")&TEXT($E63,"MMM")) -> 10Okt | H63: =IF($E63="","",TEXT($E63,"DDDD")) -> Sabtu | I63: 19.00 | J63: HESTI | K63: TERAPI AWAL | L63: AMARA PUTRI NAZARISKA | M63: =IFNA(VLOOKUP(L63,'🙎‍♂️ Pasien'!G:V,2,FALSE),"") -> A0925107929 | N63: =IFNA(VLOOKUP(L63,'🙎‍♂️ Pasien'!G:L,3,FALSE),"") -> 16 | O63: =IFNA(VLOOKUP(L63,'🙎‍♂️ Pasien'!G:V,6,FALSE),"") -> PEREMPUAN | P63: =IFNA(VLOOKUP(L63,'🙎‍♂️ Pasien'!G:V,12,FALSE),"") -> ISLAM | Q63: =IFNA(VLOOKUP(L63:L1508,'🙎‍♂️ Pasien'!G:V,13,FALSE),"") -> PELAJAR | R63: {=ifna(xlookup(L63,'🙎‍♂️ Pasien'!$G$5:$G1508,'🙎‍♂️ Pasien'!$T$5:$T1508),"")} -> SAYA MERASA KAKI SAYA PANJANG SEBELAH, KALO BERDIRI LAMA ITU KAKI SAKIT SEBELAH | S63: {=ifna(xlookup(L63,'🙎‍♂️ Pasien'!$G$5:$G1508,'🙎‍♂️ Pasien'!$U$5:$U1508),"")} -> SAYA RASA TIDAK ADA | T63: HADIR | U63: - | W63: TRUE
B64: SORE | C64: {=IFNA(XLOOKUP(J64,'⚙️ Pengaturan'!$H$5:$H1508,'⚙️ Pengaturan'!$I$5:$I1508),"")} -> TIM A | D64: NOPI | E64: 45934 | F64: =IF($E64="","",TEXT($E64,"YYYY")) -> 2025 | G64: =IF($E64="","",TEXT($E64,"MM")&TEXT($E64,"MMM")) -> 10Okt | H64: =IF($E64="","",TEXT($E64,"DDDD")) -> Sabtu | I64: 19.00 | J64: HENA | K64: PAKET TERAPI | L64: YUNI ISHAFIZA | M64: =IFNA(VLOOKUP(L64,'🙎‍♂️ Pasien'!G:V,2,FALSE),"") -> Y6625092191 | N64: =IFNA(VLOOKUP(L64,'🙎‍♂️ Pasien'!G:L,3,FALSE),"") -> 59 | O64: =IFNA(VLOOKUP(L64,'🙎‍♂️ Pasien'!G:V,6,FALSE),"") -> PEREMPUAN | P64: =IFNA(VLOOKUP(L64,'🙎‍♂️ Pasien'!G:V,12,FALSE),"") -> ISLAM | Q64: =IFNA(VLOOKUP(L64:L1508,'🙎‍♂️ Pasien'!G:V,13,FALSE),"") -> PENSIUNAN PNS | R64: {=ifna(xlookup(L64,'🙎‍♂️ Pasien'!$G$5:$G1508,'🙎‍♂️ Pasien'!$T$5:$T1508),"")} -> KAKI KIRI SAKIT, NYER JUGA NGILU KARENA HABIS TABRAKAN | S64: {=ifna(xlookup(L64,'🙎‍♂️ Pasien'!$G$5:$G1508,'🙎‍♂️ Pasien'!$U$5:$U1508),"")} -> HARI JUMAT KEMARIN HABIS TABRAKAN | T64: HADIR | U64: 2 | W64: TRUE
B65: SORE | C65: {=IFNA(XLOOKUP(J65,'⚙️ Pengaturan'!$H$5:$H1508,'⚙️ Pengaturan'!$I$5:$I1508),"")} -> TIM Y | D65: NOPI | E65: 45934 | F65: =IF($E65="","",TEXT($E65,"YYYY")) -> 2025 | G65: =IF($E65="","",TEXT($E65,"MM")&TEXT($E65,"MMM")) -> 10Okt | H65: =IF($E65="","",TEXT($E65,"DDDD")) -> Sabtu | I65: 20.00 | J65: WAHYU | K65: PAKET TERAPI | L65: SUHERMAN | M65: =IFNA(VLOOKUP(L65,'🙎‍♂️ Pasien'!G:V,2,FALSE),"") -> S7625091177 | N65: =IFNA(VLOOKUP(L65,'🙎‍♂️ Pasien'!G:L,3,FALSE),"") -> 49 | O65: =IFNA(VLOOKUP(L65,'🙎‍♂️ Pasien'!G:V,6,FALSE),"") -> LAKI-LAKI | P65: =IFNA(VLOOKUP(L65,'🙎‍♂️ Pasien'!G:V,12,FALSE),"") -> ISLAM | Q65: =IFNA(VLOOKUP(L65:L1508,'🙎‍♂️ Pasien'!G:V,13,FALSE),"") -> WIRASWASTA | R65: {=ifna(xlookup(L65,'🙎‍♂️ Pasien'!$G$5:$G1508,'🙎‍♂️ Pasien'!$T$5:$T1508),"")} -> CEDERA LUTUT | S65: {=ifna(xlookup(L65,'🙎‍♂️ Pasien'!$G$5:$G1508,'🙎‍♂️ Pasien'!$U$5:$U1508),"")} -> MAIN BADMINTON | T65: HADIR | U65: 3 | W65: TRUE
B66: PAGI | C66: {=IFNA(XLOOKUP(J66,'⚙️ Pengaturan'!$H$5:$H1508,'⚙️ Pengaturan'!$I$5:$I1508),"")} -> MANAJEMEN | D66: NOPI | E66: 45935 | F66: =IF($E66="","",TEXT($E66,"YYYY")) -> 2025 | G66: =IF($E66="","",TEXT($E66,"MM")&TEXT($E66,"MMM")) -> 10Okt | H66: =IF($E66="","",TEXT($E66,"DDDD")) -> Minggu | I66: 09.00 | J66: DANI | K66: PAKET TERAPI | L66: AGNES VERONIKA | M66: =IFNA(VLOOKUP(L66,'🙎‍♂️ Pasien'!G:V,2,FALSE),"") -> A9224038209 | N66: =IFNA(VLOOKUP(L66,'🙎‍♂️ Pasien'!G:L,3,FALSE),"") -> 33 | O66: =IFNA(VLOOKUP(L66,'🙎‍♂️ Pasien'!G:V,6,FALSE),"") -> PEREMPUAN | P66: =IFNA(VLOOKUP(L66,'🙎‍♂️ Pasien'!G:V,12,FALSE),"") -> KATOLIK | Q66: =IFNA(VLOOKUP(L66:L1508,'🙎‍♂️ Pasien'!G:V,13,FALSE),"") -> SWASTA | R66: {=ifna(xlookup(L66,'🙎‍♂️ Pasien'!$G$5:$G1508,'🙎‍♂️ Pasien'!$T$5:$T1508),"")} -> Kaki kiri sakit, bahu dan punggung kiri sakit, leher agak bungkuk | S66: {=ifna(xlookup(L66,'🙎‍♂️ Pasien'!$G$5:$G1508,'🙎‍♂️ Pasien'!$U$5:$U1508),"")} -> Olahraga, kerja, dan mengurus anak | T66: TIDAK HADIR | U66: 1 | V66: TAGIH PAKET BARU/ADA EVENT LARI | W66: TRUE
B67: PAGI | C67: {=IFNA(XLOOKUP(J67,'⚙️ Pengaturan'!$H$5:$H1508,'⚙️ Pengaturan'!$I$5:$I1508),"")} -> TIM A | D67: NOPI | E67: 45935 | F67: =IF($E67="","",TEXT($E67,"YYYY")) -> 2025 | G67: =IF($E67="","",TEXT($E67,"MM")&TEXT($E67,"MMM")) -> 10Okt | H67: =IF($E67="","",TEXT($E67,"DDDD")) -> Minggu | I67: 10.00 | J67: OKTA | K67: PAKET TERAPI | L67: ANDRIANI | M67: =IFNA(VLOOKUP(L67,'🙎‍♂️ Pasien'!G:V,2,FALSE),"") -> A5625092572 | N67: =IFNA(VLOOKUP(L67,'🙎‍♂️ Pasien'!G:L,3,FALSE),"") -> 69 | O67: =IFNA(VLOOKUP(L67,'🙎‍♂️ Pasien'!G:V,6,FALSE),"") -> PEREMPUAN | P67: =IFNA(VLOOKUP(L67,'🙎‍♂️ Pasien'!G:V,12,FALSE),"") -> ISLAM | Q67: =IFNA(VLOOKUP(L67:L1508,'🙎‍♂️ Pasien'!G:V,13,FALSE),"") -> IRT | R67: {=ifna(xlookup(L67,'🙎‍♂️ Pasien'!$G$5:$G1508,'🙎‍♂️ Pasien'!$T$5:$T1508),"")} -> PINGGANG DAN KAKI | S67: {=ifna(xlookup(L67,'🙎‍♂️ Pasien'!$G$5:$G1508,'🙎‍♂️ Pasien'!$U$5:$U1508),"")} -> - | T67: HADIR | U67: 4 | V67: PELUNASAN 250K | W67: TRUE
B68: PAGI | C68: {=IFNA(XLOOKUP(J68,'⚙️ Pengaturan'!$H$5:$H1508,'⚙️ Pengaturan'!$I$5:$I1508),"")} -> TIM A | D68: NOPI | E68: 45935 | F68: =IF($E68="","",TEXT($E68,"YYYY")) -> 2025 | G68: =IF($E68="","",TEXT($E68,"MM")&TEXT($E68,"MMM")) -> 10Okt | H68: =IF($E68="","",TEXT($E68,"DDDD")) -> Minggu | I68: 11.00 | J68: HENA | K68: SESI TERAPI | L68: AYDA RIANI JOHAR | M68: =IFNA(VLOOKUP(L68,'🙎‍♂️ Pasien'!G:V,2,FALSE),"") -> A0025068439 | N68: =IFNA(VLOOKUP(L68,'🙎‍♂️ Pasien'!G:L,3,FALSE),"") -> 25 | O68: =IFNA(VLOOKUP(L68,'🙎‍♂️ Pasien'!G:V,6,FALSE),"") -> PEREMPUAN | P68: =IFNA(VLOOKUP(L68,'🙎‍♂️ Pasien'!G:V,12,FALSE),"") -> BUDDHA | Q68: =IFNA(VLOOKUP(L68:L1508,'🙎‍♂️ Pasien'!G:V,13,FALSE),"") -> PEKERJA LEPAS/ FREELANCE | R68: {=ifna(xlookup(L68,'🙎‍♂️ Pasien'!$G$5:$G1508,'🙎‍♂️ Pasien'!$T$5:$T1508),"")} -> LUTUT SAKIT KARENA SALAH SQUAD/ JONGKOK DI OLAHRAGA/ GYM. | S68: {=ifna(xlookup(L68,'🙎‍♂️ Pasien'!$G$5:$G1508,'🙎‍♂️ Pasien'!$U$5:$U1508),"")} -> OLAHRAGA FITNESS/ GYM, MENYETIR MOBIL (KEGIATAN YANG SERING MENGGUNAKAN KAKI KANAN) | T68: HADIR | U68: 1 | W68: TRUE
B69: PAGI | C69: {=IFNA(XLOOKUP(J69,'⚙️ Pengaturan'!$H$5:$H1508,'⚙️ Pengaturan'!$I$5:$I1508),"")} -> TIM A | D69: NOPI | E69: 45935 | F69: =IF($E69="","",TEXT($E69,"YYYY")) -> 2025 | G69: =IF($E69="","",TEXT($E69,"MM")&TEXT($E69,"MMM")) -> 10Okt | H69: =IF($E69="","",TEXT($E69,"DDDD")) -> Minggu | I69: 11.00 | J69: HESTI | K69: PAKET TERAPI | L69: LENI DIANTAMI | M69: =IFNA(VLOOKUP(L69,'🙎‍♂️ Pasien'!G:V,2,FALSE),"") -> L2525104585 | N69: =IFNA(VLOOKUP(L69,'🙎‍♂️ Pasien'!G:L,3,FALSE),"") -> 0 | O69: =IFNA(VLOOKUP(L69,'🙎‍♂️ Pasien'!G:V,6,FALSE),"") -> PEREMPUAN | P69: =IFNA(VLOOKUP(L69,'🙎‍♂️ Pasien'!G:V,12,FALSE),"") -> ISLAM | Q69: =IFNA(VLOOKUP(L69:L1508,'🙎‍♂️ Pasien'!G:V,13,FALSE),"") -> ANGGOTA DPRD KOTA PONTIANAK | R69: {=ifna(xlookup(L69,'🙎‍♂️ Pasien'!$G$5:$G1508,'🙎‍♂️ Pasien'!$T$5:$T1508),"")} -> CEDERA BAHU | S69: {=ifna(xlookup(L69,'🙎‍♂️ Pasien'!$G$5:$G1508,'🙎‍♂️ Pasien'!$U$5:$U1508),"")} -> GYM | T69: HADIR | U69: 1 | W69: TRUE
B70: PAGI | C70: {=IFNA(XLOOKUP(J70,'⚙️ Pengaturan'!$H$5:$H1508,'⚙️ Pengaturan'!$I$5:$I1508),"")} -> TIM A | D70: NOPI | E70: 45935 | F70: =IF($E70="","",TEXT($E70,"YYYY")) -> 2025 | G70: =IF($E70="","",TEXT($E70,"MM")&TEXT($E70,"MMM")) -> 10Okt | H70: =IF($E70="","",TEXT($E70,"DDDD")) -> Minggu | I70: 13.00 | J70: HESTI | K70: PAKET TERAPI | L70: DEVIN PANGESTU | M70: =IFNA(VLOOKUP(L70,'🙎‍♂️ Pasien'!G:V,2,FALSE),"") -> D1025091558 | N70: =IFNA(VLOOKUP(L70,'🙎‍♂️ Pasien'!G:L,3,FALSE),"") -> 16 | O70: =IFNA(VLOOKUP(L70,'🙎‍♂️ Pasien'!G:V,6,FALSE),"") -> LAKI-LAKI | P70: =IFNA(VLOOKUP(L70,'🙎‍♂️ Pasien'!G:V,12,FALSE),"") -> PROTESTAN | Q70: =IFNA(VLOOKUP(L70:L1508,'🙎‍♂️ Pasien'!G:V,13,FALSE),"") -> MASI SEKOLAH | R70: {=ifna(xlookup(L70,'🙎‍♂️ Pasien'!$G$5:$G1508,'🙎‍♂️ Pasien'!$T$5:$T1508),"")} -> SAKIT DI BAGIAN LUTUT | S70: {=ifna(xlookup(L70,'🙎‍♂️ Pasien'!$G$5:$G1508,'🙎‍♂️ Pasien'!$U$5:$U1508),"")} -> BASKET | T70: HADIR | U70: 2 | W70: TRUE
B71: PAGI | C71: {=IFNA(XLOOKUP(J71,'⚙️ Pengaturan'!$H$5:$H1508,'⚙️ Pengaturan'!$I$5:$I1508),"")} -> TIM A | D71: NOPI | E71: 45935 | F71: =IF($E71="","",TEXT($E71,"YYYY")) -> 2025 | G71: =IF($E71="","",TEXT($E71,"MM")&TEXT($E71,"MMM")) -> 10Okt | H71: =IF($E71="","",TEXT($E71,"DDDD")) -> Minggu | I71: 13.00 | J71: OKTA | K71: PAKET/SESI | L71: SHAOUQI NASHUHA | M71: =IFNA(VLOOKUP(L71,'🙎‍♂️ Pasien'!G:V,2,FALSE),"") -> S9625108010 | N71: =IFNA(VLOOKUP(L71,'🙎‍♂️ Pasien'!G:L,3,FALSE),"") -> 29 | O71: =IFNA(VLOOKUP(L71,'🙎‍♂️ Pasien'!G:V,6,FALSE),"") -> LAKI-LAKI | P71: =IFNA(VLOOKUP(L71,'🙎‍♂️ Pasien'!G:V,12,FALSE),"") -> ISLAM | Q71: =IFNA(VLOOKUP(L71:L1508,'🙎‍♂️ Pasien'!G:V,13,FALSE),"") -> MARKETING | R71: {=ifna(xlookup(L71,'🙎‍♂️ Pasien'!$G$5:$G1508,'🙎‍♂️ Pasien'!$T$5:$T1508),"")} -> ANKLE SPRAIN | S71: {=ifna(xlookup(L71,'🙎‍♂️ Pasien'!$G$5:$G1508,'🙎‍♂️ Pasien'!$U$5:$U1508),"")} -> TENNIS | T71: TIDAK HADIR | U71: - | V71: TIDAK ADA KONFRMASI | W71: TRUE
B72: PAGI | C72: {=IFNA(XLOOKUP(J72,'⚙️ Pengaturan'!$H$5:$H1508,'⚙️ Pengaturan'!$I$5:$I1508),"")} -> TIM A | D72: NOPI | E72: 45935 | F72: =IF($E72="","",TEXT($E72,"YYYY")) -> 2025 | G72: =IF($E72="","",TEXT($E72,"MM")&TEXT($E72,"MMM")) -> 10Okt | H72: =IF($E72="","",TEXT($E72,"DDDD")) -> Minggu | I72: 13.00 | J72: HENA | K72: TERAPI AWAL | L72: TITIN MARIANTI S.PDI | M72: =IFNA(VLOOKUP(L72,'🙎‍♂️ Pasien'!G:V,2,FALSE),"") -> T6625103145 | N72: =IFNA(VLOOKUP(L72,'🙎‍♂️ Pasien'!G:L,3,FALSE),"") -> 59 | O72: =IFNA(VLOOKUP(L72,'🙎‍♂️ Pasien'!G:V,6,FALSE),"") -> PEREMPUAN | P72: =IFNA(VLOOKUP(L72,'🙎‍♂️ Pasien'!G:V,12,FALSE),"") -> ISLAM | Q72: =IFNA(VLOOKUP(L72:L1508,'🙎‍♂️ Pasien'!G:V,13,FALSE),"") -> PNS | R72: {=ifna(xlookup(L72,'🙎‍♂️ Pasien'!$G$5:$G1508,'🙎‍♂️ Pasien'!$T$5:$T1508),"")} -> LEHER | S72: {=ifna(xlookup(L72,'🙎‍♂️ Pasien'!$G$5:$G1508,'🙎‍♂️ Pasien'!$U$5:$U1508),"")} -> - | T72: HADIR | U72: - | W72: TRUE
B73: PAGI | C73: {=IFNA(XLOOKUP(J73,'⚙️ Pengaturan'!$H$5:$H1508,'⚙️ Pengaturan'!$I$5:$I1508),"")} -> TIM A | D73: NOPI | E73: 45935 | F73: =IF($E73="","",TEXT($E73,"YYYY")) -> 2025 | G73: =IF($E73="","",TEXT($E73,"MM")&TEXT($E73,"MMM")) -> 10Okt | H73: =IF($E73="","",TEXT($E73,"DDDD")) -> Minggu | I73: 14.00 | J73: HESTI | K73: PAKET TERAPI | L73: DEVIN PANGESTU | M73: =IFNA(VLOOKUP(L73,'🙎‍♂️ Pasien'!G:V,2,FALSE),"") -> D1025091558 | N73: =IFNA(VLOOKUP(L73,'🙎‍♂️ Pasien'!G:L,3,FALSE),"") -> 16 | O73: =IFNA(VLOOKUP(L73,'🙎‍♂️ Pasien'!G:V,6,FALSE),"") -> LAKI-LAKI | P73: =IFNA(VLOOKUP(L73,'🙎‍♂️ Pasien'!G:V,12,FALSE),"") -> PROTESTAN | Q73: =IFNA(VLOOKUP(L73:L1508,'🙎‍♂️ Pasien'!G:V,13,FALSE),"") -> MASI SEKOLAH | R73: {=ifna(xlookup(L73,'🙎‍♂️ Pasien'!$G$5:$G1508,'🙎‍♂️ Pasien'!$T$5:$T1508),"")} -> SAKIT DI BAGIAN LUTUT | S73: {=ifna(xlookup(L73,'🙎‍♂️ Pasien'!$G$5:$G1508,'🙎‍♂️ Pasien'!$U$5:$U1508),"")} -> BASKET | T73: HADIR | U73: 3 | W73: TRUE
B74: SORE | C74: {=IFNA(XLOOKUP(J74,'⚙️ Pengaturan'!$H$5:$H1508,'⚙️ Pengaturan'!$I$5:$I1508),"")} -> TIM Y | D74: SUCI | E74: 45935 | F74: =IF($E74="","",TEXT($E74,"YYYY")) -> 2025 | G74: =IF($E74="","",TEXT($E74,"MM")&TEXT($E74,"MMM")) -> 10Okt | H74: =IF($E74="","",TEXT($E74,"DDDD")) -> Minggu | I74: 15.00 | J74: PRITY | K74: PAKET TERAPI | L74: DIVO | M74: =IFNA(VLOOKUP(L74,'🙎‍♂️ Pasien'!G:V,2,FALSE),"") -> D0925034440 | N74: =IFNA(VLOOKUP(L74,'🙎‍♂️ Pasien'!G:L,3,FALSE),"") -> 17 | O74: =IFNA(VLOOKUP(L74,'🙎‍♂️ Pasien'!G:V,6,FALSE),"") -> LAKI-LAKI | P74: =IFNA(VLOOKUP(L74,'🙎‍♂️ Pasien'!G:V,12,FALSE),"") -> KATOLIK | Q74: =IFNA(VLOOKUP(L74:L1508,'🙎‍♂️ Pasien'!G:V,13,FALSE),"") -> PELAJAR | R74: {=ifna(xlookup(L74,'🙎‍♂️ Pasien'!$G$5:$G1508,'🙎‍♂️ Pasien'!$T$5:$T1508),"")} -> TANGAN KANAN DAN KIRI KURANG LURUS DARI LAHIR | S74: {=ifna(xlookup(L74,'🙎‍♂️ Pasien'!$G$5:$G1508,'🙎‍♂️ Pasien'!$U$5:$U1508),"")} -> JOGING | T74: HADIR | U74: 2 | W74: TRUE
B75: SORE | C75: {=IFNA(XLOOKUP(J75,'⚙️ Pengaturan'!$H$5:$H1508,'⚙️ Pengaturan'!$I$5:$I1508),"")} -> TIM Y | D75: SUCI | E75: 45935 | F75: =IF($E75="","",TEXT($E75,"YYYY")) -> 2025 | G75: =IF($E75="","",TEXT($E75,"MM")&TEXT($E75,"MMM")) -> 10Okt | H75: =IF($E75="","",TEXT($E75,"DDDD")) -> Minggu | I75: 16.00 | J75: PRITY | K75: PAKET TERAPI | L75: MARTINI | M75: =IFNA(VLOOKUP(L75,'🙎‍♂️ Pasien'!G:V,2,FALSE),"") -> M7225080167 | N75: =IFNA(VLOOKUP(L75,'🙎‍♂️ Pasien'!G:L,3,FALSE),"") -> 54 | O75: =IFNA(VLOOKUP(L75,'🙎‍♂️ Pasien'!G:V,6,FALSE),"") -> PEREMPUAN | P75: =IFNA(VLOOKUP(L75,'🙎‍♂️ Pasien'!G:V,12,FALSE),"") -> ISLAM | Q75: =IFNA(VLOOKUP(L75:L1508,'🙎‍♂️ Pasien'!G:V,13,FALSE),"") -> PNS | R75: {=ifna(xlookup(L75,'🙎‍♂️ Pasien'!$G$5:$G1508,'🙎‍♂️ Pasien'!$T$5:$T1508),"")} -> CTS PADA TANGAN KIRI | S75: {=ifna(xlookup(L75,'🙎‍♂️ Pasien'!$G$5:$G1508,'🙎‍♂️ Pasien'!$U$5:$U1508),"")} -> NGETIK , MASAK, NYETIR | T75: TIDAK HADIR | U75: 5 | V75: ADA KEGIATAN DADAKAN | W75: TRUE
B76: SORE | C76: {=IFNA(XLOOKUP(J76,'⚙️ Pengaturan'!$H$5:$H1508,'⚙️ Pengaturan'!$I$5:$I1508),"")} -> TIM Y | D76: SUCI | E76: 45935 | F76: =IF($E76="","",TEXT($E76,"YYYY")) -> 2025 | G76: =IF($E76="","",TEXT($E76,"MM")&TEXT($E76,"MMM")) -> 10Okt | H76: =IF($E76="","",TEXT($E76,"DDDD")) -> Minggu | I76: 16.00 | J76: ORY | K76: SESI TERAPI | L76: MUHAMMAD NABHIL DHOYFULLOH | M76: =IFNA(VLOOKUP(L76,'🙎‍♂️ Pasien'!G:V,2,FALSE),"") -> M0524055808 | N76: =IFNA(VLOOKUP(L76,'🙎‍♂️ Pasien'!G:L,3,FALSE),"") -> 20 | O76: =IFNA(VLOOKUP(L76,'🙎‍♂️ Pasien'!G:V,6,FALSE),"") -> LAKI-LAKI | P76: =IFNA(VLOOKUP(L76,'🙎‍♂️ Pasien'!G:V,12,FALSE),"") -> ISLAM | Q76: =IFNA(VLOOKUP(L76:L1508,'🙎‍♂️ Pasien'!G:V,13,FALSE),"") -> PELAJAR/MAHASISWA | R76: {=ifna(xlookup(L76,'🙎‍♂️ Pasien'!$G$5:$G1508,'🙎‍♂️ Pasien'!$T$5:$T1508),"")} -> goyang | S76: {=ifna(xlookup(L76,'🙎‍♂️ Pasien'!$G$5:$G1508,'🙎‍♂️ Pasien'!$U$5:$U1508),"")} -> futsal | T76: HADIR | U76: - | W76: TRUE
